Workbook

Sheet Prioritization
B1: Company Target Prioritization
B2: Industry | C2: Average Grading | D2: Average grading if willing to use 3rd Party | I2: Phase 1 | J2: Low data maturity, limited data exchange
B3: Manufacturer | C3: =SUMIF(Table1[Industry],B3,Table1[Grade])/COUNTIF(Table1[Industry],B3) -> 5.8 | D3: =IFERROR(SUMIFS(Table1[Grade],Table1[Industry],B3,Table1[Third Party],">3")/COUNTIFS(Table1[Industry],B3,Table1[Third Party],">3"),"") -> 7.5 | I3: Phase 2 | J3: Medium data maturity, some data exchange
B4: Specialty Retail | C4: =SUMIF(Table1[Industry],B4,Table1[Grade])/COUNTIF(Table1[Industry],B4) -> 5.8333333 | D4: =IFERROR(SUMIFS(Table1[Grade],Table1[Industry],B4,Table1[Third Party],">3")/COUNTIFS(Table1[Industry],B4,Table1[Third Party],">3"),"") -> 8 | I4: Phase 3 | J4: High data maturity, existing data exchange
B5: Wholesaler | C5: =SUMIF(Table1[Industry],B5,Table1[Grade])/COUNTIF(Table1[Industry],B5) -> 4.5 | D5: =IFERROR(SUMIFS(Table1[Grade],Table1[Industry],B5,Table1[Third Party],">3")/COUNTIFS(Table1[Industry],B5,Table1[Third Party],">3"),"") -> 5
B6: Retailer | C6: =SUMIF(Table1[Industry],B6,Table1[Grade])/COUNTIF(Table1[Industry],B6) -> 3 | D6: =IFERROR(SUMIFS(Table1[Grade],Table1[Industry],B6,Table1[Third Party],">3")/COUNTIFS(Table1[Industry],B6,Table1[Third Party],">3"),"")
D8: 1=Low maturity | E8: 5=high maturity | G8: 0-10
B9: Company | C9: Industry | D9: Data Maturity | E9: Collaboration | F9: Third Party | G9: Grade | H9: Notes | I9: Starting Phase | J9: Contact
B10: Dico Foods | C10: Manufacturer | D10: 1 | E10: 5 | F10: 5 | G10: 8.5 | I10: Phase 1
B11: Familia Pharmacies | C11: Specialty Retail | D11: 1 | E11: 5 | F11: 5 | G11: 8.5 | I11: Phase 1
B12: Spuntini | C12: Wholesaler | D12: 2 | E12: 5 | F12: 5 | G12: 8.5 | I12: Phase 2
B13: Tom & Co | C13: Specialty Retail | D13: 4 | E13: 4 | F13: 5 | G13: 7.5 | I13: Phase 2
B14: Edgard & Cooper | C14: Manufacturer | D14: 5 | E14: 3 | F14: 5 | G14: 7 | I14: Phase 3
B15: Wellness Pet | C15: Manufacturer | D15: 3 | E15: 5 | F15: 5 | G15: 7 | I15: Phase 1
B16: Arla | C16: Manufacturer | D16: 3 | E16: 5 | F16: 3 | G16: 6.5 | I16: Phase 2
B17: Conway | C17: Wholesaler | D17: 3 | E17: 5 | F17: 5 | G17: 5 | H17: Gondola wholesale market data | I17: No Go
B18: Solucious | C18: Wholesaler | D18: 5 | E18: 5 | F18: 3 | G18: 3 | H18: Piloting already with a company (Gondola? ) | I18: No Go
B19: Shell | C19: Specialty Retail | D19: 5 | E19: 1 | F19: 1 | G19: 1.5 | H19: Exited Nielsen data sharing 20 years ago | I19: No Go
B20: Hanos | C20: Wholesaler | D20: 3 | E20: 5 | F20: 5 | G20: 1.5 | H20: Limiting Company Policy | I20: No Go
B21: Spadel | C21: Manufacturer | D21: 5 | E21: 5 | F21: 1 | G21: 0 | H21: Limiting Company Policy | I21: No Go
B22: Lidl | C22: Retailer | D22: 5 | E22: 2 | F22: 3 | G22: 3 | H22: Limiting Company Policy | I22: Phase 2
C46: Target audience:
D47: 1) Standalone | F47: 1) Combined | I47: 1) Combined
D48: 2) Combined

Sheet Scores
A1: Tool Target Prioritization
F2: ='Analysis — Filter View'!E37 -> 17 | H2: Average Score by Industry | M2: Percentage by Industry
A3: Section | B3: Question ID | C3: Question | D3: Range | E3: Value | F3: % | H3: Manufacturer | I3: Specialty Retail | J3: Wholesaler | K3: Retailer | M3: Manufacturer | N3: Specialty Retail | O3: Wholesaler | P3: Retailer | Q3: Notes
A4: Baseline | B4: B1_INTEREST | C4: Interest (1–10) | D4: 0-1 | E4: {=TRANSPOSE('Analysis — Filter View'!H37:AP37)} -> 7.1923077 | H4: {=TRANSPOSE('Analysis — Filter View'!H38:AP38)} -> 8.4 | I4: {=TRANSPOSE('Analysis — Filter View'!H39:AP39)} -> 6 | J4: {=TRANSPOSE('Analysis — Filter View'!H40:AP40)} -> 7.625 | K4: {=TRANSPOSE('Analysis — Filter View'!H41:AP41)} -> 3 | Q4: Prioiritize Manufacturer > Wholesaer > Specialty Retailer > Retail
A5: Baseline | B5: B2_SHARING | C5: Shares data (0/1) | D5: 0-1 | E5: 13 | F5: =E5/$F$2 -> 0.76470588 | H5: 5 | I5: 3 | J5: 4 | K5: 1 | M5: =H5/'Analysis — Filter View'!$E$38 -> 1 | N5: =I5/'Analysis — Filter View'!$E$39 -> 1 | O5: =J5/'Analysis — Filter View'!$E$40 -> 1 | P5: =K5/'Analysis — Filter View'!$E$41 -> 1 | Q5: Everyone shares some sort of data in the market.
A6: Baseline | B6: B3_MONETIZE | C6: Monetizes data (0/1) | D6: 0-1 | E6: 4 | F6: =E6/$F$2 -> 0.23529412 | H6: 0 | I6: 1 | J6: 3 | K6: 0 | M6: =H6/'Analysis — Filter View'!$E$38 -> 0 | N6: =I6/'Analysis — Filter View'!$E$39 -> 0.33333333 | O6: =J6/'Analysis — Filter View'!$E$40 -> 0.75 | P6: =K6/'Analysis — Filter View'!$E$41 -> 0 | Q6: Data monetization is a critical strategic choice for retail and manufacturers, and some specialty retailers
A7: Baseline | B7: B4_STRATEGIC | C7: Strategic reasons (0/1) | D7: 0-1 | E7: 7 | F7: =E7/$F$2 -> 0.41176471 | H7: 3 | I7: 1 | J7: 2 | K7: 1 | M7: =H7/'Analysis — Filter View'!$E$38 -> 0.6 | N7: =I7/'Analysis — Filter View'!$E$39 -> 0.33333333 | O7: =J7/'Analysis — Filter View'!$E$40 -> 0.5 | P7: =K7/'Analysis — Filter View'!$E$41 -> 1 | Q7: Data sharing is a strategic choice.
A8: Maturity | B8: M1_AUTOMATED | C8: Automated vs manual | D8: 0-5 | E8: 2.7272727 | H8: 3 | I8: 1.3333333 | J8: 2.75 | K8: 0
A9: Maturity | B9: M2_REALTIME | C9: Real-time vs lagging | D9: 0-5 | E9: 2.3636364 | H9: 2.6 | I9: 1 | J9: 2.5 | K9: 0
A10: Maturity | B10: M3_STRATEGIC | C10: Ops vs strategic focus | D10: 0-5 | E10: 3.2307692 | H10: 3.8 | I10: 1.6666667 | J10: 4 | K10: 2
A11: Maturity | B11: M4_BREADTH | C11: All clients vs selective | D11: 0-5 | E11: 2.6153846 | H11: 3.2 | I11: 1.6666667 | J11: 3 | K11: 1
A12: Maturity | B12: M5_DATATYPES | C12: Breadth of data | D12: 0-5 | E12: 3.2307692 | H12: 4 | I12: 1.6666667 | J12: 3.75 | K12: 2
A13: Maturity | B13: M6_TRUST | C13: Trust in data | D13: 0-5 | E13: 2.6666667 | H13: 2.6 | I13: 1.3333333 | J13: 1.75 | K13: 0
A14: Maturity | B14: M7_BARRIERS | C14: Readiness/barriers | D14: 0-5 | E14: 3.6153846 | H14: 4 | I14: 3.3333333 | J14: 3.25 | K14: 4
A15: Maturity | B15: M8_IMPACT | C15: Operational impact | D15: 0-5 | E15: 3.3333333 | H15: 3.2 | I15: 0 | J15: 2.5 | K15: 4 | Q15: The operational inefficiencies have higher impact (to be tested further) on the retail side > sell-in opportunities missed
A16: Maturity | B16: M9_WILLINGNESS | C16: Willingness (synthesis) | D16: 0-5 | E16: 6.9230769 | H16: 8 | I16: 5.6666667 | J16: 7.5 | K16: 3 | Q16: Manufacturers have higher willingness to collaborate on data & insights. Should be the primary contact to push for collaboration.
A17: Value Unlock | B17: SV1_PRICING | C17: Pricing | D17: 0-1 | E17: 7 | F17: =E17/$F$2 -> 0.41176471 | H17: 4 | I17: 1 | J17: 2 | K17: 0 | M17: =H17/'Analysis — Filter View'!$E$38 -> 0.8 | N17: =I17/'Analysis — Filter View'!$E$39 -> 0.33333333 | O17: =J17/'Analysis — Filter View'!$E$40 -> 0.5 | P17: =K17/'Analysis — Filter View'!$E$41 -> 0 | Q17: Value driver #5
A18: Value Unlock | B18: SV2_PROMOTIONS | C18: Promotions | D18: 0-1 | E18: 8 | F18: =E18/$F$2 -> 0.47058824 | H18: 4 | I18: 1 | J18: 2 | K18: 1 | M18: =H18/'Analysis — Filter View'!$E$38 -> 0.8 | N18: =I18/'Analysis — Filter View'!$E$39 -> 0.33333333 | O18: =J18/'Analysis — Filter View'!$E$40 -> 0.5 | P18: =K18/'Analysis — Filter View'!$E$41 -> 1 | Q18: Value driver #2
A19: Value Unlock | B19: SV3_SUPPLYCHAIN | C19: Supply Chain | D19: 0-1 | E19: 8 | F19: =E19/$F$2 -> 0.47058824 | H19: 4 | I19: 2 | J19: 1 | K19: 1 | M19: =H19/'Analysis — Filter View'!$E$38 -> 0.8 | N19: =I19/'Analysis — Filter View'!$E$39 -> 0.66666667 | O19: =J19/'Analysis — Filter View'!$E$40 -> 0.25 | P19: =K19/'Analysis — Filter View'!$E$41 -> 1 | Q19: Value driver #1
A20: Value Unlock | B20: SV4_CATEGORY | C20: Category Planning | D20: 0-1 | E20: 10 | F20: =E20/$F$2 -> 0.58823529 | H20: 4 | I20: 2 | J20: 4 | K20: 0 | M20: =H20/'Analysis — Filter View'!$E$38 -> 0.8 | N20: =I20/'Analysis — Filter View'!$E$39 -> 0.66666667 | O20: =J20/'Analysis — Filter View'!$E$40 -> 1 | P20: =K20/'Analysis — Filter View'!$E$41 -> 0 | Q20: Value driver #3
A21: Value Unlock | B21: SV5_DEMAND | C21: Demand Forecasting | D21: 0-1 | E21: 4 | F21: =E21/$F$2 -> 0.23529412 | H21: 2 | I21: 0 | J21: 1 | K21: 1 | M21: =H21/'Analysis — Filter View'!$E$38 -> 0.4 | N21: =I21/'Analysis — Filter View'!$E$39 -> 0 | O21: =J21/'Analysis — Filter View'!$E$40 -> 0.25 | P21: =K21/'Analysis — Filter View'!$E$41 -> 1 | Q21: Value driver #4
A22: Value Unlock | B22: SV6_ACCOUNT | C22: Accountability | D22: 0-1 | E22: 3 | F22: =E22/$F$2 -> 0.17647059 | H22: 2 | I22: 0 | J22: 1 | K22: 0 | M22: =H22/'Analysis — Filter View'!$E$38 -> 0.4 | N22: =I22/'Analysis — Filter View'!$E$39 -> 0 | O22: =J22/'Analysis — Filter View'!$E$40 -> 0.25 | P22: =K22/'Analysis — Filter View'!$E$41 -> 0 | Q22: Value driver #7
A23: Value Unlock | B23: SV7_OPS | C23: Operationalization | D23: 0-1 | E23: 5 | F23: =E23/$F$2 -> 0.29411765 | H23: 3 | I23: 0 | J23: 2 | K23: 0 | M23: =H23/'Analysis — Filter View'!$E$38 -> 0.6 | N23: =I23/'Analysis — Filter View'!$E$39 -> 0 | O23: =J23/'Analysis — Filter View'!$E$40 -> 0.5 | P23: =K23/'Analysis — Filter View'!$E$41 -> 0 | Q23: Value driver #6
A24: Concerns | B24: SC1_DATASENS | C24: Data Sensitivity | D24: 0-1 | E24: 12 | F24: =E24/$F$2 -> 0.70588235 | H24: 5 | I24: 3 | J24: 3 | K24: 1 | M24: =H24/'Analysis — Filter View'!$E$38 -> 1 | N24: =I24/'Analysis — Filter View'!$E$39 -> 1 | O24: =J24/'Analysis — Filter View'!$E$40 -> 0.75 | P24: =K24/'Analysis — Filter View'!$E$41 -> 1 | Q24: Concern #1
A25: Concerns | B25: SC2_COMPLIANCE | C25: Compliance | D25: 0-1 | E25: 8 | F25: =E25/$F$2 -> 0.47058824 | H25: 4 | I25: 1 | J25: 2 | K25: 1 | M25: =H25/'Analysis — Filter View'!$E$38 -> 0.8 | N25: =I25/'Analysis — Filter View'!$E$39 -> 0.33333333 | O25: =J25/'Analysis — Filter View'!$E$40 -> 0.5 | P25: =K25/'Analysis — Filter View'!$E$41 -> 1 | Q25: Concern #2
A26: Concerns | B26: SC3_TRUST | C26: Trust Issues | D26: 0-1 | E26: 5 | F26: =E26/$F$2 -> 0.29411765 | H26: 3 | I26: 0 | J26: 2 | K26: 0 | M26: =H26/'Analysis — Filter View'!$E$38 -> 0.6 | N26: =I26/'Analysis — Filter View'!$E$39 -> 0 | O26: =J26/'Analysis — Filter View'!$E$40 -> 0.5 | P26: =K26/'Analysis — Filter View'!$E$41 -> 0 | Q26: Concern #4
A27: Concerns | B27: SC4_DATAPROC | C27: Data Processing | D27: 0-1 | E27: 9 | F27: =E27/$F$2 -> 0.52941176 | H27: 4 | I27: 2 | J27: 3 | K27: 0 | M27: =H27/'Analysis — Filter View'!$E$38 -> 0.8 | N27: =I27/'Analysis — Filter View'!$E$39 -> 0.66666667 | O27: =J27/'Analysis — Filter View'!$E$40 -> 0.75 | P27: =K27/'Analysis — Filter View'!$E$41 -> 0 | Q27: Concern #3
A28: Tool Features | B28: SF1_REALTIME | C28: Real-time exchange | D28: 0-1 | E28: 5 | F28: =E28/$F$2 -> 0.29411765 | H28: 3 | I28: 0 | J28: 2 | K28: 0 | M28: =H28/'Analysis — Filter View'!$E$38 -> 0.6 | N28: =I28/'Analysis — Filter View'!$E$39 -> 0 | O28: =J28/'Analysis — Filter View'!$E$40 -> 0.5 | P28: =K28/'Analysis — Filter View'!$E$41 -> 0 | Q28: Feature #3
... A38: Datasets | B38: SD6_CONJOINT | C38: Conjoint names | D38: 0-1 | E38: 0 | F38: =E38/$F$2 -> 0 | H38: 0 | I38: 0 | J38: 0 | K38: 0 | M38: =H38/'Analysis — Filter View'!$E$38 -> 0 | N38: =I38/'Analysis — Filter View'!$E$39 -> 0 | O38: =J38/'Analysis — Filter View'!$E$40 -> 0 | P38: =K38/'Analysis — Filter View'!$E$41 -> 0 | Q38: Collab data #6

Sheet Analysis — Filter View
B1: Filter View — Companies as Rows
H2: Baseline | L2: Maturity | U2: Value Unlock | AB2: Concerns | AF2: Tool Features | AK2: Datasets
B3: Company | C3: Role | D3: Industry | E3: Sub-Industry | F3: Size | G3: Country | H3: Interest (1–10) | I3: Shares data (0/1) | J3: Monetizes data (0/1) | K3: Strategic reasons (0/1) | L3: Automated vs manual | M3: Real-time vs lagging | N3: Ops vs strategic focus | O3: All clients vs selective | P3: Breadth of data | Q3: Trust in data | R3: Readiness/barriers | S3: Operational impact | T3: Willingness (synthesis) | U3: Pricing | V3: Promotions | W3: Supply Chain | X3: Category Planning | Y3: Demand Forecasting | Z3: Accountability | AA3: Operationalization | AB3: Data Sensitivity | AC3: Compliance | AD3: Trust Issues | AE3: Data Processing | AF3: Real-time exchange | AG3: Equal access | AH3: Simple UX/UI | AI3: Joint decisions | AJ3: Masking rules | AK3: Global trends | AL3: Market research | AM3: Category perf. | AN3: Shipments | AO3: Lead times | AP3: Conjoint names
B4: Company 1 | C4: =IFERROR(VLOOKUP("Interviewee Position",'Company 1'!$B:$C,2,0),"") -> Chief of Staff | D4: =IFERROR(VLOOKUP("Company Industry",'Company 1'!$B:$C,2,0),"") -> Specialty Retail | E4: =IFERROR(VLOOKUP("Company Sub-Industry",'Company 1'!$B:$C,2,0),"") -> Specialty Retail | F4: =IFERROR(VLOOKUP("Company Size (Turnover)",'Company 1'!$B:$C,2,0),"") -> 160000000 | G4: =IFERROR(VLOOKUP("Country",'Company 1'!$B:$C,2,0),"") -> Belgium | H4: =IFERROR(VLOOKUP("B1_INTEREST",'Company 1'!$B:$E,4,0),"") -> 7 | I4: =IFERROR(VLOOKUP("B2_SHARING",'Company 1'!$B:$E,4,0),"") -> 1 | J4: =IFERROR(VLOOKUP("B3_MONETIZE",'Company 1'!$B:$E,4,0),"") -> 1 | K4: =IFERROR(VLOOKUP("B4_STRATEGIC",'Company 1'!$B:$E,4,0),"") -> 0 | L4: =IFERROR(VLOOKUP("M1_AUTOMATED",'Company 1'!$B:$E,4,0),"") -> 3 | M4: =IFERROR(VLOOKUP("M2_REALTIME",'Company 1'!$B:$E,4,0),"") -> 2 | N4: =IFERROR(VLOOKUP("M3_STRATEGIC",'Company 1'!$B:$E,4,0),"") -> 2 | O4: =IFERROR(VLOOKUP("M4_BREADTH",'Company 1'!$B:$E,4,0),"") -> 2 | P4: =IFERROR(VLOOKUP("M5_DATATYPES",'Company 1'!$B:$E,4,0),"") -> 2 | Q4: =IFERROR(VLOOKUP("M6_TRUST",'Company 1'!$B:$E,4,0),"") -> 4 | R4: =IFERROR(VLOOKUP("M7_BARRIERS",'Company 1'!$B:$E,4,0),"") -> 3 | S4: =IFERROR(VLOOKUP("M8_IMPACT",'Company 1'!$B:$E,4,0),"") -> 0 | T4: =IFERROR(VLOOKUP("M9_WILLINGNESS",'Company 1'!$B:$E,4,0),"") -> 6 | U4: =IFERROR(VLOOKUP("SV1_PRICING",'Company 1'!$B:$E,4,0),"") -> 0 | V4: =IFERROR(VLOOKUP("SV2_PROMOTIONS",'Company 1'!$B:$E,4,0),"") -> 0 | W4: =IFERROR(VLOOKUP("SV3_SUPPLYCHAIN",'Company 1'!$B:$E,4,0),"") -> 0 | X4: =IFERROR(VLOOKUP("SV4_CATEGORY",'Company 1'!$B:$E,4,0),"") -> 1 | Y4: =IFERROR(VLOOKUP("SV5_DEMAND",'Company 1'!$B:$E,4,0),"") -> 0 | Z4: =IFERROR(VLOOKUP("SV6_ACCOUNT",'Company 1'!$B:$E,4,0),"") -> 0 | AA4: =IFERROR(VLOOKUP("SV7_OPS",'Company 1'!$B:$E,4,0),"") -> 0 | AB4: =IFERROR(VLOOKUP("SC1_DATASENS",'Company 1'!$B:$E,4,0),"") -> 1 | AC4: =IFERROR(VLOOKUP("SC2_COMPLIANCE",'Company 1'!$B:$E,4,0),"") -> 0 | AD4: =IFERROR(VLOOKUP("SC3_TRUST",'Company 1'!$B:$E,4,0),"") -> 0 | AE4: =IFERROR(VLOOKUP("SC4_DATAPROC",'Company 1'!$B:$E,4,0),"") -> 0 | AF4: =IFERROR(VLOOKUP("SF1_REALTIME",'Company 1'!$B:$E,4,0),"") -> 0 | AG4: =IFERROR(VLOOKUP("SF2_ACCESS",'Company 1'!$B:$E,4,0),"") -> 0 | AH4: =IFERROR(VLOOKUP("SF3_UX",'Company 1'!$B:$E,4,0),"") -> 0 | AI4: =IFERROR(VLOOKUP("SF4_DECISION",'Company 1'!$B:$E,4,0),"") -> 0 | AJ4: =IFERROR(VLOOKUP("SF5_MASKING",'Company 1'!$B:$E,4,0),"") -> 1 | AK4: =IFERROR(VLOOKUP("SD1_TRENDS",'Company 1'!$B:$E,4,0),"") -> 1 | AL4: =IFERROR(VLOOKUP("SD2_MARKET",'Company 1'!$B:$E,4,0),"") -> 1 | AM4: =IFERROR(VLOOKUP("SD3_CATEGORY",'Company 1'!$B:$E,4,0),"") -> 1 | AN4: =IFERROR(VLOOKUP("SD4_SHIPMENT",'Company 1'!$B:$E,4,0),"") -> 0 | AO4: =IFERROR(VLOOKUP("SD5_LEAD",'Company 1'!$B:$E,4,0),"") -> 0 | AP4: =IFERROR(VLOOKUP("SD6_CONJOINT",'Company 1'!$B:$E,4,0),"") -> 0
B5: Company 2 | C5: =IFERROR(VLOOKUP("Interviewee Position",'Company 2'!$B:$C,2,0),"") -> President and Managing Director Belgian Shell | D5: =IFERROR(VLOOKUP("Company Industry",'Company 2'!$B:$C,2,0),"") -> Oil & Gas | E5: =IFERROR(VLOOKUP("Company Sub-Industry",'Company 2'!$B:$C,2,0),"") -> Specialty Retail | F5: =IFERROR(VLOOKUP("Company Size (Turnover)",'Company 2'!$B:$C,2,0),"") -> 2000000000 | G5: =IFERROR(VLOOKUP("Country",'Company 2'!$B:$C,2,0),"") -> UK | H5: =IFERROR(VLOOKUP("B1_INTEREST",'Company 2'!$B:$E,4,0),"") -> 2 | I5: =IFERROR(VLOOKUP("B2_SHARING",'Company 2'!$B:$E,4,0),"") -> 1 | J5: =IFERROR(VLOOKUP("B3_MONETIZE",'Company 2'!$B:$E,4,0),"") -> 0 | K5: =IFERROR(VLOOKUP("B4_STRATEGIC",'Company 2'!$B:$E,4,0),"") -> 1 | L5: =IFERROR(VLOOKUP("M1_AUTOMATED",'Company 2'!$B:$E,4,0),"") -> 0 | M5: =IFERROR(VLOOKUP("M2_REALTIME",'Company 2'!$B:$E,4,0),"") -> 0 | N5: =IFERROR(VLOOKUP("M3_STRATEGIC",'Company 2'!$B:$E,4,0),"") -> 1 | O5: =IFERROR(VLOOKUP("M4_BREADTH",'Company 2'!$B:$E,4,0),"") -> 1 | P5: =IFERROR(VLOOKUP("M5_DATATYPES",'Company 2'!$B:$E,4,0),"") -> 1 | Q5: =IFERROR(VLOOKUP("M6_TRUST",'Company 2'!$B:$E,4,0),"") -> 0 | R5: =IFERROR(VLOOKUP("M7_BARRIERS",'Company 2'!$B:$E,4,0),"") -> 5 | S5: =IFERROR(VLOOKUP("M8_IMPACT",'Company 2'!$B:$E,4,0),"") -> 0 | T5: =IFERROR(VLOOKUP("M9_WILLINGNESS",'Company 2'!$B:$E,4,0),"") -> 2 | U5: =IFERROR(VLOOKUP("SV1_PRICING",'Company 2'!$B:$E,4,0),"") -> 0 | V5: =IFERROR(VLOOKUP("SV2_PROMOTIONS",'Company 2'!$B:$E,4,0),"") -> 0 | W5: =IFERROR(VLOOKUP("SV3_SUPPLYCHAIN",'Company 2'!$B:$E,4,0),"") -> 1 | X5: =IFERROR(VLOOKUP("SV4_CATEGORY",'Company 2'!$B:$E,4,0),"") -> 0 | Y5: =IFERROR(VLOOKUP("SV5_DEMAND",'Company 2'!$B:$E,4,0),"") -> 0 | Z5: =IFERROR(VLOOKUP("SV6_ACCOUNT",'Company 2'!$B:$E,4,0),"") -> 0 | AA5: =IFERROR(VLOOKUP("SV7_OPS",'Company 2'!$B:$E,4,0),"") -> 0 | AB5: =IFERROR(VLOOKUP("SC1_DATASENS",'Company 2'!$B:$E,4,0),"") -> 1 | AC5: =IFERROR(VLOOKUP("SC2_COMPLIANCE",'Company 2'!$B:$E,4,0),"") -> 1 | AD5: =IFERROR(VLOOKUP("SC3_TRUST",'Company 2'!$B:$E,4,0),"") -> 0 | AE5: =IFERROR(VLOOKUP("SC4_DATAPROC",'Company 2'!$B:$E,4,0),"") -> 1 | AF5: =IFERROR(VLOOKUP("SF1_REALTIME",'Company 2'!$B:$E,4,0),"") -> 0 | AG5: =IFERROR(VLOOKUP("SF2_ACCESS",'Company 2'!$B:$E,4,0),"") -> 0 | AH5: =IFERROR(VLOOKUP("SF3_UX",'Company 2'!$B:$E,4,0),"") -> 0 | AI5: =IFERROR(VLOOKUP("SF4_DECISION",'Company 2'!$B:$E,4,0),"") -> 0 | AJ5: =IFERROR(VLOOKUP("SF5_MASKING",'Company 2'!$B:$E,4,0),"") -> 1 | AK5: =IFERROR(VLOOKUP("SD1_TRENDS",'Company 2'!$B:$E,4,0),"") -> 0 | AL5: =IFERROR(VLOOKUP("SD2_MARKET",'Company 2'!$B:$E,4,0),"") -> 1 | AM5: =IFERROR(VLOOKUP("SD3_CATEGORY",'Company 2'!$B:$E,4,0),"") -> 0 | AN5: =IFERROR(VLOOKUP("SD4_SHIPMENT",'Company 2'!$B:$E,4,0),"") -> 0 | AO5: =IFERROR(VLOOKUP("SD5_LEAD",'Company 2'!$B:$E,4,0),"") -> 0 | AP5: =IFERROR(VLOOKUP("SD6_CONJOINT",'Company 2'!$B:$E,4,0),"") -> 0
B6: Company 3 | C6: =IFERROR(VLOOKUP("Interviewee Position",'Company 3'!$B:$C,2,0),"") -> Business Development / Media Services Manager | D6: =IFERROR(VLOOKUP("Company Industry",'Company 3'!$B:$C,2,0),"") -> B2B Food Service Distribution | E6: =IFERROR(VLOOKUP("Company Sub-Industry",'Company 3'!$B:$C,2,0),"") -> Wholesaler | F6: =IFERROR(VLOOKUP("Company Size (Turnover)",'Company 3'!$B:$C,2,0),"") -> 332000000 | G6: =IFERROR(VLOOKUP("Country",'Company 3'!$B:$C,2,0),"") -> Belgium | H6: =IFERROR(VLOOKUP("B1_INTEREST",'Company 3'!$B:$E,4,0),"") -> 7 | I6: =IFERROR(VLOOKUP("B2_SHARING",'Company 3'!$B:$E,4,0),"") -> 1 | J6: =IFERROR(VLOOKUP("B3_MONETIZE",'Company 3'!$B:$E,4,0),"") -> 1 | K6: =IFERROR(VLOOKUP("B4_STRATEGIC",'Company 3'!$B:$E,4,0),"") -> 1 | L6: =IFERROR(VLOOKUP("M1_AUTOMATED",'Company 3'!$B:$E,4,0),"") -> 4 | M6: =IFERROR(VLOOKUP("M2_REALTIME",'Company 3'!$B:$E,4,0),"") -> 4 | N6: =IFERROR(VLOOKUP("M3_STRATEGIC",'Company 3'!$B:$E,4,0),"") -> 4 | O6: =IFERROR(VLOOKUP("M4_BREADTH",'Company 3'!$B:$E,4,0),"") -> 5 | P6: =IFERROR(VLOOKUP("M5_DATATYPES",'Company 3'!$B:$E,4,0),"") -> 4 | Q6: =IFERROR(VLOOKUP("M6_TRUST",'Company 3'!$B:$E,4,0),"") -> 3 | R6: =IFERROR(VLOOKUP("M7_BARRIERS",'Company 3'!$B:$E,4,0),"") -> 4 | S6: =IFERROR(VLOOKUP("M8_IMPACT",'Company 3'!$B:$E,4,0),"") -> 3 | T6: =IFERROR(VLOOKUP("M9_WILLINGNESS",'Company 3'!$B:$E,4,0),"") -> 8 | U6: =IFERROR(VLOOKUP("SV1_PRICING",'Company 3'!$B:$E,4,0),"") -> 1 | V6: =IFERROR(VLOOKUP("SV2_PROMOTIONS",'Company 3'!$B:$E,4,0),"") -> 1 | W6: =IFERROR(VLOOKUP("SV3_SUPPLYCHAIN",'Company 3'!$B:$E,4,0),"") -> 0 | X6: =IFERROR(VLOOKUP("SV4_CATEGORY",'Company 3'!$B:$E,4,0),"") -> 1 | Y6: =IFERROR(VLOOKUP("SV5_DEMAND",'Company 3'!$B:$E,4,0),"") -> 0 | Z6: =IFERROR(VLOOKUP("SV6_ACCOUNT",'Company 3'!$B:$E,4,0),"") -> 0 | AA6: =IFERROR(VLOOKUP("SV7_OPS",'Company 3'!$B:$E,4,0),"") -> 0 | AB6: =IFERROR(VLOOKUP("SC1_DATASENS",'Company 3'!$B:$E,4,0),"") -> 1 | AC6: =IFERROR(VLOOKUP("SC2_COMPLIANCE",'Company 3'!$B:$E,4,0),"") -> 1 | AD6: =IFERROR(VLOOKUP("SC3_TRUST",'Company 3'!$B:$E,4,0),"") -> 1 | AE6: =IFERROR(VLOOKUP("SC4_DATAPROC",'Company 3'!$B:$E,4,0),"") -> 1 | AF6: =IFERROR(VLOOKUP("SF1_REALTIME",'Company 3'!$B:$E,4,0),"") -> 1 | AG6: =IFERROR(VLOOKUP("SF2_ACCESS",'Company 3'!$B:$E,4,0),"") -> 1 | AH6: =IFERROR(VLOOKUP("SF3_UX",'Company 3'!$B:$E,4,0),"") -> 0 | AI6: =IFERROR(VLOOKUP("SF4_DECISION",'Company 3'!$B:$E,4,0),"") -> 1 | AJ6: =IFERROR(VLOOKUP("SF5_MASKING",'Company 3'!$B:$E,4,0),"") -> 0 | AK6: =IFERROR(VLOOKUP("SD1_TRENDS",'Company 3'!$B:$E,4,0),"") -> 0 | AL6: =IFERROR(VLOOKUP("SD2_MARKET",'Company 3'!$B:$E,4,0),"") -> 0 | AM6: =IFERROR(VLOOKUP("SD3_CATEGORY",'Company 3'!$B:$E,4,0),"") -> 1 | AN6: =IFERROR(VLOOKUP("SD4_SHIPMENT",'Company 3'!$B:$E,4,0),"") -> 0 | AO6: =IFERROR(VLOOKUP("SD5_LEAD",'Company 3'!$B:$E,4,0),"") -> 0 | AP6: =IFERROR(VLOOKUP("SD6_CONJOINT",'Company 3'!$B:$E,4,0),"") -> 0
B7: Company 4 | C7: =IFERROR(VLOOKUP("Interviewee Position",'Company 4'!$B:$C,2,0),"") -> Data/Analytics role (formerly Department Head of Logistics) | D7: =IFERROR(VLOOKUP("Company Industry",'Company 4'!$B:$C,2,0),"") -> Food Service | E7: =IFERROR(VLOOKUP("Company Sub-Industry",'Company 4'!$B:$C,2,0),"") -> Wholesaler | F7: =IFERROR(VLOOKUP("Company Size (Turnover)",'Company 4'!$B:$C,2,0),"") -> 332000000 | G7: =IFERROR(VLOOKUP("Country",'Company 4'!$B:$C,2,0),"") -> Belgium | H7: =IFERROR(VLOOKUP("B1_INTEREST",'Company 4'!$B:$E,4,0),"") -> 7.5 | I7: =IFERROR(VLOOKUP("B2_SHARING",'Company 4'!$B:$E,4,0),"") -> 1 | J7: =IFERROR(VLOOKUP("B3_MONETIZE",'Company 4'!$B:$E,4,0),"") -> 0 | K7: =IFERROR(VLOOKUP("B4_STRATEGIC",'Company 4'!$B:$E,4,0),"") -> 1 | L7: =IFERROR(VLOOKUP("M1_AUTOMATED",'Company 4'!$B:$E,4,0),"") -> 3 | M7: =IFERROR(VLOOKUP("M2_REALTIME",'Company 4'!$B:$E,4,0),"") -> 2 | N7: =IFERROR(VLOOKUP("M3_STRATEGIC",'Company 4'!$B:$E,4,0),"") -> 4 | O7: =IFERROR(VLOOKUP("M4_BREADTH",'Company 4'!$B:$E,4,0),"") -> 2 | P7: =IFERROR(VLOOKUP("M5_DATATYPES",'Company 4'!$B:$E,4,0),"") -> 3 | Q7: =IFERROR(VLOOKUP("M6_TRUST",'Company 4'!$B:$E,4,0),"") -> 2 | R7: =IFERROR(VLOOKUP("M7_BARRIERS",'Company 4'!$B:$E,4,0),"") -> 3 | S7: =IFERROR(VLOOKUP("M8_IMPACT",'Company 4'!$B:$E,4,0),"") -> 0 | T7: =IFERROR(VLOOKUP("M9_WILLINGNESS",'Company 4'!$B:$E,4,0),"") -> 8 | U7: =IFERROR(VLOOKUP("SV1_PRICING",'Company 4'!$B:$E,4,0),"") -> 1 | V7: =IFERROR(VLOOKUP("SV2_PROMOTIONS",'Company 4'!$B:$E,4,0),"") -> 1 | W7: =IFERROR(VLOOKUP("SV3_SUPPLYCHAIN",'Company 4'!$B:$E,4,0),"") -> 1 | X7: =IFERROR(VLOOKUP("SV4_CATEGORY",'Company 4'!$B:$E,4,0),"") -> 1 | Y7: =IFERROR(VLOOKUP("SV5_DEMAND",'Company 4'!$B:$E,4,0),"") -> 0 | Z7: =IFERROR(VLOOKUP("SV6_ACCOUNT",'Company 4'!$B:$E,4,0),"") -> 1 | AA7: =IFERROR(VLOOKUP("SV7_OPS",'Company 4'!$B:$E,4,0),"") -> 1 | AB7: =IFERROR(VLOOKUP("SC1_DATASENS",'Company 4'!$B:$E,4,0),"") -> 1 | AC7: =IFERROR(VLOOKUP("SC2_COMPLIANCE",'Company 4'!$B:$E,4,0),"") -> 1 | AD7: =IFERROR(VLOOKUP("SC3_TRUST",'Company 4'!$B:$E,4,0),"") -> 1 | AE7: =IFERROR(VLOOKUP("SC4_DATAPROC",'Company 4'!$B:$E,4,0),"") -> 1 | AF7: =IFERROR(VLOOKUP("SF1_REALTIME",'Company 4'!$B:$E,4,0),"") -> 0 | AG7: =IFERROR(VLOOKUP("SF2_ACCESS",'Company 4'!$B:$E,4,0),"") -> 0 | AH7: =IFERROR(VLOOKUP("SF3_UX",'Company 4'!$B:$E,4,0),"") -> 1 | AI7: =IFERROR(VLOOKUP("SF4_DECISION",'Company 4'!$B:$E,4,0),"") -> 0 | AJ7: =IFERROR(VLOOKUP("SF5_MASKING",'Company 4'!$B:$E,4,0),"") -> 0 | AK7: =IFERROR(VLOOKUP("SD1_TRENDS",'Company 4'!$B:$E,4,0),"") -> 0 | AL7: =IFERROR(VLOOKUP("SD2_MARKET",'Company 4'!$B:$E,4,0),"") -> 1 | AM7: =IFERROR(VLOOKUP("SD3_CATEGORY",'Company 4'!$B:$E,4,0),"") -> 1 | AN7: =IFERROR(VLOOKUP("SD4_SHIPMENT",'Company 4'!$B:$E,4,0),"") -> 1 | AO7: =IFERROR(VLOOKUP("SD5_LEAD",'Company 4'!$B:$E,4,0),"") -> 1 | AP7: =IFERROR(VLOOKUP("SD6_CONJOINT",'Company 4'!$B:$E,4,0),"") -> 0
B8: Company 5 | C8: =IFERROR(VLOOKUP("Interviewee Position",'Company 5'!$B:$C,2,0),"") -> Supply Chain Director | D8: =IFERROR(VLOOKUP("Company Industry",'Company 5'!$B:$C,2,0),"") -> Food Manufacturing | E8: =IFERROR(VLOOKUP("Company Sub-Industry",'Company 5'!$B:$C,2,0),"") -> Manufacturer | F8: =IFERROR(VLOOKUP("Company Size (Turnover)",'Company 5'!$B:$C,2,0),"") -> 134000000 | G8: =IFERROR(VLOOKUP("Country",'Company 5'!$B:$C,2,0),"") -> Belgium | H8: =IFERROR(VLOOKUP("B1_INTEREST",'Company 5'!$B:$E,4,0),"") -> 10 | I8: =IFERROR(VLOOKUP("B2_SHARING",'Company 5'!$B:$E,4,0),"") -> 1 | J8: =IFERROR(VLOOKUP("B3_MONETIZE",'Company 5'!$B:$E,4,0),"") -> 0 | K8: =IFERROR(VLOOKUP("B4_STRATEGIC",'Company 5'!$B:$E,4,0),"") -> 1 | L8: =IFERROR(VLOOKUP("M1_AUTOMATED",'Company 5'!$B:$E,4,0),"") -> 2 | M8: =IFERROR(VLOOKUP("M2_REALTIME",'Company 5'!$B:$E,4,0),"") -> 2 | N8: =IFERROR(VLOOKUP("M3_STRATEGIC",'Company 5'!$B:$E,4,0),"") -> 2 | O8: =IFERROR(VLOOKUP("M4_BREADTH",'Company 5'!$B:$E,4,0),"") -> 4 | P8: =IFERROR(VLOOKUP("M5_DATATYPES",'Company 5'!$B:$E,4,0),"") -> 2 | Q8: =IFERROR(VLOOKUP("M6_TRUST",'Company 5'!$B:$E,4,0),"") -> 2 | R8: =IFERROR(VLOOKUP("M7_BARRIERS",'Company 5'!$B:$E,4,0),"") -> 4 | S8: =IFERROR(VLOOKUP("M8_IMPACT",'Company 5'!$B:$E,4,0),"") -> 2 | T8: =IFERROR(VLOOKUP("M9_WILLINGNESS",'Company 5'!$B:$E,4,0),"") -> 10 | U8: =IFERROR(VLOOKUP("SV1_PRICING",'Company 5'!$B:$E,4,0),"") -> 1 | V8: =IFERROR(VLOOKUP("SV2_PROMOTIONS",'Company 5'!$B:$E,4,0),"") -> 1 | W8: =IFERROR(VLOOKUP("SV3_SUPPLYCHAIN",'Company 5'!$B:$E,4,0),"") -> 1 | X8: =IFERROR(VLOOKUP("SV4_CATEGORY",'Company 5'!$B:$E,4,0),"") -> 0 | Y8: =IFERROR(VLOOKUP("SV5_DEMAND",'Company 5'!$B:$E,4,0),"") -> 1 | Z8: =IFERROR(VLOOKUP("SV6_ACCOUNT",'Company 5'!$B:$E,4,0),"") -> 1 | AA8: =IFERROR(VLOOKUP("SV7_OPS",'Company 5'!$B:$E,4,0),"") -> 1 | AB8: =IFERROR(VLOOKUP("SC1_DATASENS",'Company 5'!$B:$E,4,0),"") -> 1 | AC8: =IFERROR(VLOOKUP("SC2_COMPLIANCE",'Company 5'!$B:$E,4,0),"") -> 0 | AD8: =IFERROR(VLOOKUP("SC3_TRUST",'Company 5'!$B:$E,4,0),"") -> 1 | AE8: =IFERROR(VLOOKUP("SC4_DATAPROC",'Company 5'!$B:$E,4,0),"") -> 1 | AF8: =IFERROR(VLOOKUP("SF1_REALTIME",'Company 5'!$B:$E,4,0),"") -> 1 | AG8: =IFERROR(VLOOKUP("SF2_ACCESS",'Company 5'!$B:$E,4,0),"") -> 0 | AH8: =IFERROR(VLOOKUP("SF3_UX",'Company 5'!$B:$E,4,0),"") -> 1 | AI8: =IFERROR(VLOOKUP("SF4_DECISION",'Company 5'!$B:$E,4,0),"") -> 1 | AJ8: =IFERROR(VLOOKUP("SF5_MASKING",'Company 5'!$B:$E,4,0),"") -> 0 | AK8: =IFERROR(VLOOKUP("SD1_TRENDS",'Company 5'!$B:$E,4,0),"") -> 0 | AL8: =IFERROR(VLOOKUP("SD2_MARKET",'Company 5'!$B:$E,4,0),"") -> 0 | AM8: =IFERROR(VLOOKUP("SD3_CATEGORY",'Company 5'!$B:$E,4,0),"") -> 0 | AN8: =IFERROR(VLOOKUP("SD4_SHIPMENT",'Company 5'!$B:$E,4,0),"") -> 1 | AO8: =IFERROR(VLOOKUP("SD5_LEAD",'Company 5'!$B:$E,4,0),"") -> 1 | AP8: =IFERROR(VLOOKUP("SD6_CONJOINT",'Company 5'!$B:$E,4,0),"") -> 0
B9: Company 6 | C9: =IFERROR(VLOOKUP("Interviewee Position",'Company 6'!$B:$C,2,0),"") -> Sales Director | D9: =IFERROR(VLOOKUP("Company Industry",'Company 6'!$B:$C,2,0),"") -> FMCG | E9: =IFERROR(VLOOKUP("Company Sub-Industry",'Company 6'!$B:$C,2,0),"") -> Manufacturer | F9: =IFERROR(VLOOKUP("Company Size (Turnover)",'Company 6'!$B:$C,2,0),"") -> 380000000 | G9: =IFERROR(VLOOKUP("Country",'Company 6'!$B:$C,2,0),"") -> Belgium | H9: =IFERROR(VLOOKUP("B1_INTEREST",'Company 6'!$B:$E,4,0),"") -> 8 | I9: =IFERROR(VLOOKUP("B2_SHARING",'Company 6'!$B:$E,4,0),"") -> 1 | J9: =IFERROR(VLOOKUP("B3_MONETIZE",'Company 6'!$B:$E,4,0),"") -> 0 | K9: =IFERROR(VLOOKUP("B4_STRATEGIC",'Company 6'!$B:$E,4,0),"") -> 1 | L9: =IFERROR(VLOOKUP("M1_AUTOMATED",'Company 6'!$B:$E,4,0),"") -> 5 | M9: =IFERROR(VLOOKUP("M2_REALTIME",'Company 6'!$B:$E,4,0),"") -> 4 | N9: =IFERROR(VLOOKUP("M3_STRATEGIC",'Company 6'!$B:$E,4,0),"") -> 4 | O9: =IFERROR(VLOOKUP("M4_BREADTH",'Company 6'!$B:$E,4,0),"") -> 3 | P9: =IFERROR(VLOOKUP("M5_DATATYPES",'Company 6'!$B:$E,4,0),"") -> 5 | Q9: =IFERROR(VLOOKUP("M6_TRUST",'Company 6'!$B:$E,4,0),"") -> 2 | R9: =IFERROR(VLOOKUP("M7_BARRIERS",'Company 6'!$B:$E,4,0),"") -> 5 | S9: =IFERROR(VLOOKUP("M8_IMPACT",'Company 6'!$B:$E,4,0),"") -> 5 | T9: =IFERROR(VLOOKUP("M9_WILLINGNESS",'Company 6'!$B:$E,4,0),"") -> 6 | U9: =IFERROR(VLOOKUP("SV1_PRICING",'Company 6'!$B:$E,4,0),"") -> 1 | V9: =IFERROR(VLOOKUP("SV2_PROMOTIONS",'Company 6'!$B:$E,4,0),"") -> 1 | W9: =IFERROR(VLOOKUP("SV3_SUPPLYCHAIN",'Company 6'!$B:$E,4,0),"") -> 1 | X9: =IFERROR(VLOOKUP("SV4_CATEGORY",'Company 6'!$B:$E,4,0),"") -> 1 | Y9: =IFERROR(VLOOKUP("SV5_DEMAND",'Company 6'!$B:$E,4,0),"") -> 1 | Z9: =IFERROR(VLOOKUP("SV6_ACCOUNT",'Company 6'!$B:$E,4,0),"") -> 1 | AA9: =IFERROR(VLOOKUP("SV7_OPS",'Company 6'!$B:$E,4,0),"") -> 1 | AB9: =IFERROR(VLOOKUP("SC1_DATASENS",'Company 6'!$B:$E,4,0),"") -> 1 | AC9: =IFERROR(VLOOKUP("SC2_COMPLIANCE",'Company 6'!$B:$E,4,0),"") -> 1 | AD9: =IFERROR(VLOOKUP("SC3_TRUST",'Company 6'!$B:$E,4,0),"") -> 1 | AE9: =IFERROR(VLOOKUP("SC4_DATAPROC",'Company 6'!$B:$E,4,0),"") -> 1 | AF9: =IFERROR(VLOOKUP("SF1_REALTIME",'Company 6'!$B:$E,4,0),"") -> 1 | AG9: =IFERROR(VLOOKUP("SF2_ACCESS",'Company 6'!$B:$E,4,0),"") -> 1 | AH9: =IFERROR(VLOOKUP("SF3_UX",'Company 6'!$B:$E,4,0),"") -> 0 | AI9: =IFERROR(VLOOKUP("SF4_DECISION",'Company 6'!$B:$E,4,0),"") -> 1 | AJ9: =IFERROR(VLOOKUP("SF5_MASKING",'Company 6'!$B:$E,4,0),"") -> 0 | AK9: =IFERROR(VLOOKUP("SD1_TRENDS",'Company 6'!$B:$E,4,0),"") -> 1 | AL9: =IFERROR(VLOOKUP("SD2_MARKET",'Company 6'!$B:$E,4,0),"") -> 1 | AM9: =IFERROR(VLOOKUP("SD3_CATEGORY",'Company 6'!$B:$E,4,0),"") -> 1 | AN9: =IFERROR(VLOOKUP("SD4_SHIPMENT",'Company 6'!$B:$E,4,0),"") -> 1 | AO9: =IFERROR(VLOOKUP("SD5_LEAD",'Company 6'!$B:$E,4,0),"") -> 0 | AP9: =IFERROR(VLOOKUP("SD6_CONJOINT",'Company 6'!$B:$E,4,0),"") -> 0
B10: Company 7 | C10: =IFERROR(VLOOKUP("Interviewee Position",'Company 7'!$B:$C,2,0),"") -> CEO | D10: =IFERROR(VLOOKUP("Company Industry",'Company 7'!$B:$C,2,0),"") -> Food Service / Wholesale Distribution | E10: =IFERROR(VLOOKUP("Company Sub-Industry",'Company 7'!$B:$C,2,0),"") -> Wholesaler | F10: =IFERROR(VLOOKUP("Company Size (Turnover)",'Company 7'!$B:$C,2,0),"") -> 7800000 | G10: =IFERROR(VLOOKUP("Country",'Company 7'!$B:$C,2,0),"") -> Belgium | H10: =IFERROR(VLOOKUP("B1_INTEREST",'Company 7'!$B:$E,4,0),"") -> 8 | I10: =IFERROR(VLOOKUP("B2_SHARING",'Company 7'!$B:$E,4,0),"") -> 1 | J10: =IFERROR(VLOOKUP("B3_MONETIZE",'Company 7'!$B:$E,4,0),"") -> 1 | K10: =IFERROR(VLOOKUP("B4_STRATEGIC",'Company 7'!$B:$E,4,0),"") -> 0 | L10: =IFERROR(VLOOKUP("M1_AUTOMATED",'Company 7'!$B:$E,4,0),"") -> 1 | M10: =IFERROR(VLOOKUP("M2_REALTIME",'Company 7'!$B:$E,4,0),"") -> 2 | N10: =IFERROR(VLOOKUP("M3_STRATEGIC",'Company 7'!$B:$E,4,0),"") -> 4 | O10: =IFERROR(VLOOKUP("M4_BREADTH",'Company 7'!$B:$E,4,0),"") -> 3 | P10: =IFERROR(VLOOKUP("M5_DATATYPES",'Company 7'!$B:$E,4,0),"") -> 3 | Q10: =IFERROR(VLOOKUP("M6_TRUST",'Company 7'!$B:$E,4,0),"") -> 0 | R10: =IFERROR(VLOOKUP("M7_BARRIERS",'Company 7'!$B:$E,4,0),"") -> 2 | S10: =IFERROR(VLOOKUP("M8_IMPACT",'Company 7'!$B:$E,4,0),"") -> 3 | T10: =IFERROR(VLOOKUP("M9_WILLINGNESS",'Company 7'!$B:$E,4,0),"") -> 8 | U10: =IFERROR(VLOOKUP("SV1_PRICING",'Company 7'!$B:$E,4,0),"") -> 0 | V10: =IFERROR(VLOOKUP("SV2_PROMOTIONS",'Company 7'!$B:$E,4,0),"") -> 0 | W10: =IFERROR(VLOOKUP("SV3_SUPPLYCHAIN",'Company 7'!$B:$E,4,0),"") -> 0 | X10: =IFERROR(VLOOKUP("SV4_CATEGORY",'Company 7'!$B:$E,4,0),"") -> 1 | Y10: =IFERROR(VLOOKUP("SV5_DEMAND",'Company 7'!$B:$E,4,0),"") -> 0 | Z10: =IFERROR(VLOOKUP("SV6_ACCOUNT",'Company 7'!$B:$E,4,0),"") -> 0 | AA10: =IFERROR(VLOOKUP("SV7_OPS",'Company 7'!$B:$E,4,0),"") -> 1 | AB10: =IFERROR(VLOOKUP("SC1_DATASENS",'Company 7'!$B:$E,4,0),"") -> 0 | AC10: =IFERROR(VLOOKUP("SC2_COMPLIANCE",'Company 7'!$B:$E,4,0),"") -> 0 | AD10: =IFERROR(VLOOKUP("SC3_TRUST",'Company 7'!$B:$E,4,0),"") -> 0 | AE10: =IFERROR(VLOOKUP("SC4_DATAPROC",'Company 7'!$B:$E,4,0),"") -> 1 | AF10: =IFERROR(VLOOKUP("SF1_REALTIME",'Company 7'!$B:$E,4,0),"") -> 1 | AG10: =IFERROR(VLOOKUP("SF2_ACCESS",'Company 7'!$B:$E,4,0),"") -> 0 | AH10: =IFERROR(VLOOKUP("SF3_UX",'Company 7'!$B:$E,4,0),"") -> 1 | AI10: =IFERROR(VLOOKUP("SF4_DECISION",'Company 7'!$B:$E,4,0),"") -> 0 | AJ10: =IFERROR(VLOOKUP("SF5_MASKING",'Company 7'!$B:$E,4,0),"") -> 0 | AK10: =IFERROR(VLOOKUP("SD1_TRENDS",'Company 7'!$B:$E,4,0),"") -> 0 | AL10: =IFERROR(VLOOKUP("SD2_MARKET",'Company 7'!$B:$E,4,0),"") -> 1 | AM10: =IFERROR(VLOOKUP("SD3_CATEGORY",'Company 7'!$B:$E,4,0),"") -> 1 | AN10: =IFERROR(VLOOKUP("SD4_SHIPMENT",'Company 7'!$B:$E,4,0),"") -> 0 | AO10: =IFERROR(VLOOKUP("SD5_LEAD",'Company 7'!$B:$E,4,0),"") -> 0 | AP10: =IFERROR(VLOOKUP("SD6_CONJOINT",'Company 7'!$B:$E,4,0),"") -> 0
B11: Company 8 | C11: =IFERROR(VLOOKUP("Interviewee Position",'Company 8'!$B:$C,2,0),"") -> CFO / Finance Lead EMEA & LATAM | D11: =IFERROR(VLOOKUP("Company Industry",'Company 8'!$B:$C,2,0),"") -> Pet Food & Products | E11: =IFERROR(VLOOKUP("Company Sub-Industry",'Company 8'!$B:$C,2,0),"") -> Manufacturer | F11: =IFERROR(VLOOKUP("Company Size (Turnover)",'Company 8'!$B:$C,2,0),"") -> 90000000 | G11: =IFERROR(VLOOKUP("Country",'Company 8'!$B:$C,2,0),"") -> US | H11: =IFERROR(VLOOKUP("B1_INTEREST",'Company 8'!$B:$E,4,0),"") -> 8 | I11: =IFERROR(VLOOKUP("B2_SHARING",'Company 8'!$B:$E,4,0),"") -> 1 | J11: =IFERROR(VLOOKUP("B3_MONETIZE",'Company 8'!$B:$E,4,0),"") -> 0 | K11: =IFERROR(VLOOKUP("B4_STRATEGIC",'Company 8'!$B:$E,4,0),"") -> 0 | L11: =IFERROR(VLOOKUP("M1_AUTOMATED",'Company 8'!$B:$E,4,0),"") -> 3 | M11: =IFERROR(VLOOKUP("M2_REALTIME",'Company 8'!$B:$E,4,0),"") -> 2 | N11: =IFERROR(VLOOKUP("M3_STRATEGIC",'Company 8'!$B:$E,4,0),"") -> 4 | O11: =IFERROR(VLOOKUP("M4_BREADTH",'Company 8'!$B:$E,4,0),"") -> 3 | P11: =IFERROR(VLOOKUP("M5_DATATYPES",'Company 8'!$B:$E,4,0),"") -> 4 | Q11: =IFERROR(VLOOKUP("M6_TRUST",'Company 8'!$B:$E,4,0),"") -> 4 | R11: =IFERROR(VLOOKUP("M7_BARRIERS",'Company 8'!$B:$E,4,0),"") -> 4 | S11: =IFERROR(VLOOKUP("M8_IMPACT",'Company 8'!$B:$E,4,0),"") -> 2 | T11: =IFERROR(VLOOKUP("M9_WILLINGNESS",'Company 8'!$B:$E,4,0),"") -> 8 | U11: =IFERROR(VLOOKUP("SV1_PRICING",'Company 8'!$B:$E,4,0),"") -> 1 | V11: =IFERROR(VLOOKUP("SV2_PROMOTIONS",'Company 8'!$B:$E,4,0),"") -> 1 | W11: =IFERROR(VLOOKUP("SV3_SUPPLYCHAIN",'Company 8'!$B:$E,4,0),"") -> 0 | X11: =IFERROR(VLOOKUP("SV4_CATEGORY",'Company 8'!$B:$E,4,0),"") -> 1 | Y11: =IFERROR(VLOOKUP("SV5_DEMAND",'Company 8'!$B:$E,4,0),"") -> 0 | Z11: =IFERROR(VLOOKUP("SV6_ACCOUNT",'Company 8'!$B:$E,4,0),"") -> 0 | AA11: =IFERROR(VLOOKUP("SV7_OPS",'Company 8'!$B:$E,4,0),"") -> 0 | AB11: =IFERROR(VLOOKUP("SC1_DATASENS",'Company 8'!$B:$E,4,0),"") -> 1 | AC11: =IFERROR(VLOOKUP("SC2_COMPLIANCE",'Company 8'!$B:$E,4,0),"") -> 1 | AD11: =IFERROR(VLOOKUP("SC3_TRUST",'Company 8'!$B:$E,4,0),"") -> 0 | AE11: =IFERROR(VLOOKUP("SC4_DATAPROC",'Company 8'!$B:$E,4,0),"") -> 0 | AF11: =IFERROR(VLOOKUP("SF1_REALTIME",'Company 8'!$B:$E,4,0),"") -> 0 | AG11: =IFERROR(VLOOKUP("SF2_ACCESS",'Company 8'!$B:$E,4,0),"") -> 0 | AH11: =IFERROR(VLOOKUP("SF3_UX",'Company 8'!$B:$E,4,0),"") -> 0 | AI11: =IFERROR(VLOOKUP("SF4_DECISION",'Company 8'!$B:$E,4,0),"") -> 0 | AJ11: =IFERROR(VLOOKUP("SF5_MASKING",'Company 8'!$B:$E,4,0),"") -> 0 | AK11: =IFERROR(VLOOKUP("SD1_TRENDS",'Company 8'!$B:$E,4,0),"") -> 1 | AL11: =IFERROR(VLOOKUP("SD2_MARKET",'Company 8'!$B:$E,4,0),"") -> 1 | AM11: =IFERROR(VLOOKUP("SD3_CATEGORY",'Company 8'!$B:$E,4,0),"") -> 1 | AN11: =IFERROR(VLOOKUP("SD4_SHIPMENT",'Company 8'!$B:$E,4,0),"") -> 0 | AO11: =IFERROR(VLOOKUP("SD5_LEAD",'Company 8'!$B:$E,4,0),"") -> 0 | AP11: =IFERROR(VLOOKUP("SD6_CONJOINT",'Company 8'!$B:$E,4,0),"") -> 0
B12: Company 9 | C12: =IFERROR(VLOOKUP("Interviewee Position",'Company 9'!$B:$C,2,0),"") -> Commercial Director | D12: =IFERROR(VLOOKUP("Company Industry",'Company 9'!$B:$C,2,0),"") -> Wholesale | E12: =IFERROR(VLOOKUP("Company Sub-Industry",'Company 9'!$B:$C,2,0),"") -> Wholesaler | F12: =IFERROR(VLOOKUP("Company Size (Turnover)",'Company 9'!$B:$C,2,0),"") -> 2000000000 | G12: =IFERROR(VLOOKUP("Country",'Company 9'!$B:$C,2,0),"") -> Belgium | H12: =IFERROR(VLOOKUP("B1_INTEREST",'Company 9'!$B:$E,4,0),"") -> 8 | I12: =IFERROR(VLOOKUP("B2_SHARING",'Company 9'!$B:$E,4,0),"") -> 1 | J12: =IFERROR(VLOOKUP("B3_MONETIZE",'Company 9'!$B:$E,4,0),"") -> 1 | K12: =IFERROR(VLOOKUP("B4_STRATEGIC",'Company 9'!$B:$E,4,0),"") -> 0 | L12: =IFERROR(VLOOKUP("M1_AUTOMATED",'Company 9'!$B:$E,4,0),"") -> 3 | M12: =IFERROR(VLOOKUP("M2_REALTIME",'Company 9'!$B:$E,4,0),"") -> 2 | N12: =IFERROR(VLOOKUP("M3_STRATEGIC",'Company 9'!$B:$E,4,0),"") -> 4 | O12: =IFERROR(VLOOKUP("M4_BREADTH",'Company 9'!$B:$E,4,0),"") -> 2 | P12: =IFERROR(VLOOKUP("M5_DATATYPES",'Company 9'!$B:$E,4,0),"") -> 5 | Q12: =IFERROR(VLOOKUP("M6_TRUST",'Company 9'!$B:$E,4,0),"") -> 2 | R12: =IFERROR(VLOOKUP("M7_BARRIERS",'Company 9'!$B:$E,4,0),"") -> 4 | S12: =IFERROR(VLOOKUP("M8_IMPACT",'Company 9'!$B:$E,4,0),"") -> 4 | T12: =IFERROR(VLOOKUP("M9_WILLINGNESS",'Company 9'!$B:$E,4,0),"") -> 6 | U12: =IFERROR(VLOOKUP("SV1_PRICING",'Company 9'!$B:$E,4,0),"") -> 0 | V12: =IFERROR(VLOOKUP("SV2_PROMOTIONS",'Company 9'!$B:$E,4,0),"") -> 0 | W12: =IFERROR(VLOOKUP("SV3_SUPPLYCHAIN",'Company 9'!$B:$E,4,0),"") -> 0 | X12: =IFERROR(VLOOKUP("SV4_CATEGORY",'Company 9'!$B:$E,4,0),"") -> 1 | Y12: =IFERROR(VLOOKUP("SV5_DEMAND",'Company 9'!$B:$E,4,0),"") -> 1 | Z12: =IFERROR(VLOOKUP("SV6_ACCOUNT",'Company 9'!$B:$E,4,0),"") -> 0 | AA12: =IFERROR(VLOOKUP("SV7_OPS",'Company 9'!$B:$E,4,0),"") -> 0 | AB12: =IFERROR(VLOOKUP("SC1_DATASENS",'Company 9'!$B:$E,4,0),"") -> 1 | AC12: =IFERROR(VLOOKUP("SC2_COMPLIANCE",'Company 9'!$B:$E,4,0),"") -> 0 | AD12: =IFERROR(VLOOKUP("SC3_TRUST",'Company 9'!$B:$E,4,0),"") -> 0 | AE12: =IFERROR(VLOOKUP("SC4_DATAPROC",'Company 9'!$B:$E,4,0),"") -> 0 | AF12: =IFERROR(VLOOKUP("SF1_REALTIME",'Company 9'!$B:$E,4,0),"") -> 0 | AG12: =IFERROR(VLOOKUP("SF2_ACCESS",'Company 9'!$B:$E,4,0),"") -> 1 | AH12: =IFERROR(VLOOKUP("SF3_UX",'Company 9'!$B:$E,4,0),"") -> 1 | AI12: =IFERROR(VLOOKUP("SF4_DECISION",'Company 9'!$B:$E,4,0),"") -> 0 | AJ12: =IFERROR(VLOOKUP("SF5_MASKING",'Company 9'!$B:$E,4,0),"") -> 0 | AK12: =IFERROR(VLOOKUP("SD1_TRENDS",'Company 9'!$B:$E,4,0),"") -> 1 | AL12: =IFERROR(VLOOKUP("SD2_MARKET",'Company 9'!$B:$E,4,0),"") -> 1 | AM12: =IFERROR(VLOOKUP("SD3_CATEGORY",'Company 9'!$B:$E,4,0),"") -> 1 | AN12: =IFERROR(VLOOKUP("SD4_SHIPMENT",'Company 9'!$B:$E,4,0),"") -> 1 | AO12: =IFERROR(VLOOKUP("SD5_LEAD",'Company 9'!$B:$E,4,0),"") -> 0 | AP12: =IFERROR(VLOOKUP("SD6_CONJOINT",'Company 9'!$B:$E,4,0),"") -> 0
B13: Company 10 | C13: =IFERROR(VLOOKUP("Interviewee Position",'Company 10'!$B:$C,2,0),"") -> Data Insights Team | D13: =IFERROR(VLOOKUP("Company Industry",'Company 10'!$B:$C,2,0),"") -> FMCG | E13: =IFERROR(VLOOKUP("Company Sub-Industry",'Company 10'!$B:$C,2,0),"") -> Manufacturer | F13: =IFERROR(VLOOKUP("Company Size (Turnover)",'Company 10'!$B:$C,2,0),"") -> 52000000 | G13: =IFERROR(VLOOKUP("Country",'Company 10'!$B:$C,2,0),"") -> Denmark | H13: =IFERROR(VLOOKUP("B1_INTEREST",'Company 10'!$B:$E,4,0),"") -> 7 | I13: =IFERROR(VLOOKUP("B2_SHARING",'Company 10'!$B:$E,4,0),"") -> 1 | J13: =IFERROR(VLOOKUP("B3_MONETIZE",'Company 10'!$B:$E,4,0),"") -> 0 | K13: =IFERROR(VLOOKUP("B4_STRATEGIC",'Company 10'!$B:$E,4,0),"") -> 1 | L13: =IFERROR(VLOOKUP("M1_AUTOMATED",'Company 10'!$B:$E,4,0),"") -> 2 | M13: =IFERROR(VLOOKUP("M2_REALTIME",'Company 10'!$B:$E,4,0),"") -> 2 | N13: =IFERROR(VLOOKUP("M3_STRATEGIC",'Company 10'!$B:$E,4,0),"") -> 5 | O13: =IFERROR(VLOOKUP("M4_BREADTH",'Company 10'!$B:$E,4,0),"") -> 3 | P13: =IFERROR(VLOOKUP("M5_DATATYPES",'Company 10'!$B:$E,4,0),"") -> 5 | Q13: =IFERROR(VLOOKUP("M6_TRUST",'Company 10'!$B:$E,4,0),"") -> 3 | R13: =IFERROR(VLOOKUP("M7_BARRIERS",'Company 10'!$B:$E,4,0),"") -> 4 | S13: =IFERROR(VLOOKUP("M8_IMPACT",'Company 10'!$B:$E,4,0),"") -> 4 | T13: =IFERROR(VLOOKUP("M9_WILLINGNESS",'Company 10'!$B:$E,4,0),"") -> 7 | U13: =IFERROR(VLOOKUP("SV1_PRICING",'Company 10'!$B:$E,4,0),"") -> 1 | V13: =IFERROR(VLOOKUP("SV2_PROMOTIONS",'Company 10'!$B:$E,4,0),"") -> 0 | W13: =IFERROR(VLOOKUP("SV3_SUPPLYCHAIN",'Company 10'!$B:$E,4,0),"") -> 1 | X13: =IFERROR(VLOOKUP("SV4_CATEGORY",'Company 10'!$B:$E,4,0),"") -> 1 | Y13: =IFERROR(VLOOKUP("SV5_DEMAND",'Company 10'!$B:$E,4,0),"") -> 0 | Z13: =IFERROR(VLOOKUP("SV6_ACCOUNT",'Company 10'!$B:$E,4,0),"") -> 0 | AA13: =IFERROR(VLOOKUP("SV7_OPS",'Company 10'!$B:$E,4,0),"") -> 0 | AB13: =IFERROR(VLOOKUP("SC1_DATASENS",'Company 10'!$B:$E,4,0),"") -> 1 | AC13: =IFERROR(VLOOKUP("SC2_COMPLIANCE",'Company 10'!$B:$E,4,0),"") -> 1 | AD13: =IFERROR(VLOOKUP("SC3_TRUST",'Company 10'!$B:$E,4,0),"") -> 0 | AE13: =IFERROR(VLOOKUP("SC4_DATAPROC",'Company 10'!$B:$E,4,0),"") -> 1 | AF13: =IFERROR(VLOOKUP("SF1_REALTIME",'Company 10'!$B:$E,4,0),"") -> 1 | AG13: =IFERROR(VLOOKUP("SF2_ACCESS",'Company 10'!$B:$E,4,0),"") -> 0 | AH13: =IFERROR(VLOOKUP("SF3_UX",'Company 10'!$B:$E,4,0),"") -> 1 | AI13: =IFERROR(VLOOKUP("SF4_DECISION",'Company 10'!$B:$E,4,0),"") -> 0 | AJ13: =IFERROR(VLOOKUP("SF5_MASKING",'Company 10'!$B:$E,4,0),"") -> 0 | AK13: =IFERROR(VLOOKUP("SD1_TRENDS",'Company 10'!$B:$E,4,0),"") -> 1 | AL13: =IFERROR(VLOOKUP("SD2_MARKET",'Company 10'!$B:$E,4,0),"") -> 1 | AM13: =IFERROR(VLOOKUP("SD3_CATEGORY",'Company 10'!$B:$E,4,0),"") -> 1 | AN13: =IFERROR(VLOOKUP("SD4_SHIPMENT",'Company 10'!$B:$E,4,0),"") -> 0 | AO13: =IFERROR(VLOOKUP("SD5_LEAD",'Company 10'!$B:$E,4,0),"") -> 0 | AP13: =IFERROR(VLOOKUP("SD6_CONJOINT",'Company 10'!$B:$E,4,0),"") -> 0
B14: Company 11 | C14: =IFERROR(VLOOKUP("Interviewee Position",'Company 11'!$B:$C,2,0),"") -> Marketing Strategic Role | D14: =IFERROR(VLOOKUP("Company Industry",'Company 11'!$B:$C,2,0),"") -> Pharmacy/Healthcare Retail | E14: =IFERROR(VLOOKUP("Company Sub-Industry",'Company 11'!$B:$C,2,0),"") -> Specialty Retail | F14: =IFERROR(VLOOKUP("Company Size (Turnover)",'Company 11'!$B:$C,2,0),"") -> 140000000 | G14: =IFERROR(VLOOKUP("Country",'Company 11'!$B:$C,2,0),"") -> Belgium | H14: =IFERROR(VLOOKUP("B1_INTEREST",'Company 11'!$B:$E,4,0),"") -> 9 | I14: =IFERROR(VLOOKUP("B2_SHARING",'Company 11'!$B:$E,4,0),"") -> 1 | J14: =IFERROR(VLOOKUP("B3_MONETIZE",'Company 11'!$B:$E,4,0),"") -> 0 | K14: =IFERROR(VLOOKUP("B4_STRATEGIC",'Company 11'!$B:$E,4,0),"") -> 0 | L14: =IFERROR(VLOOKUP("M1_AUTOMATED",'Company 11'!$B:$E,4,0),"") -> 1 | M14: =IFERROR(VLOOKUP("M2_REALTIME",'Company 11'!$B:$E,4,0),"") -> 1 | N14: =IFERROR(VLOOKUP("M3_STRATEGIC",'Company 11'!$B:$E,4,0),"") -> 2 | O14: =IFERROR(VLOOKUP("M4_BREADTH",'Company 11'!$B:$E,4,0),"") -> 2 | P14: =IFERROR(VLOOKUP("M5_DATATYPES",'Company 11'!$B:$E,4,0),"") -> 2 | Q14: =IFERROR(VLOOKUP("M6_TRUST",'Company 11'!$B:$E,4,0),"") -> 0 | R14: =IFERROR(VLOOKUP("M7_BARRIERS",'Company 11'!$B:$E,4,0),"") -> 2 | S14: =IFERROR(VLOOKUP("M8_IMPACT",'Company 11'!$B:$E,4,0),"") -> 0 | T14: =IFERROR(VLOOKUP("M9_WILLINGNESS",'Company 11'!$B:$E,4,0),"") -> 9 | U14: =IFERROR(VLOOKUP("SV1_PRICING",'Company 11'!$B:$E,4,0),"") -> 1 | V14: =IFERROR(VLOOKUP("SV2_PROMOTIONS",'Company 11'!$B:$E,4,0),"") -> 1 | W14: =IFERROR(VLOOKUP("SV3_SUPPLYCHAIN",'Company 11'!$B:$E,4,0),"") -> 1 | X14: =IFERROR(VLOOKUP("SV4_CATEGORY",'Company 11'!$B:$E,4,0),"") -> 1 | Y14: =IFERROR(VLOOKUP("SV5_DEMAND",'Company 11'!$B:$E,4,0),"") -> 0 | Z14: =IFERROR(VLOOKUP("SV6_ACCOUNT",'Company 11'!$B:$E,4,0),"") -> 0 | AA14: =IFERROR(VLOOKUP("SV7_OPS",'Company 11'!$B:$E,4,0),"") -> 0 | AB14: =IFERROR(VLOOKUP("SC1_DATASENS",'Company 11'!$B:$E,4,0),"") -> 1 | AC14: =IFERROR(VLOOKUP("SC2_COMPLIANCE",'Company 11'!$B:$E,4,0),"") -> 0 | AD14: =IFERROR(VLOOKUP("SC3_TRUST",'Company 11'!$B:$E,4,0),"") -> 0 | AE14: =IFERROR(VLOOKUP("SC4_DATAPROC",'Company 11'!$B:$E,4,0),"") -> 1 | AF14: =IFERROR(VLOOKUP("SF1_REALTIME",'Company 11'!$B:$E,4,0),"") -> 0 | AG14: =IFERROR(VLOOKUP("SF2_ACCESS",'Company 11'!$B:$E,4,0),"") -> 0 | AH14: =IFERROR(VLOOKUP("SF3_UX",'Company 11'!$B:$E,4,0),"") -> 1 | AI14: =IFERROR(VLOOKUP("SF4_DECISION",'Company 11'!$B:$E,4,0),"") -> 0 | AJ14: =IFERROR(VLOOKUP("SF5_MASKING",'Company 11'!$B:$E,4,0),"") -> 0 | AK14: =IFERROR(VLOOKUP("SD1_TRENDS",'Company 11'!$B:$E,4,0),"") -> 1 | AL14: =IFERROR(VLOOKUP("SD2_MARKET",'Company 11'!$B:$E,4,0),"") -> 1 | AM14: =IFERROR(VLOOKUP("SD3_CATEGORY",'Company 11'!$B:$E,4,0),"") -> 1 | AN14: =IFERROR(VLOOKUP("SD4_SHIPMENT",'Company 11'!$B:$E,4,0),"") -> 0 | AO14: =IFERROR(VLOOKUP("SD5_LEAD",'Company 11'!$B:$E,4,0),"") -> 0 | AP14: =IFERROR(VLOOKUP("SD6_CONJOINT",'Company 11'!$B:$E,4,0),"") -> 0
B15: Company 12 | C15: =IFERROR(VLOOKUP("Interviewee Position",'Company 12'!$B:$C,2,0),"") -> Marketing / Commercial Director | D15: =IFERROR(VLOOKUP("Company Industry",'Company 12'!$B:$C,2,0),"") -> Grocery Retail | E15: =IFERROR(VLOOKUP("Company Sub-Industry",'Company 12'!$B:$C,2,0),"") -> Retailer | F15: =IFERROR(VLOOKUP("Company Size (Turnover)",'Company 12'!$B:$C,2,0),"") -> 3240000000 | G15: =IFERROR(VLOOKUP("Country",'Company 12'!$B:$C,2,0),"") -> Germany | H15: =IFERROR(VLOOKUP("B1_INTEREST",'Company 12'!$B:$E,4,0),"") -> 3 | I15: =IFERROR(VLOOKUP("B2_SHARING",'Company 12'!$B:$E,4,0),"") -> 1 | J15: =IFERROR(VLOOKUP("B3_MONETIZE",'Company 12'!$B:$E,4,0),"") -> 0 | K15: =IFERROR(VLOOKUP("B4_STRATEGIC",'Company 12'!$B:$E,4,0),"") -> 1 | L15: =IFERROR(VLOOKUP("M1_AUTOMATED",'Company 12'!$B:$E,4,0),"") -> 0 | M15: =IFERROR(VLOOKUP("M2_REALTIME",'Company 12'!$B:$E,4,0),"") -> 0 | N15: =IFERROR(VLOOKUP("M3_STRATEGIC",'Company 12'!$B:$E,4,0),"") -> 2 | O15: =IFERROR(VLOOKUP("M4_BREADTH",'Company 12'!$B:$E,4,0),"") -> 1 | P15: =IFERROR(VLOOKUP("M5_DATATYPES",'Company 12'!$B:$E,4,0),"") -> 2 | Q15: =IFERROR(VLOOKUP("M6_TRUST",'Company 12'!$B:$E,4,0),"") -> 0 | R15: =IFERROR(VLOOKUP("M7_BARRIERS",'Company 12'!$B:$E,4,0),"") -> 4 | S15: =IFERROR(VLOOKUP("M8_IMPACT",'Company 12'!$B:$E,4,0),"") -> 4 | T15: =IFERROR(VLOOKUP("M9_WILLINGNESS",'Company 12'!$B:$E,4,0),"") -> 3 | U15: =IFERROR(VLOOKUP("SV1_PRICING",'Company 12'!$B:$E,4,0),"") -> 0 | V15: =IFERROR(VLOOKUP("SV2_PROMOTIONS",'Company 12'!$B:$E,4,0),"") -> 1 | W15: =IFERROR(VLOOKUP("SV3_SUPPLYCHAIN",'Company 12'!$B:$E,4,0),"") -> 1 | X15: =IFERROR(VLOOKUP("SV4_CATEGORY",'Company 12'!$B:$E,4,0),"") -> 0 | Y15: =IFERROR(VLOOKUP("SV5_DEMAND",'Company 12'!$B:$E,4,0),"") -> 1 | Z15: =IFERROR(VLOOKUP("SV6_ACCOUNT",'Company 12'!$B:$E,4,0),"") -> 0 | AA15: =IFERROR(VLOOKUP("SV7_OPS",'Company 12'!$B:$E,4,0),"") -> 0 | AB15: =IFERROR(VLOOKUP("SC1_DATASENS",'Company 12'!$B:$E,4,0),"") -> 1 | AC15: =IFERROR(VLOOKUP("SC2_COMPLIANCE",'Company 12'!$B:$E,4,0),"") -> 1 | AD15: =IFERROR(VLOOKUP("SC3_TRUST",'Company 12'!$B:$E,4,0),"") -> 0 | AE15: =IFERROR(VLOOKUP("SC4_DATAPROC",'Company 12'!$B:$E,4,0),"") -> 0 | AF15: =IFERROR(VLOOKUP("SF1_REALTIME",'Company 12'!$B:$E,4,0),"") -> 0 | AG15: =IFERROR(VLOOKUP("SF2_ACCESS",'Company 12'!$B:$E,4,0),"") -> 0 | AH15: =IFERROR(VLOOKUP("SF3_UX",'Company 12'!$B:$E,4,0),"") -> 0 | AI15: =IFERROR(VLOOKUP("SF4_DECISION",'Company 12'!$B:$E,4,0),"") -> 0 | AJ15: =IFERROR(VLOOKUP("SF5_MASKING",'Company 12'!$B:$E,4,0),"") -> 1 | AK15: =IFERROR(VLOOKUP("SD1_TRENDS",'Company 12'!$B:$E,4,0),"") -> 1 | AL15: =IFERROR(VLOOKUP("SD2_MARKET",'Company 12'!$B:$E,4,0),"") -> 1 | AM15: =IFERROR(VLOOKUP("SD3_CATEGORY",'Company 12'!$B:$E,4,0),"") -> 0 | AN15: =IFERROR(VLOOKUP("SD4_SHIPMENT",'Company 12'!$B:$E,4,0),"") -> 1 | AO15: =IFERROR(VLOOKUP("SD5_LEAD",'Company 12'!$B:$E,4,0),"") -> 0 | AP15: =IFERROR(VLOOKUP("SD6_CONJOINT",'Company 12'!$B:$E,4,0),"") -> 0
B16: Company 13 | C16: =IFERROR(VLOOKUP("Interviewee Position",'Company 13'!$B:$C,2,0),"") -> Data Lead / Head of IT & ERP | D16: =IFERROR(VLOOKUP("Company Industry",'Company 13'!$B:$C,2,0),"") -> Pet Food Manufacturing | E16: =IFERROR(VLOOKUP("Company Sub-Industry",'Company 13'!$B:$C,2,0),"") -> Manufacturer | F16: =IFERROR(VLOOKUP("Company Size (Turnover)",'Company 13'!$B:$C,2,0),"") -> 140000000 | G16: =IFERROR(VLOOKUP("Country",'Company 13'!$B:$C,2,0),"") -> Belgium | H16: =IFERROR(VLOOKUP("B1_INTEREST",'Company 13'!$B:$E,4,0),"") -> 9 | I16: =IFERROR(VLOOKUP("B2_SHARING",'Company 13'!$B:$E,4,0),"") -> 1 | J16: =IFERROR(VLOOKUP("B3_MONETIZE",'Company 13'!$B:$E,4,0),"") -> 0 | K16: =IFERROR(VLOOKUP("B4_STRATEGIC",'Company 13'!$B:$E,4,0),"") -> 0 | L16: =IFERROR(VLOOKUP("M1_AUTOMATED",'Company 13'!$B:$E,4,0),"") -> 3 | M16: =IFERROR(VLOOKUP("M2_REALTIME",'Company 13'!$B:$E,4,0),"") -> 3 | N16: =IFERROR(VLOOKUP("M3_STRATEGIC",'Company 13'!$B:$E,4,0),"") -> 4 | O16: =IFERROR(VLOOKUP("M4_BREADTH",'Company 13'!$B:$E,4,0),"") -> 3 | P16: =IFERROR(VLOOKUP("M5_DATATYPES",'Company 13'!$B:$E,4,0),"") -> 4 | Q16: =IFERROR(VLOOKUP("M6_TRUST",'Company 13'!$B:$E,4,0),"") -> 2 | R16: =IFERROR(VLOOKUP("M7_BARRIERS",'Company 13'!$B:$E,4,0),"") -> 3 | S16: =IFERROR(VLOOKUP("M8_IMPACT",'Company 13'!$B:$E,4,0),"") -> 3 | T16: =IFERROR(VLOOKUP("M9_WILLINGNESS",'Company 13'!$B:$E,4,0),"") -> 9 | U16: =IFERROR(VLOOKUP("SV1_PRICING",'Company 13'!$B:$E,4,0),"") -> 0 | V16: =IFERROR(VLOOKUP("SV2_PROMOTIONS",'Company 13'!$B:$E,4,0),"") -> 1 | W16: =IFERROR(VLOOKUP("SV3_SUPPLYCHAIN",'Company 13'!$B:$E,4,0),"") -> 1 | X16: =IFERROR(VLOOKUP("SV4_CATEGORY",'Company 13'!$B:$E,4,0),"") -> 1 | Y16: =IFERROR(VLOOKUP("SV5_DEMAND",'Company 13'!$B:$E,4,0),"") -> 0 | Z16: =IFERROR(VLOOKUP("SV6_ACCOUNT",'Company 13'!$B:$E,4,0),"") -> 0 | AA16: =IFERROR(VLOOKUP("SV7_OPS",'Company 13'!$B:$E,4,0),"") -> 1 | AB16: =IFERROR(VLOOKUP("SC1_DATASENS",'Company 13'!$B:$E,4,0),"") -> 1 | AC16: =IFERROR(VLOOKUP("SC2_COMPLIANCE",'Company 13'!$B:$E,4,0),"") -> 1 | AD16: =IFERROR(VLOOKUP("SC3_TRUST",'Company 13'!$B:$E,4,0),"") -> 1 | AE16: =IFERROR(VLOOKUP("SC4_DATAPROC",'Company 13'!$B:$E,4,0),"") -> 1 | AF16: =IFERROR(VLOOKUP("SF1_REALTIME",'Company 13'!$B:$E,4,0),"") -> 0 | AG16: =IFERROR(VLOOKUP("SF2_ACCESS",'Company 13'!$B:$E,4,0),"") -> 1 | AH16: =IFERROR(VLOOKUP("SF3_UX",'Company 13'!$B:$E,4,0),"") -> 0 | AI16: =IFERROR(VLOOKUP("SF4_DECISION",'Company 13'!$B:$E,4,0),"") -> 1 | AJ16: =IFERROR(VLOOKUP("SF5_MASKING",'Company 13'!$B:$E,4,0),"") -> 1 | AK16: =IFERROR(VLOOKUP("SD1_TRENDS",'Company 13'!$B:$E,4,0),"") -> 1 | AL16: =IFERROR(VLOOKUP("SD2_MARKET",'Company 13'!$B:$E,4,0),"") -> 1 | AM16: =IFERROR(VLOOKUP("SD3_CATEGORY",'Company 13'!$B:$E,4,0),"") -> 1 | AN16: =IFERROR(VLOOKUP("SD4_SHIPMENT",'Company 13'!$B:$E,4,0),"") -> 1 | AO16: =IFERROR(VLOOKUP("SD5_LEAD",'Company 13'!$B:$E,4,0),"") -> 1 | AP16: =IFERROR(VLOOKUP("SD6_CONJOINT",'Company 13'!$B:$E,4,0),"") -> 0
B17: Company 14 | C17: =IFERROR(VLOOKUP("Interviewee Position",#REF!,2,0),"") | D17: =IFERROR(VLOOKUP("Company Industry",#REF!,2,0),"") | E17: =IFERROR(VLOOKUP("Company Sub-Industry",#REF!,2,0),"") | F17: =IFERROR(VLOOKUP("Company Size (Turnover)",#REF!,2,0),"") | G17: =IFERROR(VLOOKUP("Country",#REF!,2,0),"") | H17: =IFERROR(VLOOKUP("B1_INTEREST",#REF!,4,0),"") | I17: =IFERROR(VLOOKUP("B2_SHARING",#REF!,4,0),"") | J17: =IFERROR(VLOOKUP("B3_MONETIZE",#REF!,4,0),"") | K17: =IFERROR(VLOOKUP("B4_STRATEGIC",#REF!,4,0),"") | L17: =IFERROR(VLOOKUP("M1_AUTOMATED",#REF!,4,0),"") | M17: =IFERROR(VLOOKUP("M2_REALTIME",#REF!,4,0),"") | N17: =IFERROR(VLOOKUP("M3_STRATEGIC",#REF!,4,0),"") | O17: =IFERROR(VLOOKUP("M4_BREADTH",#REF!,4,0),"") | P17: =IFERROR(VLOOKUP("M5_DATATYPES",#REF!,4,0),"") | Q17: =IFERROR(VLOOKUP("M6_TRUST",#REF!,4,0),"") | R17: =IFERROR(VLOOKUP("M7_BARRIERS",#REF!,4,0),"") | S17: =IFERROR(VLOOKUP("M8_IMPACT",#REF!,4,0),"") | T17: =IFERROR(VLOOKUP("M9_WILLINGNESS",#REF!,4,0),"") | U17: =IFERROR(VLOOKUP("SV1_PRICING",#REF!,4,0),"") | V17: =IFERROR(VLOOKUP("SV2_PROMOTIONS",#REF!,4,0),"") | W17: =IFERROR(VLOOKUP("SV3_SUPPLYCHAIN",#REF!,4,0),"") | X17: =IFERROR(VLOOKUP("SV4_CATEGORY",#REF!,4,0),"") | Y17: =IFERROR(VLOOKUP("SV5_DEMAND",#REF!,4,0),"") | Z17: =IFERROR(VLOOKUP("SV6_ACCOUNT",#REF!,4,0),"") | AA17: =IFERROR(VLOOKUP("SV7_OPS",#REF!,4,0),"") | AB17: =IFERROR(VLOOKUP("SC1_DATASENS",#REF!,4,0),"") | AC17: =IFERROR(VLOOKUP("SC2_COMPLIANCE",#REF!,4,0),"") | AD17: =IFERROR(VLOOKUP("SC3_TRUST",#REF!,4,0),"") | AE17: =IFERROR(VLOOKUP("SC4_DATAPROC",#REF!,4,0),"") | AF17: =IFERROR(VLOOKUP("SF1_REALTIME",#REF!,4,0),"") | AG17: =IFERROR(VLOOKUP("SF2_ACCESS",#REF!,4,0),"") | AH17: =IFERROR(VLOOKUP("SF3_UX",#REF!,4,0),"") | AI17: =IFERROR(VLOOKUP("SF4_DECISION",#REF!,4,0),"") | AJ17: =IFERROR(VLOOKUP("SF5_MASKING",#REF!,4,0),"") | AK17: =IFERROR(VLOOKUP("SD1_TRENDS",#REF!,4,0),"") | AL17: =IFERROR(VLOOKUP("SD2_MARKET",#REF!,4,0),"") | AM17: =IFERROR(VLOOKUP("SD3_CATEGORY",#REF!,4,0),"") | AN17: =IFERROR(VLOOKUP("SD4_SHIPMENT",#REF!,4,0),"") | AO17: =IFERROR(VLOOKUP("SD5_LEAD",#REF!,4,0),"") | AP17: =IFERROR(VLOOKUP("SD6_CONJOINT",#REF!,4,0),"")
B18: Company 15 | C18: =IFERROR(VLOOKUP("Interviewee Position",#REF!,2,0),"") | D18: =IFERROR(VLOOKUP("Company Industry",#REF!,2,0),"") | E18: =IFERROR(VLOOKUP("Company Sub-Industry",#REF!,2,0),"") | F18: =IFERROR(VLOOKUP("Company Size (Turnover)",#REF!,2,0),"") | G18: =IFERROR(VLOOKUP("Country",#REF!,2,0),"") | H18: =IFERROR(VLOOKUP("B1_INTEREST",#REF!,4,0),"") | I18: =IFERROR(VLOOKUP("B2_SHARING",#REF!,4,0),"") | J18: =IFERROR(VLOOKUP("B3_MONETIZE",#REF!,4,0),"") | K18: =IFERROR(VLOOKUP("B4_STRATEGIC",#REF!,4,0),"") | L18: =IFERROR(VLOOKUP("M1_AUTOMATED",#REF!,4,0),"") | M18: =IFERROR(VLOOKUP("M2_REALTIME",#REF!,4,0),"") | N18: =IFERROR(VLOOKUP("M3_STRATEGIC",#REF!,4,0),"") | O18: =IFERROR(VLOOKUP("M4_BREADTH",#REF!,4,0),"") | P18: =IFERROR(VLOOKUP("M5_DATATYPES",#REF!,4,0),"") | Q18: =IFERROR(VLOOKUP("M6_TRUST",#REF!,4,0),"") | R18: =IFERROR(VLOOKUP("M7_BARRIERS",#REF!,4,0),"") | S18: =IFERROR(VLOOKUP("M8_IMPACT",#REF!,4,0),"") | T18: =IFERROR(VLOOKUP("M9_WILLINGNESS",#REF!,4,0),"") | U18: =IFERROR(VLOOKUP("SV1_PRICING",#REF!,4,0),"") | V18: =IFERROR(VLOOKUP("SV2_PROMOTIONS",#REF!,4,0),"") | W18: =IFERROR(VLOOKUP("SV3_SUPPLYCHAIN",#REF!,4,0),"") | X18: =IFERROR(VLOOKUP("SV4_CATEGORY",#REF!,4,0),"") | Y18: =IFERROR(VLOOKUP("SV5_DEMAND",#REF!,4,0),"") | Z18: =IFERROR(VLOOKUP("SV6_ACCOUNT",#REF!,4,0),"") | AA18: =IFERROR(VLOOKUP("SV7_OPS",#REF!,4,0),"") | AB18: =IFERROR(VLOOKUP("SC1_DATASENS",#REF!,4,0),"") | AC18: =IFERROR(VLOOKUP("SC2_COMPLIANCE",#REF!,4,0),"") | AD18: =IFERROR(VLOOKUP("SC3_TRUST",#REF!,4,0),"") | AE18: =IFERROR(VLOOKUP("SC4_DATAPROC",#REF!,4,0),"") | AF18: =IFERROR(VLOOKUP("SF1_REALTIME",#REF!,4,0),"") | AG18: =IFERROR(VLOOKUP("SF2_ACCESS",#REF!,4,0),"") | AH18: =IFERROR(VLOOKUP("SF3_UX",#REF!,4,0),"") | AI18: =IFERROR(VLOOKUP("SF4_DECISION",#REF!,4,0),"") | AJ18: =IFERROR(VLOOKUP("SF5_MASKING",#REF!,4,0),"") | AK18: =IFERROR(VLOOKUP("SD1_TRENDS",#REF!,4,0),"") | AL18: =IFERROR(VLOOKUP("SD2_MARKET",#REF!,4,0),"") | AM18: =IFERROR(VLOOKUP("SD3_CATEGORY",#REF!,4,0),"") | AN18: =IFERROR(VLOOKUP("SD4_SHIPMENT",#REF!,4,0),"") | AO18: =IFERROR(VLOOKUP("SD5_LEAD",#REF!,4,0),"") | AP18: =IFERROR(VLOOKUP("SD6_CONJOINT",#REF!,4,0),"")
B19: Company 16 | C19: =IFERROR(VLOOKUP("Interviewee Position",#REF!,2,0),"") | D19: =IFERROR(VLOOKUP("Company Industry",#REF!,2,0),"") | E19: =IFERROR(VLOOKUP("Company Sub-Industry",#REF!,2,0),"") | F19: =IFERROR(VLOOKUP("Company Size (Turnover)",#REF!,2,0),"") | G19: =IFERROR(VLOOKUP("Country",#REF!,2,0),"") | H19: =IFERROR(VLOOKUP("B1_INTEREST",#REF!,4,0),"") | I19: =IFERROR(VLOOKUP("B2_SHARING",#REF!,4,0),"") | J19: =IFERROR(VLOOKUP("B3_MONETIZE",#REF!,4,0),"") | K19: =IFERROR(VLOOKUP("B4_STRATEGIC",#REF!,4,0),"") | L19: =IFERROR(VLOOKUP("M1_AUTOMATED",#REF!,4,0),"") | M19: =IFERROR(VLOOKUP("M2_REALTIME",#REF!,4,0),"") | N19: =IFERROR(VLOOKUP("M3_STRATEGIC",#REF!,4,0),"") | O19: =IFERROR(VLOOKUP("M4_BREADTH",#REF!,4,0),"") | P19: =IFERROR(VLOOKUP("M5_DATATYPES",#REF!,4,0),"") | Q19: =IFERROR(VLOOKUP("M6_TRUST",#REF!,4,0),"") | R19: =IFERROR(VLOOKUP("M7_BARRIERS",#REF!,4,0),"") | S19: =IFERROR(VLOOKUP("M8_IMPACT",#REF!,4,0),"") | T19: =IFERROR(VLOOKUP("M9_WILLINGNESS",#REF!,4,0),"") | U19: =IFERROR(VLOOKUP("SV1_PRICING",#REF!,4,0),"") | V19: =IFERROR(VLOOKUP("SV2_PROMOTIONS",#REF!,4,0),"") | W19: =IFERROR(VLOOKUP("SV3_SUPPLYCHAIN",#REF!,4,0),"") | X19: =IFERROR(VLOOKUP("SV4_CATEGORY",#REF!,4,0),"") | Y19: =IFERROR(VLOOKUP("SV5_DEMAND",#REF!,4,0),"") | Z19: =IFERROR(VLOOKUP("SV6_ACCOUNT",#REF!,4,0),"") | AA19: =IFERROR(VLOOKUP("SV7_OPS",#REF!,4,0),"") | AB19: =IFERROR(VLOOKUP("SC1_DATASENS",#REF!,4,0),"") | AC19: =IFERROR(VLOOKUP("SC2_COMPLIANCE",#REF!,4,0),"") | AD19: =IFERROR(VLOOKUP("SC3_TRUST",#REF!,4,0),"") | AE19: =IFERROR(VLOOKUP("SC4_DATAPROC",#REF!,4,0),"") | AF19: =IFERROR(VLOOKUP("SF1_REALTIME",#REF!,4,0),"") | AG19: =IFERROR(VLOOKUP("SF2_ACCESS",#REF!,4,0),"") | AH19: =IFERROR(VLOOKUP("SF3_UX",#REF!,4,0),"") | AI19: =IFERROR(VLOOKUP("SF4_DECISION",#REF!,4,0),"") | AJ19: =IFERROR(VLOOKUP("SF5_MASKING",#REF!,4,0),"") | AK19: =IFERROR(VLOOKUP("SD1_TRENDS",#REF!,4,0),"") | AL19: =IFERROR(VLOOKUP("SD2_MARKET",#REF!,4,0),"") | AM19: =IFERROR(VLOOKUP("SD3_CATEGORY",#REF!,4,0),"") | AN19: =IFERROR(VLOOKUP("SD4_SHIPMENT",#REF!,4,0),"") | AO19: =IFERROR(VLOOKUP("SD5_LEAD",#REF!,4,0),"") | AP19: =IFERROR(VLOOKUP("SD6_CONJOINT",#REF!,4,0),"")
B20: Company 17 | C20: =IFERROR(VLOOKUP("Interviewee Position",#REF!,2,0),"") | D20: =IFERROR(VLOOKUP("Company Industry",#REF!,2,0),"") | E20: =IFERROR(VLOOKUP("Company Sub-Industry",#REF!,2,0),"") | F20: =IFERROR(VLOOKUP("Company Size (Turnover)",#REF!,2,0),"") | G20: =IFERROR(VLOOKUP("Country",#REF!,2,0),"") | H20: =IFERROR(VLOOKUP("B1_INTEREST",#REF!,4,0),"") | I20: =IFERROR(VLOOKUP("B2_SHARING",#REF!,4,0),"") | J20: =IFERROR(VLOOKUP("B3_MONETIZE",#REF!,4,0),"") | K20: =IFERROR(VLOOKUP("B4_STRATEGIC",#REF!,4,0),"") | L20: =IFERROR(VLOOKUP("M1_AUTOMATED",#REF!,4,0),"") | M20: =IFERROR(VLOOKUP("M2_REALTIME",#REF!,4,0),"") | N20: =IFERROR(VLOOKUP("M3_STRATEGIC",#REF!,4,0),"") | O20: =IFERROR(VLOOKUP("M4_BREADTH",#REF!,4,0),"") | P20: =IFERROR(VLOOKUP("M5_DATATYPES",#REF!,4,0),"") | Q20: =IFERROR(VLOOKUP("M6_TRUST",#REF!,4,0),"") | R20: =IFERROR(VLOOKUP("M7_BARRIERS",#REF!,4,0),"") | S20: =IFERROR(VLOOKUP("M8_IMPACT",#REF!,4,0),"") | T20: =IFERROR(VLOOKUP("M9_WILLINGNESS",#REF!,4,0),"") | U20: =IFERROR(VLOOKUP("SV1_PRICING",#REF!,4,0),"") | V20: =IFERROR(VLOOKUP("SV2_PROMOTIONS",#REF!,4,0),"") | W20: =IFERROR(VLOOKUP("SV3_SUPPLYCHAIN",#REF!,4,0),"") | X20: =IFERROR(VLOOKUP("SV4_CATEGORY",#REF!,4,0),"") | Y20: =IFERROR(VLOOKUP("SV5_DEMAND",#REF!,4,0),"") | Z20: =IFERROR(VLOOKUP("SV6_ACCOUNT",#REF!,4,0),"") | AA20: =IFERROR(VLOOKUP("SV7_OPS",#REF!,4,0),"") | AB20: =IFERROR(VLOOKUP("SC1_DATASENS",#REF!,4,0),"") | AC20: =IFERROR(VLOOKUP("SC2_COMPLIANCE",#REF!,4,0),"") | AD20: =IFERROR(VLOOKUP("SC3_TRUST",#REF!,4,0),"") | AE20: =IFERROR(VLOOKUP("SC4_DATAPROC",#REF!,4,0),"") | AF20: =IFERROR(VLOOKUP("SF1_REALTIME",#REF!,4,0),"") | AG20: =IFERROR(VLOOKUP("SF2_ACCESS",#REF!,4,0),"") | AH20: =IFERROR(VLOOKUP("SF3_UX",#REF!,4,0),"") | AI20: =IFERROR(VLOOKUP("SF4_DECISION",#REF!,4,0),"") | AJ20: =IFERROR(VLOOKUP("SF5_MASKING",#REF!,4,0),"") | AK20: =IFERROR(VLOOKUP("SD1_TRENDS",#REF!,4,0),"") | AL20: =IFERROR(VLOOKUP("SD2_MARKET",#REF!,4,0),"") | AM20: =IFERROR(VLOOKUP("SD3_CATEGORY",#REF!,4,0),"") | AN20: =IFERROR(VLOOKUP("SD4_SHIPMENT",#REF!,4,0),"") | AO20: =IFERROR(VLOOKUP("SD5_LEAD",#REF!,4,0),"") | AP20: =IFERROR(VLOOKUP("SD6_CONJOINT",#REF!,4,0),"")
B21: Company 18 | C21: =IFERROR(VLOOKUP("Interviewee Position",'Company 18'!$B:$C,2,0),"") -> 0 | D21: =IFERROR(VLOOKUP("Company Industry",'Company 18'!$B:$C,2,0),"") -> 0 | E21: =IFERROR(VLOOKUP("Company Sub-Industry",'Company 18'!$B:$C,2,0),"") -> 0 | F21: =IFERROR(VLOOKUP("Company Size (Turnover)",'Company 18'!$B:$C,2,0),"") -> 0 | G21: =IFERROR(VLOOKUP("Country",'Company 18'!$B:$C,2,0),"") -> 0 | H21: =IFERROR(VLOOKUP("B1_INTEREST",'Company 18'!$B:$E,4,0),"") -> 0 | I21: =IFERROR(VLOOKUP("B2_SHARING",'Company 18'!$B:$E,4,0),"") -> 0 | J21: =IFERROR(VLOOKUP("B3_MONETIZE",'Company 18'!$B:$E,4,0),"") -> 0 | K21: =IFERROR(VLOOKUP("B4_STRATEGIC",'Company 18'!$B:$E,4,0),"") -> 0 | L21: =IFERROR(VLOOKUP("M1_AUTOMATED",'Company 18'!$B:$E,4,0),"") -> 0 | M21: =IFERROR(VLOOKUP("M2_REALTIME",'Company 18'!$B:$E,4,0),"") -> 0 | N21: =IFERROR(VLOOKUP("M3_STRATEGIC",'Company 18'!$B:$E,4,0),"") -> 0 | O21: =IFERROR(VLOOKUP("M4_BREADTH",'Company 18'!$B:$E,4,0),"") -> 0 | P21: =IFERROR(VLOOKUP("M5_DATATYPES",'Company 18'!$B:$E,4,0),"") -> 0 | Q21: =IFERROR(VLOOKUP("M6_TRUST",'Company 18'!$B:$E,4,0),"") -> 0 | R21: =IFERROR(VLOOKUP("M7_BARRIERS",'Company 18'!$B:$E,4,0),"") -> 0 | S21: =IFERROR(VLOOKUP("M8_IMPACT",'Company 18'!$B:$E,4,0),"") -> 0 | T21: =IFERROR(VLOOKUP("M9_WILLINGNESS",'Company 18'!$B:$E,4,0),"") -> 0 | U21: =IFERROR(VLOOKUP("SV1_PRICING",'Company 18'!$B:$E,4,0),"") -> 0 | V21: =IFERROR(VLOOKUP("SV2_PROMOTIONS",'Company 18'!$B:$E,4,0),"") -> 0 | W21: =IFERROR(VLOOKUP("SV3_SUPPLYCHAIN",'Company 18'!$B:$E,4,0),"") -> 0 | X21: =IFERROR(VLOOKUP("SV4_CATEGORY",'Company 18'!$B:$E,4,0),"") -> 0 | Y21: =IFERROR(VLOOKUP("SV5_DEMAND",'Company 18'!$B:$E,4,0),"") -> 0 | Z21: =IFERROR(VLOOKUP("SV6_ACCOUNT",'Company 18'!$B:$E,4,0),"") -> 0 | AA21: =IFERROR(VLOOKUP("SV7_OPS",'Company 18'!$B:$E,4,0),"") -> 0 | AB21: =IFERROR(VLOOKUP("SC1_DATASENS",'Company 18'!$B:$E,4,0),"") -> 0 | AC21: =IFERROR(VLOOKUP("SC2_COMPLIANCE",'Company 18'!$B:$E,4,0),"") -> 0 | AD21: =IFERROR(VLOOKUP("SC3_TRUST",'Company 18'!$B:$E,4,0),"") -> 0 | AE21: =IFERROR(VLOOKUP("SC4_DATAPROC",'Company 18'!$B:$E,4,0),"") -> 0 | AF21: =IFERROR(VLOOKUP("SF1_REALTIME",'Company 18'!$B:$E,4,0),"") -> 0 | AG21: =IFERROR(VLOOKUP("SF2_ACCESS",'Company 18'!$B:$E,4,0),"") -> 0 | AH21: =IFERROR(VLOOKUP("SF3_UX",'Company 18'!$B:$E,4,0),"") -> 0 | AI21: =IFERROR(VLOOKUP("SF4_DECISION",'Company 18'!$B:$E,4,0),"") -> 0 | AJ21: =IFERROR(VLOOKUP("SF5_MASKING",'Company 18'!$B:$E,4,0),"") -> 0 | AK21: =IFERROR(VLOOKUP("SD1_TRENDS",'Company 18'!$B:$E,4,0),"") -> 0 | AL21: =IFERROR(VLOOKUP("SD2_MARKET",'Company 18'!$B:$E,4,0),"") -> 0 | AM21: =IFERROR(VLOOKUP("SD3_CATEGORY",'Company 18'!$B:$E,4,0),"") -> 0 | AN21: =IFERROR(VLOOKUP("SD4_SHIPMENT",'Company 18'!$B:$E,4,0),"") -> 0 | AO21: =IFERROR(VLOOKUP("SD5_LEAD",'Company 18'!$B:$E,4,0),"") -> 0 | AP21: =IFERROR(VLOOKUP("SD6_CONJOINT",'Company 18'!$B:$E,4,0),"") -> 0
B22: Company 19 | C22: =IFERROR(VLOOKUP("Interviewee Position",'Company 19'!$B:$C,2,0),"") -> 0 | D22: =IFERROR(VLOOKUP("Company Industry",'Company 19'!$B:$C,2,0),"") -> 0 | E22: =IFERROR(VLOOKUP("Company Sub-Industry",'Company 19'!$B:$C,2,0),"") -> 0 | F22: =IFERROR(VLOOKUP("Company Size (Turnover)",'Company 19'!$B:$C,2,0),"") -> 0 | G22: =IFERROR(VLOOKUP("Country",'Company 19'!$B:$C,2,0),"") -> 0 | H22: =IFERROR(VLOOKUP("B1_INTEREST",'Company 19'!$B:$E,4,0),"") -> 0 | I22: =IFERROR(VLOOKUP("B2_SHARING",'Company 19'!$B:$E,4,0),"") -> 0 | J22: =IFERROR(VLOOKUP("B3_MONETIZE",'Company 19'!$B:$E,4,0),"") -> 0 | K22: =IFERROR(VLOOKUP("B4_STRATEGIC",'Company 19'!$B:$E,4,0),"") -> 0 | L22: =IFERROR(VLOOKUP("M1_AUTOMATED",'Company 19'!$B:$E,4,0),"") -> 0 | M22: =IFERROR(VLOOKUP("M2_REALTIME",'Company 19'!$B:$E,4,0),"") -> 0 | N22: =IFERROR(VLOOKUP("M3_STRATEGIC",'Company 19'!$B:$E,4,0),"") -> 0 | O22: =IFERROR(VLOOKUP("M4_BREADTH",'Company 19'!$B:$E,4,0),"") -> 0 | P22: =IFERROR(VLOOKUP("M5_DATATYPES",'Company 19'!$B:$E,4,0),"") -> 0 | Q22: =IFERROR(VLOOKUP("M6_TRUST",'Company 19'!$B:$E,4,0),"") -> 0 | R22: =IFERROR(VLOOKUP("M7_BARRIERS",'Company 19'!$B:$E,4,0),"") -> 0 | S22: =IFERROR(VLOOKUP("M8_IMPACT",'Company 19'!$B:$E,4,0),"") -> 0 | T22: =IFERROR(VLOOKUP("M9_WILLINGNESS",'Company 19'!$B:$E,4,0),"") -> 0 | U22: =IFERROR(VLOOKUP("SV1_PRICING",'Company 19'!$B:$E,4,0),"") -> 0 | V22: =IFERROR(VLOOKUP("SV2_PROMOTIONS",'Company 19'!$B:$E,4,0),"") -> 0 | W22: =IFERROR(VLOOKUP("SV3_SUPPLYCHAIN",'Company 19'!$B:$E,4,0),"") -> 0 | X22: =IFERROR(VLOOKUP("SV4_CATEGORY",'Company 19'!$B:$E,4,0),"") -> 0 | Y22: =IFERROR(VLOOKUP("SV5_DEMAND",'Company 19'!$B:$E,4,0),"") -> 0 | Z22: =IFERROR(VLOOKUP("SV6_ACCOUNT",'Company 19'!$B:$E,4,0),"") -> 0 | AA22: =IFERROR(VLOOKUP("SV7_OPS",'Company 19'!$B:$E,4,0),"") -> 0 | AB22: =IFERROR(VLOOKUP("SC1_DATASENS",'Company 19'!$B:$E,4,0),"") -> 0 | AC22: =IFERROR(VLOOKUP("SC2_COMPLIANCE",'Company 19'!$B:$E,4,0),"") -> 0 | AD22: =IFERROR(VLOOKUP("SC3_TRUST",'Company 19'!$B:$E,4,0),"") -> 0 | AE22: =IFERROR(VLOOKUP("SC4_DATAPROC",'Company 19'!$B:$E,4,0),"") -> 0 | AF22: =IFERROR(VLOOKUP("SF1_REALTIME",'Company 19'!$B:$E,4,0),"") -> 0 | AG22: =IFERROR(VLOOKUP("SF2_ACCESS",'Company 19'!$B:$E,4,0),"") -> 0 | AH22: =IFERROR(VLOOKUP("SF3_UX",'Company 19'!$B:$E,4,0),"") -> 0 | AI22: =IFERROR(VLOOKUP("SF4_DECISION",'Company 19'!$B:$E,4,0),"") -> 0 | AJ22: =IFERROR(VLOOKUP("SF5_MASKING",'Company 19'!$B:$E,4,0),"") -> 0 | AK22: =IFERROR(VLOOKUP("SD1_TRENDS",'Company 19'!$B:$E,4,0),"") -> 0 | AL22: =IFERROR(VLOOKUP("SD2_MARKET",'Company 19'!$B:$E,4,0),"") -> 0 | AM22: =IFERROR(VLOOKUP("SD3_CATEGORY",'Company 19'!$B:$E,4,0),"") -> 0 | AN22: =IFERROR(VLOOKUP("SD4_SHIPMENT",'Company 19'!$B:$E,4,0),"") -> 0 | AO22: =IFERROR(VLOOKUP("SD5_LEAD",'Company 19'!$B:$E,4,0),"") -> 0 | AP22: =IFERROR(VLOOKUP("SD6_CONJOINT",'Company 19'!$B:$E,4,0),"") -> 0
B23: Company 20 | C23: =IFERROR(VLOOKUP("Interviewee Position",'Company 20'!$B:$C,2,0),"") -> 0 | D23: =IFERROR(VLOOKUP("Company Industry",'Company 20'!$B:$C,2,0),"") -> 0 | E23: =IFERROR(VLOOKUP("Company Sub-Industry",'Company 20'!$B:$C,2,0),"") -> 0 | F23: =IFERROR(VLOOKUP("Company Size (Turnover)",'Company 20'!$B:$C,2,0),"") -> 0 | G23: =IFERROR(VLOOKUP("Country",'Company 20'!$B:$C,2,0),"") -> 0 | H23: =IFERROR(VLOOKUP("B1_INTEREST",'Company 20'!$B:$E,4,0),"") -> 0 | I23: =IFERROR(VLOOKUP("B2_SHARING",'Company 20'!$B:$E,4,0),"") -> 0 | J23: =IFERROR(VLOOKUP("B3_MONETIZE",'Company 20'!$B:$E,4,0),"") -> 0 | K23: =IFERROR(VLOOKUP("B4_STRATEGIC",'Company 20'!$B:$E,4,0),"") -> 0 | L23: =IFERROR(VLOOKUP("M1_AUTOMATED",'Company 20'!$B:$E,4,0),"") -> 0 | M23: =IFERROR(VLOOKUP("M2_REALTIME",'Company 20'!$B:$E,4,0),"") -> 0 | N23: =IFERROR(VLOOKUP("M3_STRATEGIC",'Company 20'!$B:$E,4,0),"") -> 0 | O23: =IFERROR(VLOOKUP("M4_BREADTH",'Company 20'!$B:$E,4,0),"") -> 0 | P23: =IFERROR(VLOOKUP("M5_DATATYPES",'Company 20'!$B:$E,4,0),"") -> 0 | Q23: =IFERROR(VLOOKUP("M6_TRUST",'Company 20'!$B:$E,4,0),"") -> 0 | R23: =IFERROR(VLOOKUP("M7_BARRIERS",'Company 20'!$B:$E,4,0),"") -> 0 | S23: =IFERROR(VLOOKUP("M8_IMPACT",'Company 20'!$B:$E,4,0),"") -> 0 | T23: =IFERROR(VLOOKUP("M9_WILLINGNESS",'Company 20'!$B:$E,4,0),"") -> 0 | U23: =IFERROR(VLOOKUP("SV1_PRICING",'Company 20'!$B:$E,4,0),"") -> 0 | V23: =IFERROR(VLOOKUP("SV2_PROMOTIONS",'Company 20'!$B:$E,4,0),"") -> 0 | W23: =IFERROR(VLOOKUP("SV3_SUPPLYCHAIN",'Company 20'!$B:$E,4,0),"") -> 0 | X23: =IFERROR(VLOOKUP("SV4_CATEGORY",'Company 20'!$B:$E,4,0),"") -> 0 | Y23: =IFERROR(VLOOKUP("SV5_DEMAND",'Company 20'!$B:$E,4,0),"") -> 0 | Z23: =IFERROR(VLOOKUP("SV6_ACCOUNT",'Company 20'!$B:$E,4,0),"") -> 0 | AA23: =IFERROR(VLOOKUP("SV7_OPS",'Company 20'!$B:$E,4,0),"") -> 0 | AB23: =IFERROR(VLOOKUP("SC1_DATASENS",'Company 20'!$B:$E,4,0),"") -> 0 | AC23: =IFERROR(VLOOKUP("SC2_COMPLIANCE",'Company 20'!$B:$E,4,0),"") -> 0 | AD23: =IFERROR(VLOOKUP("SC3_TRUST",'Company 20'!$B:$E,4,0),"") -> 0 | AE23: =IFERROR(VLOOKUP("SC4_DATAPROC",'Company 20'!$B:$E,4,0),"") -> 0 | AF23: =IFERROR(VLOOKUP("SF1_REALTIME",'Company 20'!$B:$E,4,0),"") -> 0 | AG23: =IFERROR(VLOOKUP("SF2_ACCESS",'Company 20'!$B:$E,4,0),"") -> 0 | AH23: =IFERROR(VLOOKUP("SF3_UX",'Company 20'!$B:$E,4,0),"") -> 0 | AI23: =IFERROR(VLOOKUP("SF4_DECISION",'Company 20'!$B:$E,4,0),"") -> 0 | AJ23: =IFERROR(VLOOKUP("SF5_MASKING",'Company 20'!$B:$E,4,0),"") -> 0 | AK23: =IFERROR(VLOOKUP("SD1_TRENDS",'Company 20'!$B:$E,4,0),"") -> 0 | AL23: =IFERROR(VLOOKUP("SD2_MARKET",'Company 20'!$B:$E,4,0),"") -> 0 | AM23: =IFERROR(VLOOKUP("SD3_CATEGORY",'Company 20'!$B:$E,4,0),"") -> 0 | AN23: =IFERROR(VLOOKUP("SD4_SHIPMENT",'Company 20'!$B:$E,4,0),"") -> 0 | AO23: =IFERROR(VLOOKUP("SD5_LEAD",'Company 20'!$B:$E,4,0),"") -> 0 | AP23: =IFERROR(VLOOKUP("SD6_CONJOINT",'Company 20'!$B:$E,4,0),"") -> 0
B24: Company 21 | C24: =IFERROR(VLOOKUP("Interviewee Position",'Company 21'!$B:$C,2,0),"") -> 0 | D24: =IFERROR(VLOOKUP("Company Industry",'Company 21'!$B:$C,2,0),"") -> 0 | E24: =IFERROR(VLOOKUP("Company Sub-Industry",'Company 21'!$B:$C,2,0),"") -> 0 | F24: =IFERROR(VLOOKUP("Company Size (Turnover)",'Company 21'!$B:$C,2,0),"") -> 0 | G24: =IFERROR(VLOOKUP("Country",'Company 21'!$B:$C,2,0),"") -> 0 | H24: =IFERROR(VLOOKUP("B1_INTEREST",'Company 21'!$B:$E,4,0),"") -> 0 | I24: =IFERROR(VLOOKUP("B2_SHARING",'Company 21'!$B:$E,4,0),"") -> 0 | J24: =IFERROR(VLOOKUP("B3_MONETIZE",'Company 21'!$B:$E,4,0),"") -> 0 | K24: =IFERROR(VLOOKUP("B4_STRATEGIC",'Company 21'!$B:$E,4,0),"") -> 0 | L24: =IFERROR(VLOOKUP("M1_AUTOMATED",'Company 21'!$B:$E,4,0),"") -> 0 | M24: =IFERROR(VLOOKUP("M2_REALTIME",'Company 21'!$B:$E,4,0),"") -> 0 | N24: =IFERROR(VLOOKUP("M3_STRATEGIC",'Company 21'!$B:$E,4,0),"") -> 0 | O24: =IFERROR(VLOOKUP("M4_BREADTH",'Company 21'!$B:$E,4,0),"") -> 0 | P24: =IFERROR(VLOOKUP("M5_DATATYPES",'Company 21'!$B:$E,4,0),"") -> 0 | Q24: =IFERROR(VLOOKUP("M6_TRUST",'Company 21'!$B:$E,4,0),"") -> 0 | R24: =IFERROR(VLOOKUP("M7_BARRIERS",'Company 21'!$B:$E,4,0),"") -> 0 | S24: =IFERROR(VLOOKUP("M8_IMPACT",'Company 21'!$B:$E,4,0),"") -> 0 | T24: =IFERROR(VLOOKUP("M9_WILLINGNESS",'Company 21'!$B:$E,4,0),"") -> 0 | U24: =IFERROR(VLOOKUP("SV1_PRICING",'Company 21'!$B:$E,4,0),"") -> 0 | V24: =IFERROR(VLOOKUP("SV2_PROMOTIONS",'Company 21'!$B:$E,4,0),"") -> 0 | W24: =IFERROR(VLOOKUP("SV3_SUPPLYCHAIN",'Company 21'!$B:$E,4,0),"") -> 0 | X24: =IFERROR(VLOOKUP("SV4_CATEGORY",'Company 21'!$B:$E,4,0),"") -> 0 | Y24: =IFERROR(VLOOKUP("SV5_DEMAND",'Company 21'!$B:$E,4,0),"") -> 0 | Z24: =IFERROR(VLOOKUP("SV6_ACCOUNT",'Company 21'!$B:$E,4,0),"") -> 0 | AA24: =IFERROR(VLOOKUP("SV7_OPS",'Company 21'!$B:$E,4,0),"") -> 0 | AB24: =IFERROR(VLOOKUP("SC1_DATASENS",'Company 21'!$B:$E,4,0),"") -> 0 | AC24: =IFERROR(VLOOKUP("SC2_COMPLIANCE",'Company 21'!$B:$E,4,0),"") -> 0 | AD24: =IFERROR(VLOOKUP("SC3_TRUST",'Company 21'!$B:$E,4,0),"") -> 0 | AE24: =IFERROR(VLOOKUP("SC4_DATAPROC",'Company 21'!$B:$E,4,0),"") -> 0 | AF24: =IFERROR(VLOOKUP("SF1_REALTIME",'Company 21'!$B:$E,4,0),"") -> 0 | AG24: =IFERROR(VLOOKUP("SF2_ACCESS",'Company 21'!$B:$E,4,0),"") -> 0 | AH24: =IFERROR(VLOOKUP("SF3_UX",'Company 21'!$B:$E,4,0),"") -> 0 | AI24: =IFERROR(VLOOKUP("SF4_DECISION",'Company 21'!$B:$E,4,0),"") -> 0 | AJ24: =IFERROR(VLOOKUP("SF5_MASKING",'Company 21'!$B:$E,4,0),"") -> 0 | AK24: =IFERROR(VLOOKUP("SD1_TRENDS",'Company 21'!$B:$E,4,0),"") -> 0 | AL24: =IFERROR(VLOOKUP("SD2_MARKET",'Company 21'!$B:$E,4,0),"") -> 0 | AM24: =IFERROR(VLOOKUP("SD3_CATEGORY",'Company 21'!$B:$E,4,0),"") -> 0 | AN24: =IFERROR(VLOOKUP("SD4_SHIPMENT",'Company 21'!$B:$E,4,0),"") -> 0 | AO24: =IFERROR(VLOOKUP("SD5_LEAD",'Company 21'!$B:$E,4,0),"") -> 0 | AP24: =IFERROR(VLOOKUP("SD6_CONJOINT",'Company 21'!$B:$E,4,0),"") -> 0
B25: Company 22 | C25: =IFERROR(VLOOKUP("Interviewee Position",'Company 22'!$B:$C,2,0),"") -> 0 | D25: =IFERROR(VLOOKUP("Company Industry",'Company 22'!$B:$C,2,0),"") -> 0 | E25: =IFERROR(VLOOKUP("Company Sub-Industry",'Company 22'!$B:$C,2,0),"") -> 0 | F25: =IFERROR(VLOOKUP("Company Size (Turnover)",'Company 22'!$B:$C,2,0),"") -> 0 | G25: =IFERROR(VLOOKUP("Country",'Company 22'!$B:$C,2,0),"") -> 0 | H25: =IFERROR(VLOOKUP("B1_INTEREST",'Company 22'!$B:$E,4,0),"") -> 0 | I25: =IFERROR(VLOOKUP("B2_SHARING",'Company 22'!$B:$E,4,0),"") -> 0 | J25: =IFERROR(VLOOKUP("B3_MONETIZE",'Company 22'!$B:$E,4,0),"") -> 0 | K25: =IFERROR(VLOOKUP("B4_STRATEGIC",'Company 22'!$B:$E,4,0),"") -> 0 | L25: =IFERROR(VLOOKUP("M1_AUTOMATED",'Company 22'!$B:$E,4,0),"") -> 0 | M25: =IFERROR(VLOOKUP("M2_REALTIME",'Company 22'!$B:$E,4,0),"") -> 0 | N25: =IFERROR(VLOOKUP("M3_STRATEGIC",'Company 22'!$B:$E,4,0),"") -> 0 | O25: =IFERROR(VLOOKUP("M4_BREADTH",'Company 22'!$B:$E,4,0),"") -> 0 | P25: =IFERROR(VLOOKUP("M5_DATATYPES",'Company 22'!$B:$E,4,0),"") -> 0 | Q25: =IFERROR(VLOOKUP("M6_TRUST",'Company 22'!$B:$E,4,0),"") -> 0 | R25: =IFERROR(VLOOKUP("M7_BARRIERS",'Company 22'!$B:$E,4,0),"") -> 0 | S25: =IFERROR(VLOOKUP("M8_IMPACT",'Company 22'!$B:$E,4,0),"") -> 0 | T25: =IFERROR(VLOOKUP("M9_WILLINGNESS",'Company 22'!$B:$E,4,0),"") -> 0 | U25: =IFERROR(VLOOKUP("SV1_PRICING",'Company 22'!$B:$E,4,0),"") -> 0 | V25: =IFERROR(VLOOKUP("SV2_PROMOTIONS",'Company 22'!$B:$E,4,0),"") -> 0 | W25: =IFERROR(VLOOKUP("SV3_SUPPLYCHAIN",'Company 22'!$B:$E,4,0),"") -> 0 | X25: =IFERROR(VLOOKUP("SV4_CATEGORY",'Company 22'!$B:$E,4,0),"") -> 0 | Y25: =IFERROR(VLOOKUP("SV5_DEMAND",'Company 22'!$B:$E,4,0),"") -> 0 | Z25: =IFERROR(VLOOKUP("SV6_ACCOUNT",'Company 22'!$B:$E,4,0),"") -> 0 | AA25: =IFERROR(VLOOKUP("SV7_OPS",'Company 22'!$B:$E,4,0),"") -> 0 | AB25: =IFERROR(VLOOKUP("SC1_DATASENS",'Company 22'!$B:$E,4,0),"") -> 0 | AC25: =IFERROR(VLOOKUP("SC2_COMPLIANCE",'Company 22'!$B:$E,4,0),"") -> 0 | AD25: =IFERROR(VLOOKUP("SC3_TRUST",'Company 22'!$B:$E,4,0),"") -> 0 | AE25: =IFERROR(VLOOKUP("SC4_DATAPROC",'Company 22'!$B:$E,4,0),"") -> 0 | AF25: =IFERROR(VLOOKUP("SF1_REALTIME",'Company 22'!$B:$E,4,0),"") -> 0 | AG25: =IFERROR(VLOOKUP("SF2_ACCESS",'Company 22'!$B:$E,4,0),"") -> 0 | AH25: =IFERROR(VLOOKUP("SF3_UX",'Company 22'!$B:$E,4,0),"") -> 0 | AI25: =IFERROR(VLOOKUP("SF4_DECISION",'Company 22'!$B:$E,4,0),"") -> 0 | AJ25: =IFERROR(VLOOKUP("SF5_MASKING",'Company 22'!$B:$E,4,0),"") -> 0 | AK25: =IFERROR(VLOOKUP("SD1_TRENDS",'Company 22'!$B:$E,4,0),"") -> 0 | AL25: =IFERROR(VLOOKUP("SD2_MARKET",'Company 22'!$B:$E,4,0),"") -> 0 | AM25: =IFERROR(VLOOKUP("SD3_CATEGORY",'Company 22'!$B:$E,4,0),"") -> 0 | AN25: =IFERROR(VLOOKUP("SD4_SHIPMENT",'Company 22'!$B:$E,4,0),"") -> 0 | AO25: =IFERROR(VLOOKUP("SD5_LEAD",'Company 22'!$B:$E,4,0),"") -> 0 | AP25: =IFERROR(VLOOKUP("SD6_CONJOINT",'Company 22'!$B:$E,4,0),"") -> 0
B26: Company 23 | C26: =IFERROR(VLOOKUP("Interviewee Position",'Company 23'!$B:$C,2,0),"") -> 0 | D26: =IFERROR(VLOOKUP("Company Industry",'Company 23'!$B:$C,2,0),"") -> 0 | E26: =IFERROR(VLOOKUP("Company Sub-Industry",'Company 23'!$B:$C,2,0),"") -> 0 | F26: =IFERROR(VLOOKUP("Company Size (Turnover)",'Company 23'!$B:$C,2,0),"") -> 0 | G26: =IFERROR(VLOOKUP("Country",'Company 23'!$B:$C,2,0),"") -> 0 | H26: =IFERROR(VLOOKUP("B1_INTEREST",'Company 23'!$B:$E,4,0),"") -> 0 | I26: =IFERROR(VLOOKUP("B2_SHARING",'Company 23'!$B:$E,4,0),"") -> 0 | J26: =IFERROR(VLOOKUP("B3_MONETIZE",'Company 23'!$B:$E,4,0),"") -> 0 | K26: =IFERROR(VLOOKUP("B4_STRATEGIC",'Company 23'!$B:$E,4,0),"") -> 0 | L26: =IFERROR(VLOOKUP("M1_AUTOMATED",'Company 23'!$B:$E,4,0),"") -> 0 | M26: =IFERROR(VLOOKUP("M2_REALTIME",'Company 23'!$B:$E,4,0),"") -> 0 | N26: =IFERROR(VLOOKUP("M3_STRATEGIC",'Company 23'!$B:$E,4,0),"") -> 0 | O26: =IFERROR(VLOOKUP("M4_BREADTH",'Company 23'!$B:$E,4,0),"") -> 0 | P26: =IFERROR(VLOOKUP("M5_DATATYPES",'Company 23'!$B:$E,4,0),"") -> 0 | Q26: =IFERROR(VLOOKUP("M6_TRUST",'Company 23'!$B:$E,4,0),"") -> 0 | R26: =IFERROR(VLOOKUP("M7_BARRIERS",'Company 23'!$B:$E,4,0),"") -> 0 | S26: =IFERROR(VLOOKUP("M8_IMPACT",'Company 23'!$B:$E,4,0),"") -> 0 | T26: =IFERROR(VLOOKUP("M9_WILLINGNESS",'Company 23'!$B:$E,4,0),"") -> 0 | U26: =IFERROR(VLOOKUP("SV1_PRICING",'Company 23'!$B:$E,4,0),"") -> 0 | V26: =IFERROR(VLOOKUP("SV2_PROMOTIONS",'Company 23'!$B:$E,4,0),"") -> 0 | W26: =IFERROR(VLOOKUP("SV3_SUPPLYCHAIN",'Company 23'!$B:$E,4,0),"") -> 0 | X26: =IFERROR(VLOOKUP("SV4_CATEGORY",'Company 23'!$B:$E,4,0),"") -> 0 | Y26: =IFERROR(VLOOKUP("SV5_DEMAND",'Company 23'!$B:$E,4,0),"") -> 0 | Z26: =IFERROR(VLOOKUP("SV6_ACCOUNT",'Company 23'!$B:$E,4,0),"") -> 0 | AA26: =IFERROR(VLOOKUP("SV7_OPS",'Company 23'!$B:$E,4,0),"") -> 0 | AB26: =IFERROR(VLOOKUP("SC1_DATASENS",'Company 23'!$B:$E,4,0),"") -> 0 | AC26: =IFERROR(VLOOKUP("SC2_COMPLIANCE",'Company 23'!$B:$E,4,0),"") -> 0 | AD26: =IFERROR(VLOOKUP("SC3_TRUST",'Company 23'!$B:$E,4,0),"") -> 0 | AE26: =IFERROR(VLOOKUP("SC4_DATAPROC",'Company 23'!$B:$E,4,0),"") -> 0 | AF26: =IFERROR(VLOOKUP("SF1_REALTIME",'Company 23'!$B:$E,4,0),"") -> 0 | AG26: =IFERROR(VLOOKUP("SF2_ACCESS",'Company 23'!$B:$E,4,0),"") -> 0 | AH26: =IFERROR(VLOOKUP("SF3_UX",'Company 23'!$B:$E,4,0),"") -> 0 | AI26: =IFERROR(VLOOKUP("SF4_DECISION",'Company 23'!$B:$E,4,0),"") -> 0 | AJ26: =IFERROR(VLOOKUP("SF5_MASKING",'Company 23'!$B:$E,4,0),"") -> 0 | AK26: =IFERROR(VLOOKUP("SD1_TRENDS",'Company 23'!$B:$E,4,0),"") -> 0 | AL26: =IFERROR(VLOOKUP("SD2_MARKET",'Company 23'!$B:$E,4,0),"") -> 0 | AM26: =IFERROR(VLOOKUP("SD3_CATEGORY",'Company 23'!$B:$E,4,0),"") -> 0 | AN26: =IFERROR(VLOOKUP("SD4_SHIPMENT",'Company 23'!$B:$E,4,0),"") -> 0 | AO26: =IFERROR(VLOOKUP("SD5_LEAD",'Company 23'!$B:$E,4,0),"") -> 0 | AP26: =IFERROR(VLOOKUP("SD6_CONJOINT",'Company 23'!$B:$E,4,0),"") -> 0
B27: Company 24 | C27: =IFERROR(VLOOKUP("Interviewee Position",'Company 24'!$B:$C,2,0),"") -> 0 | D27: =IFERROR(VLOOKUP("Company Industry",'Company 24'!$B:$C,2,0),"") -> 0 | E27: =IFERROR(VLOOKUP("Company Sub-Industry",'Company 24'!$B:$C,2,0),"") -> 0 | F27: =IFERROR(VLOOKUP("Company Size (Turnover)",'Company 24'!$B:$C,2,0),"") -> 0 | G27: =IFERROR(VLOOKUP("Country",'Company 24'!$B:$C,2,0),"") -> 0 | H27: =IFERROR(VLOOKUP("B1_INTEREST",'Company 24'!$B:$E,4,0),"") -> 0 | I27: =IFERROR(VLOOKUP("B2_SHARING",'Company 24'!$B:$E,4,0),"") -> 0 | J27: =IFERROR(VLOOKUP("B3_MONETIZE",'Company 24'!$B:$E,4,0),"") -> 0 | K27: =IFERROR(VLOOKUP("B4_STRATEGIC",'Company 24'!$B:$E,4,0),"") -> 0 | L27: =IFERROR(VLOOKUP("M1_AUTOMATED",'Company 24'!$B:$E,4,0),"") -> 0 | M27: =IFERROR(VLOOKUP("M2_REALTIME",'Company 24'!$B:$E,4,0),"") -> 0 | N27: =IFERROR(VLOOKUP("M3_STRATEGIC",'Company 24'!$B:$E,4,0),"") -> 0 | O27: =IFERROR(VLOOKUP("M4_BREADTH",'Company 24'!$B:$E,4,0),"") -> 0 | P27: =IFERROR(VLOOKUP("M5_DATATYPES",'Company 24'!$B:$E,4,0),"") -> 0 | Q27: =IFERROR(VLOOKUP("M6_TRUST",'Company 24'!$B:$E,4,0),"") -> 0 | R27: =IFERROR(VLOOKUP("M7_BARRIERS",'Company 24'!$B:$E,4,0),"") -> 0 | S27: =IFERROR(VLOOKUP("M8_IMPACT",'Company 24'!$B:$E,4,0),"") -> 0 | T27: =IFERROR(VLOOKUP("M9_WILLINGNESS",'Company 24'!$B:$E,4,0),"") -> 0 | U27: =IFERROR(VLOOKUP("SV1_PRICING",'Company 24'!$B:$E,4,0),"") -> 0 | V27: =IFERROR(VLOOKUP("SV2_PROMOTIONS",'Company 24'!$B:$E,4,0),"") -> 0 | W27: =IFERROR(VLOOKUP("SV3_SUPPLYCHAIN",'Company 24'!$B:$E,4,0),"") -> 0 | X27: =IFERROR(VLOOKUP("SV4_CATEGORY",'Company 24'!$B:$E,4,0),"") -> 0 | Y27: =IFERROR(VLOOKUP("SV5_DEMAND",'Company 24'!$B:$E,4,0),"") -> 0 | Z27: =IFERROR(VLOOKUP("SV6_ACCOUNT",'Company 24'!$B:$E,4,0),"") -> 0 | AA27: =IFERROR(VLOOKUP("SV7_OPS",'Company 24'!$B:$E,4,0),"") -> 0 | AB27: =IFERROR(VLOOKUP("SC1_DATASENS",'Company 24'!$B:$E,4,0),"") -> 0 | AC27: =IFERROR(VLOOKUP("SC2_COMPLIANCE",'Company 24'!$B:$E,4,0),"") -> 0 | AD27: =IFERROR(VLOOKUP("SC3_TRUST",'Company 24'!$B:$E,4,0),"") -> 0 | AE27: =IFERROR(VLOOKUP("SC4_DATAPROC",'Company 24'!$B:$E,4,0),"") -> 0 | AF27: =IFERROR(VLOOKUP("SF1_REALTIME",'Company 24'!$B:$E,4,0),"") -> 0 | AG27: =IFERROR(VLOOKUP("SF2_ACCESS",'Company 24'!$B:$E,4,0),"") -> 0 | AH27: =IFERROR(VLOOKUP("SF3_UX",'Company 24'!$B:$E,4,0),"") -> 0 | AI27: =IFERROR(VLOOKUP("SF4_DECISION",'Company 24'!$B:$E,4,0),"") -> 0 | AJ27: =IFERROR(VLOOKUP("SF5_MASKING",'Company 24'!$B:$E,4,0),"") -> 0 | AK27: =IFERROR(VLOOKUP("SD1_TRENDS",'Company 24'!$B:$E,4,0),"") -> 0 | AL27: =IFERROR(VLOOKUP("SD2_MARKET",'Company 24'!$B:$E,4,0),"") -> 0 | AM27: =IFERROR(VLOOKUP("SD3_CATEGORY",'Company 24'!$B:$E,4,0),"") -> 0 | AN27: =IFERROR(VLOOKUP("SD4_SHIPMENT",'Company 24'!$B:$E,4,0),"") -> 0 | AO27: =IFERROR(VLOOKUP("SD5_LEAD",'Company 24'!$B:$E,4,0),"") -> 0 | AP27: =IFERROR(VLOOKUP("SD6_CONJOINT",'Company 24'!$B:$E,4,0),"") -> 0
B28: Company 25 | C28: =IFERROR(VLOOKUP("Interviewee Position",'Company 25'!$B:$C,2,0),"") -> 0 | D28: =IFERROR(VLOOKUP("Company Industry",'Company 25'!$B:$C,2,0),"") -> 0 | E28: =IFERROR(VLOOKUP("Company Sub-Industry",'Company 25'!$B:$C,2,0),"") -> 0 | F28: =IFERROR(VLOOKUP("Company Size (Turnover)",'Company 25'!$B:$C,2,0),"") -> 0 | G28: =IFERROR(VLOOKUP("Country",'Company 25'!$B:$C,2,0),"") -> 0 | H28: =IFERROR(VLOOKUP("B1_INTEREST",'Company 25'!$B:$E,4,0),"") -> 0 | I28: =IFERROR(VLOOKUP("B2_SHARING",'Company 25'!$B:$E,4,0),"") -> 0 | J28: =IFERROR(VLOOKUP("B3_MONETIZE",'Company 25'!$B:$E,4,0),"") -> 0 | K28: =IFERROR(VLOOKUP("B4_STRATEGIC",'Company 25'!$B:$E,4,0),"") -> 0 | L28: =IFERROR(VLOOKUP("M1_AUTOMATED",'Company 25'!$B:$E,4,0),"") -> 0 | M28: =IFERROR(VLOOKUP("M2_REALTIME",'Company 25'!$B:$E,4,0),"") -> 0 | N28: =IFERROR(VLOOKUP("M3_STRATEGIC",'Company 25'!$B:$E,4,0),"") -> 0 | O28: =IFERROR(VLOOKUP("M4_BREADTH",'Company 25'!$B:$E,4,0),"") -> 0 | P28: =IFERROR(VLOOKUP("M5_DATATYPES",'Company 25'!$B:$E,4,0),"") -> 0 | Q28: =IFERROR(VLOOKUP("M6_TRUST",'Company 25'!$B:$E,4,0),"") -> 0 | R28: =IFERROR(VLOOKUP("M7_BARRIERS",'Company 25'!$B:$E,4,0),"") -> 0 | S28: =IFERROR(VLOOKUP("M8_IMPACT",'Company 25'!$B:$E,4,0),"") -> 0 | T28: =IFERROR(VLOOKUP("M9_WILLINGNESS",'Company 25'!$B:$E,4,0),"") -> 0 | U28: =IFERROR(VLOOKUP("SV1_PRICING",'Company 25'!$B:$E,4,0),"") -> 0 | V28: =IFERROR(VLOOKUP("SV2_PROMOTIONS",'Company 25'!$B:$E,4,0),"") -> 0 | W28: =IFERROR(VLOOKUP("SV3_SUPPLYCHAIN",'Company 25'!$B:$E,4,0),"") -> 0 | X28: =IFERROR(VLOOKUP("SV4_CATEGORY",'Company 25'!$B:$E,4,0),"") -> 0 | Y28: =IFERROR(VLOOKUP("SV5_DEMAND",'Company 25'!$B:$E,4,0),"") -> 0 | Z28: =IFERROR(VLOOKUP("SV6_ACCOUNT",'Company 25'!$B:$E,4,0),"") -> 0 | AA28: =IFERROR(VLOOKUP("SV7_OPS",'Company 25'!$B:$E,4,0),"") -> 0 | AB28: =IFERROR(VLOOKUP("SC1_DATASENS",'Company 25'!$B:$E,4,0),"") -> 0 | AC28: =IFERROR(VLOOKUP("SC2_COMPLIANCE",'Company 25'!$B:$E,4,0),"") -> 0 | AD28: =IFERROR(VLOOKUP("SC3_TRUST",'Company 25'!$B:$E,4,0),"") -> 0 | AE28: =IFERROR(VLOOKUP("SC4_DATAPROC",'Company 25'!$B:$E,4,0),"") -> 0 | AF28: =IFERROR(VLOOKUP("SF1_REALTIME",'Company 25'!$B:$E,4,0),"") -> 0 | AG28: =IFERROR(VLOOKUP("SF2_ACCESS",'Company 25'!$B:$E,4,0),"") -> 0 | AH28: =IFERROR(VLOOKUP("SF3_UX",'Company 25'!$B:$E,4,0),"") -> 0 | AI28: =IFERROR(VLOOKUP("SF4_DECISION",'Company 25'!$B:$E,4,0),"") -> 0 | AJ28: =IFERROR(VLOOKUP("SF5_MASKING",'Company 25'!$B:$E,4,0),"") -> 0 | AK28: =IFERROR(VLOOKUP("SD1_TRENDS",'Company 25'!$B:$E,4,0),"") -> 0 | AL28: =IFERROR(VLOOKUP("SD2_MARKET",'Company 25'!$B:$E,4,0),"") -> 0 | AM28: =IFERROR(VLOOKUP("SD3_CATEGORY",'Company 25'!$B:$E,4,0),"") -> 0 | AN28: =IFERROR(VLOOKUP("SD4_SHIPMENT",'Company 25'!$B:$E,4,0),"") -> 0 | AO28: =IFERROR(VLOOKUP("SD5_LEAD",'Company 25'!$B:$E,4,0),"") -> 0 | AP28: =IFERROR(VLOOKUP("SD6_CONJOINT",'Company 25'!$B:$E,4,0),"") -> 0
B29: Company 26 | C29: =IFERROR(VLOOKUP("Interviewee Position",'Company 26'!$B:$C,2,0),"") -> 0 | D29: =IFERROR(VLOOKUP("Company Industry",'Company 26'!$B:$C,2,0),"") -> 0 | E29: =IFERROR(VLOOKUP("Company Sub-Industry",'Company 26'!$B:$C,2,0),"") -> 0 | F29: =IFERROR(VLOOKUP("Company Size (Turnover)",'Company 26'!$B:$C,2,0),"") -> 0 | G29: =IFERROR(VLOOKUP("Country",'Company 26'!$B:$C,2,0),"") -> 0 | H29: =IFERROR(VLOOKUP("B1_INTEREST",'Company 26'!$B:$E,4,0),"") -> 0 | I29: =IFERROR(VLOOKUP("B2_SHARING",'Company 26'!$B:$E,4,0),"") -> 0 | J29: =IFERROR(VLOOKUP("B3_MONETIZE",'Company 26'!$B:$E,4,0),"") -> 0 | K29: =IFERROR(VLOOKUP("B4_STRATEGIC",'Company 26'!$B:$E,4,0),"") -> 0 | L29: =IFERROR(VLOOKUP("M1_AUTOMATED",'Company 26'!$B:$E,4,0),"") -> 0 | M29: =IFERROR(VLOOKUP("M2_REALTIME",'Company 26'!$B:$E,4,0),"") -> 0 | N29: =IFERROR(VLOOKUP("M3_STRATEGIC",'Company 26'!$B:$E,4,0),"") -> 0 | O29: =IFERROR(VLOOKUP("M4_BREADTH",'Company 26'!$B:$E,4,0),"") -> 0 | P29: =IFERROR(VLOOKUP("M5_DATATYPES",'Company 26'!$B:$E,4,0),"") -> 0 | Q29: =IFERROR(VLOOKUP("M6_TRUST",'Company 26'!$B:$E,4,0),"") -> 0 | R29: =IFERROR(VLOOKUP("M7_BARRIERS",'Company 26'!$B:$E,4,0),"") -> 0 | S29: =IFERROR(VLOOKUP("M8_IMPACT",'Company 26'!$B:$E,4,0),"") -> 0 | T29: =IFERROR(VLOOKUP("M9_WILLINGNESS",'Company 26'!$B:$E,4,0),"") -> 0 | U29: =IFERROR(VLOOKUP("SV1_PRICING",'Company 26'!$B:$E,4,0),"") -> 0 | V29: =IFERROR(VLOOKUP("SV2_PROMOTIONS",'Company 26'!$B:$E,4,0),"") -> 0 | W29: =IFERROR(VLOOKUP("SV3_SUPPLYCHAIN",'Company 26'!$B:$E,4,0),"") -> 0 | X29: =IFERROR(VLOOKUP("SV4_CATEGORY",'Company 26'!$B:$E,4,0),"") -> 0 | Y29: =IFERROR(VLOOKUP("SV5_DEMAND",'Company 26'!$B:$E,4,0),"") -> 0 | Z29: =IFERROR(VLOOKUP("SV6_ACCOUNT",'Company 26'!$B:$E,4,0),"") -> 0 | AA29: =IFERROR(VLOOKUP("SV7_OPS",'Company 26'!$B:$E,4,0),"") -> 0 | AB29: =IFERROR(VLOOKUP("SC1_DATASENS",'Company 26'!$B:$E,4,0),"") -> 0 | AC29: =IFERROR(VLOOKUP("SC2_COMPLIANCE",'Company 26'!$B:$E,4,0),"") -> 0 | AD29: =IFERROR(VLOOKUP("SC3_TRUST",'Company 26'!$B:$E,4,0),"") -> 0 | AE29: =IFERROR(VLOOKUP("SC4_DATAPROC",'Company 26'!$B:$E,4,0),"") -> 0 | AF29: =IFERROR(VLOOKUP("SF1_REALTIME",'Company 26'!$B:$E,4,0),"") -> 0 | AG29: =IFERROR(VLOOKUP("SF2_ACCESS",'Company 26'!$B:$E,4,0),"") -> 0 | AH29: =IFERROR(VLOOKUP("SF3_UX",'Company 26'!$B:$E,4,0),"") -> 0 | AI29: =IFERROR(VLOOKUP("SF4_DECISION",'Company 26'!$B:$E,4,0),"") -> 0 | AJ29: =IFERROR(VLOOKUP("SF5_MASKING",'Company 26'!$B:$E,4,0),"") -> 0 | AK29: =IFERROR(VLOOKUP("SD1_TRENDS",'Company 26'!$B:$E,4,0),"") -> 0 | AL29: =IFERROR(VLOOKUP("SD2_MARKET",'Company 26'!$B:$E,4,0),"") -> 0 | AM29: =IFERROR(VLOOKUP("SD3_CATEGORY",'Company 26'!$B:$E,4,0),"") -> 0 | AN29: =IFERROR(VLOOKUP("SD4_SHIPMENT",'Company 26'!$B:$E,4,0),"") -> 0 | AO29: =IFERROR(VLOOKUP("SD5_LEAD",'Company 26'!$B:$E,4,0),"") -> 0 | AP29: =IFERROR(VLOOKUP("SD6_CONJOINT",'Company 26'!$B:$E,4,0),"") -> 0
B30: Company 27 | C30: =IFERROR(VLOOKUP("Interviewee Position",'Company 27'!$B:$C,2,0),"") -> 0 | D30: =IFERROR(VLOOKUP("Company Industry",'Company 27'!$B:$C,2,0),"") -> 0 | E30: =IFERROR(VLOOKUP("Company Sub-Industry",'Company 27'!$B:$C,2,0),"") -> 0 | F30: =IFERROR(VLOOKUP("Company Size (Turnover)",'Company 27'!$B:$C,2,0),"") -> 0 | G30: =IFERROR(VLOOKUP("Country",'Company 27'!$B:$C,2,0),"") -> 0 | H30: =IFERROR(VLOOKUP("B1_INTEREST",'Company 27'!$B:$E,4,0),"") -> 0 | I30: =IFERROR(VLOOKUP("B2_SHARING",'Company 27'!$B:$E,4,0),"") -> 0 | J30: =IFERROR(VLOOKUP("B3_MONETIZE",'Company 27'!$B:$E,4,0),"") -> 0 | K30: =IFERROR(VLOOKUP("B4_STRATEGIC",'Company 27'!$B:$E,4,0),"") -> 0 | L30: =IFERROR(VLOOKUP("M1_AUTOMATED",'Company 27'!$B:$E,4,0),"") -> 0 | M30: =IFERROR(VLOOKUP("M2_REALTIME",'Company 27'!$B:$E,4,0),"") -> 0 | N30: =IFERROR(VLOOKUP("M3_STRATEGIC",'Company 27'!$B:$E,4,0),"") -> 0 | O30: =IFERROR(VLOOKUP("M4_BREADTH",'Company 27'!$B:$E,4,0),"") -> 0 | P30: =IFERROR(VLOOKUP("M5_DATATYPES",'Company 27'!$B:$E,4,0),"") -> 0 | Q30: =IFERROR(VLOOKUP("M6_TRUST",'Company 27'!$B:$E,4,0),"") -> 0 | R30: =IFERROR(VLOOKUP("M7_BARRIERS",'Company 27'!$B:$E,4,0),"") -> 0 | S30: =IFERROR(VLOOKUP("M8_IMPACT",'Company 27'!$B:$E,4,0),"") -> 0 | T30: =IFERROR(VLOOKUP("M9_WILLINGNESS",'Company 27'!$B:$E,4,0),"") -> 0 | U30: =IFERROR(VLOOKUP("SV1_PRICING",'Company 27'!$B:$E,4,0),"") -> 0 | V30: =IFERROR(VLOOKUP("SV2_PROMOTIONS",'Company 27'!$B:$E,4,0),"") -> 0 | W30: =IFERROR(VLOOKUP("SV3_SUPPLYCHAIN",'Company 27'!$B:$E,4,0),"") -> 0 | X30: =IFERROR(VLOOKUP("SV4_CATEGORY",'Company 27'!$B:$E,4,0),"") -> 0 | Y30: =IFERROR(VLOOKUP("SV5_DEMAND",'Company 27'!$B:$E,4,0),"") -> 0 | Z30: =IFERROR(VLOOKUP("SV6_ACCOUNT",'Company 27'!$B:$E,4,0),"") -> 0 | AA30: =IFERROR(VLOOKUP("SV7_OPS",'Company 27'!$B:$E,4,0),"") -> 0 | AB30: =IFERROR(VLOOKUP("SC1_DATASENS",'Company 27'!$B:$E,4,0),"") -> 0 | AC30: =IFERROR(VLOOKUP("SC2_COMPLIANCE",'Company 27'!$B:$E,4,0),"") -> 0 | AD30: =IFERROR(VLOOKUP("SC3_TRUST",'Company 27'!$B:$E,4,0),"") -> 0 | AE30: =IFERROR(VLOOKUP("SC4_DATAPROC",'Company 27'!$B:$E,4,0),"") -> 0 | AF30: =IFERROR(VLOOKUP("SF1_REALTIME",'Company 27'!$B:$E,4,0),"") -> 0 | AG30: =IFERROR(VLOOKUP("SF2_ACCESS",'Company 27'!$B:$E,4,0),"") -> 0 | AH30: =IFERROR(VLOOKUP("SF3_UX",'Company 27'!$B:$E,4,0),"") -> 0 | AI30: =IFERROR(VLOOKUP("SF4_DECISION",'Company 27'!$B:$E,4,0),"") -> 0 | AJ30: =IFERROR(VLOOKUP("SF5_MASKING",'Company 27'!$B:$E,4,0),"") -> 0 | AK30: =IFERROR(VLOOKUP("SD1_TRENDS",'Company 27'!$B:$E,4,0),"") -> 0 | AL30: =IFERROR(VLOOKUP("SD2_MARKET",'Company 27'!$B:$E,4,0),"") -> 0 | AM30: =IFERROR(VLOOKUP("SD3_CATEGORY",'Company 27'!$B:$E,4,0),"") -> 0 | AN30: =IFERROR(VLOOKUP("SD4_SHIPMENT",'Company 27'!$B:$E,4,0),"") -> 0 | AO30: =IFERROR(VLOOKUP("SD5_LEAD",'Company 27'!$B:$E,4,0),"") -> 0 | AP30: =IFERROR(VLOOKUP("SD6_CONJOINT",'Company 27'!$B:$E,4,0),"") -> 0
B31: Company 28 | C31: =IFERROR(VLOOKUP("Interviewee Position",'Company 28'!$B:$C,2,0),"") -> 0 | D31: =IFERROR(VLOOKUP("Company Industry",'Company 28'!$B:$C,2,0),"") -> 0 | E31: =IFERROR(VLOOKUP("Company Sub-Industry",'Company 28'!$B:$C,2,0),"") -> 0 | F31: =IFERROR(VLOOKUP("Company Size (Turnover)",'Company 28'!$B:$C,2,0),"") -> 0 | G31: =IFERROR(VLOOKUP("Country",'Company 28'!$B:$C,2,0),"") -> 0 | H31: =IFERROR(VLOOKUP("B1_INTEREST",'Company 28'!$B:$E,4,0),"") -> 0 | I31: =IFERROR(VLOOKUP("B2_SHARING",'Company 28'!$B:$E,4,0),"") -> 0 | J31: =IFERROR(VLOOKUP("B3_MONETIZE",'Company 28'!$B:$E,4,0),"") -> 0 | K31: =IFERROR(VLOOKUP("B4_STRATEGIC",'Company 28'!$B:$E,4,0),"") -> 0 | L31: =IFERROR(VLOOKUP("M1_AUTOMATED",'Company 28'!$B:$E,4,0),"") -> 0 | M31: =IFERROR(VLOOKUP("M2_REALTIME",'Company 28'!$B:$E,4,0),"") -> 0 | N31: =IFERROR(VLOOKUP("M3_STRATEGIC",'Company 28'!$B:$E,4,0),"") -> 0 | O31: =IFERROR(VLOOKUP("M4_BREADTH",'Company 28'!$B:$E,4,0),"") -> 0 | P31: =IFERROR(VLOOKUP("M5_DATATYPES",'Company 28'!$B:$E,4,0),"") -> 0 | Q31: =IFERROR(VLOOKUP("M6_TRUST",'Company 28'!$B:$E,4,0),"") -> 0 | R31: =IFERROR(VLOOKUP("M7_BARRIERS",'Company 28'!$B:$E,4,0),"") -> 0 | S31: =IFERROR(VLOOKUP("M8_IMPACT",'Company 28'!$B:$E,4,0),"") -> 0 | T31: =IFERROR(VLOOKUP("M9_WILLINGNESS",'Company 28'!$B:$E,4,0),"") -> 0 | U31: =IFERROR(VLOOKUP("SV1_PRICING",'Company 28'!$B:$E,4,0),"") -> 0 | V31: =IFERROR(VLOOKUP("SV2_PROMOTIONS",'Company 28'!$B:$E,4,0),"") -> 0 | W31: =IFERROR(VLOOKUP("SV3_SUPPLYCHAIN",'Company 28'!$B:$E,4,0),"") -> 0 | X31: =IFERROR(VLOOKUP("SV4_CATEGORY",'Company 28'!$B:$E,4,0),"") -> 0 | Y31: =IFERROR(VLOOKUP("SV5_DEMAND",'Company 28'!$B:$E,4,0),"") -> 0 | Z31: =IFERROR(VLOOKUP("SV6_ACCOUNT",'Company 28'!$B:$E,4,0),"") -> 0 | AA31: =IFERROR(VLOOKUP("SV7_OPS",'Company 28'!$B:$E,4,0),"") -> 0 | AB31: =IFERROR(VLOOKUP("SC1_DATASENS",'Company 28'!$B:$E,4,0),"") -> 0 | AC31: =IFERROR(VLOOKUP("SC2_COMPLIANCE",'Company 28'!$B:$E,4,0),"") -> 0 | AD31: =IFERROR(VLOOKUP("SC3_TRUST",'Company 28'!$B:$E,4,0),"") -> 0 | AE31: =IFERROR(VLOOKUP("SC4_DATAPROC",'Company 28'!$B:$E,4,0),"") -> 0 | AF31: =IFERROR(VLOOKUP("SF1_REALTIME",'Company 28'!$B:$E,4,0),"") -> 0 | AG31: =IFERROR(VLOOKUP("SF2_ACCESS",'Company 28'!$B:$E,4,0),"") -> 0 | AH31: =IFERROR(VLOOKUP("SF3_UX",'Company 28'!$B:$E,4,0),"") -> 0 | AI31: =IFERROR(VLOOKUP("SF4_DECISION",'Company 28'!$B:$E,4,0),"") -> 0 | AJ31: =IFERROR(VLOOKUP("SF5_MASKING",'Company 28'!$B:$E,4,0),"") -> 0 | AK31: =IFERROR(VLOOKUP("SD1_TRENDS",'Company 28'!$B:$E,4,0),"") -> 0 | AL31: =IFERROR(VLOOKUP("SD2_MARKET",'Company 28'!$B:$E,4,0),"") -> 0 | AM31: =IFERROR(VLOOKUP("SD3_CATEGORY",'Company 28'!$B:$E,4,0),"") -> 0 | AN31: =IFERROR(VLOOKUP("SD4_SHIPMENT",'Company 28'!$B:$E,4,0),"") -> 0 | AO31: =IFERROR(VLOOKUP("SD5_LEAD",'Company 28'!$B:$E,4,0),"") -> 0 | AP31: =IFERROR(VLOOKUP("SD6_CONJOINT",'Company 28'!$B:$E,4,0),"") -> 0
B32: Company 29 | C32: =IFERROR(VLOOKUP("Interviewee Position",'Company 29'!$B:$C,2,0),"") -> 0 | D32: =IFERROR(VLOOKUP("Company Industry",'Company 29'!$B:$C,2,0),"") -> 0 | E32: =IFERROR(VLOOKUP("Company Sub-Industry",'Company 29'!$B:$C,2,0),"") -> 0 | F32: =IFERROR(VLOOKUP("Company Size (Turnover)",'Company 29'!$B:$C,2,0),"") -> 0 | G32: =IFERROR(VLOOKUP("Country",'Company 29'!$B:$C,2,0),"") -> 0 | H32: =IFERROR(VLOOKUP("B1_INTEREST",'Company 29'!$B:$E,4,0),"") -> 0 | I32: =IFERROR(VLOOKUP("B2_SHARING",'Company 29'!$B:$E,4,0),"") -> 0 | J32: =IFERROR(VLOOKUP("B3_MONETIZE",'Company 29'!$B:$E,4,0),"") -> 0 | K32: =IFERROR(VLOOKUP("B4_STRATEGIC",'Company 29'!$B:$E,4,0),"") -> 0 | L32: =IFERROR(VLOOKUP("M1_AUTOMATED",'Company 29'!$B:$E,4,0),"") -> 0 | M32: =IFERROR(VLOOKUP("M2_REALTIME",'Company 29'!$B:$E,4,0),"") -> 0 | N32: =IFERROR(VLOOKUP("M3_STRATEGIC",'Company 29'!$B:$E,4,0),"") -> 0 | O32: =IFERROR(VLOOKUP("M4_BREADTH",'Company 29'!$B:$E,4,0),"") -> 0 | P32: =IFERROR(VLOOKUP("M5_DATATYPES",'Company 29'!$B:$E,4,0),"") -> 0 | Q32: =IFERROR(VLOOKUP("M6_TRUST",'Company 29'!$B:$E,4,0),"") -> 0 | R32: =IFERROR(VLOOKUP("M7_BARRIERS",'Company 29'!$B:$E,4,0),"") -> 0 | S32: =IFERROR(VLOOKUP("M8_IMPACT",'Company 29'!$B:$E,4,0),"") -> 0 | T32: =IFERROR(VLOOKUP("M9_WILLINGNESS",'Company 29'!$B:$E,4,0),"") -> 0 | U32: =IFERROR(VLOOKUP("SV1_PRICING",'Company 29'!$B:$E,4,0),"") -> 0 | V32: =IFERROR(VLOOKUP("SV2_PROMOTIONS",'Company 29'!$B:$E,4,0),"") -> 0 | W32: =IFERROR(VLOOKUP("SV3_SUPPLYCHAIN",'Company 29'!$B:$E,4,0),"") -> 0 | X32: =IFERROR(VLOOKUP("SV4_CATEGORY",'Company 29'!$B:$E,4,0),"") -> 0 | Y32: =IFERROR(VLOOKUP("SV5_DEMAND",'Company 29'!$B:$E,4,0),"") -> 0 | Z32: =IFERROR(VLOOKUP("SV6_ACCOUNT",'Company 29'!$B:$E,4,0),"") -> 0 | AA32: =IFERROR(VLOOKUP("SV7_OPS",'Company 29'!$B:$E,4,0),"") -> 0 | AB32: =IFERROR(VLOOKUP("SC1_DATASENS",'Company 29'!$B:$E,4,0),"") -> 0 | AC32: =IFERROR(VLOOKUP("SC2_COMPLIANCE",'Company 29'!$B:$E,4,0),"") -> 0 | AD32: =IFERROR(VLOOKUP("SC3_TRUST",'Company 29'!$B:$E,4,0),"") -> 0 | AE32: =IFERROR(VLOOKUP("SC4_DATAPROC",'Company 29'!$B:$E,4,0),"") -> 0 | AF32: =IFERROR(VLOOKUP("SF1_REALTIME",'Company 29'!$B:$E,4,0),"") -> 0 | AG32: =IFERROR(VLOOKUP("SF2_ACCESS",'Company 29'!$B:$E,4,0),"") -> 0 | AH32: =IFERROR(VLOOKUP("SF3_UX",'Company 29'!$B:$E,4,0),"") -> 0 | AI32: =IFERROR(VLOOKUP("SF4_DECISION",'Company 29'!$B:$E,4,0),"") -> 0 | AJ32: =IFERROR(VLOOKUP("SF5_MASKING",'Company 29'!$B:$E,4,0),"") -> 0 | AK32: =IFERROR(VLOOKUP("SD1_TRENDS",'Company 29'!$B:$E,4,0),"") -> 0 | AL32: =IFERROR(VLOOKUP("SD2_MARKET",'Company 29'!$B:$E,4,0),"") -> 0 | AM32: =IFERROR(VLOOKUP("SD3_CATEGORY",'Company 29'!$B:$E,4,0),"") -> 0 | AN32: =IFERROR(VLOOKUP("SD4_SHIPMENT",'Company 29'!$B:$E,4,0),"") -> 0 | AO32: =IFERROR(VLOOKUP("SD5_LEAD",'Company 29'!$B:$E,4,0),"") -> 0 | AP32: =IFERROR(VLOOKUP("SD6_CONJOINT",'Company 29'!$B:$E,4,0),"") -> 0
B33: Company 30 | C33: =IFERROR(VLOOKUP("Interviewee Position",'Company 30'!$B:$C,2,0),"") -> 0 | D33: =IFERROR(VLOOKUP("Company Industry",'Company 30'!$B:$C,2,0),"") -> 0 | E33: =IFERROR(VLOOKUP("Company Sub-Industry",'Company 30'!$B:$C,2,0),"") -> 0 | F33: =IFERROR(VLOOKUP("Company Size (Turnover)",'Company 30'!$B:$C,2,0),"") -> 0 | G33: =IFERROR(VLOOKUP("Country",'Company 30'!$B:$C,2,0),"") -> 0 | H33: =IFERROR(VLOOKUP("B1_INTEREST",'Company 30'!$B:$E,4,0),"") -> 0 | I33: =IFERROR(VLOOKUP("B2_SHARING",'Company 30'!$B:$E,4,0),"") -> 0 | J33: =IFERROR(VLOOKUP("B3_MONETIZE",'Company 30'!$B:$E,4,0),"") -> 0 | K33: =IFERROR(VLOOKUP("B4_STRATEGIC",'Company 30'!$B:$E,4,0),"") -> 0 | L33: =IFERROR(VLOOKUP("M1_AUTOMATED",'Company 30'!$B:$E,4,0),"") -> 0 | M33: =IFERROR(VLOOKUP("M2_REALTIME",'Company 30'!$B:$E,4,0),"") -> 0 | N33: =IFERROR(VLOOKUP("M3_STRATEGIC",'Company 30'!$B:$E,4,0),"") -> 0 | O33: =IFERROR(VLOOKUP("M4_BREADTH",'Company 30'!$B:$E,4,0),"") -> 0 | P33: =IFERROR(VLOOKUP("M5_DATATYPES",'Company 30'!$B:$E,4,0),"") -> 0 | Q33: =IFERROR(VLOOKUP("M6_TRUST",'Company 30'!$B:$E,4,0),"") -> 0 | R33: =IFERROR(VLOOKUP("M7_BARRIERS",'Company 30'!$B:$E,4,0),"") -> 0 | S33: =IFERROR(VLOOKUP("M8_IMPACT",'Company 30'!$B:$E,4,0),"") -> 0 | T33: =IFERROR(VLOOKUP("M9_WILLINGNESS",'Company 30'!$B:$E,4,0),"") -> 0 | U33: =IFERROR(VLOOKUP("SV1_PRICING",'Company 30'!$B:$E,4,0),"") -> 0 | V33: =IFERROR(VLOOKUP("SV2_PROMOTIONS",'Company 30'!$B:$E,4,0),"") -> 0 | W33: =IFERROR(VLOOKUP("SV3_SUPPLYCHAIN",'Company 30'!$B:$E,4,0),"") -> 0 | X33: =IFERROR(VLOOKUP("SV4_CATEGORY",'Company 30'!$B:$E,4,0),"") -> 0 | Y33: =IFERROR(VLOOKUP("SV5_DEMAND",'Company 30'!$B:$E,4,0),"") -> 0 | Z33: =IFERROR(VLOOKUP("SV6_ACCOUNT",'Company 30'!$B:$E,4,0),"") -> 0 | AA33: =IFERROR(VLOOKUP("SV7_OPS",'Company 30'!$B:$E,4,0),"") -> 0 | AB33: =IFERROR(VLOOKUP("SC1_DATASENS",'Company 30'!$B:$E,4,0),"") -> 0 | AC33: =IFERROR(VLOOKUP("SC2_COMPLIANCE",'Company 30'!$B:$E,4,0),"") -> 0 | AD33: =IFERROR(VLOOKUP("SC3_TRUST",'Company 30'!$B:$E,4,0),"") -> 0 | AE33: =IFERROR(VLOOKUP("SC4_DATAPROC",'Company 30'!$B:$E,4,0),"") -> 0 | AF33: =IFERROR(VLOOKUP("SF1_REALTIME",'Company 30'!$B:$E,4,0),"") -> 0 | AG33: =IFERROR(VLOOKUP("SF2_ACCESS",'Company 30'!$B:$E,4,0),"") -> 0 | AH33: =IFERROR(VLOOKUP("SF3_UX",'Company 30'!$B:$E,4,0),"") -> 0 | AI33: =IFERROR(VLOOKUP("SF4_DECISION",'Company 30'!$B:$E,4,0),"") -> 0 | AJ33: =IFERROR(VLOOKUP("SF5_MASKING",'Company 30'!$B:$E,4,0),"") -> 0 | AK33: =IFERROR(VLOOKUP("SD1_TRENDS",'Company 30'!$B:$E,4,0),"") -> 0 | AL33: =IFERROR(VLOOKUP("SD2_MARKET",'Company 30'!$B:$E,4,0),"") -> 0 | AM33: =IFERROR(VLOOKUP("SD3_CATEGORY",'Company 30'!$B:$E,4,0),"") -> 0 | AN33: =IFERROR(VLOOKUP("SD4_SHIPMENT",'Company 30'!$B:$E,4,0),"") -> 0 | AO33: =IFERROR(VLOOKUP("SD5_LEAD",'Company 30'!$B:$E,4,0),"") -> 0 | AP33: =IFERROR(VLOOKUP("SD6_CONJOINT",'Company 30'!$B:$E,4,0),"") -> 0
B35: HOW TO FILTER | C35: Click ▼ on any column header to filter by Role, Industry, Size, Country. Each row = one interview. Stack filters freely.
B37: Totals | E37: =30-COUNT(E4:E33) -> 17 | H37: =SUMIF(H4:H33,">0")/COUNTIF(H4:H33,">0") -> 7.1923077 | I37: =COUNTIF(I4:I33,">0") -> 13 | J37: =COUNTIF(J4:J33,">0") -> 4 | K37: =COUNTIF(K4:K33,">0") -> 7 | L37: =SUMIF(L4:L33,">0")/COUNTIF(L4:L33,">0") -> 2.7272727 | M37: =SUMIF(M4:M33,">0")/COUNTIF(M4:M33,">0") -> 2.3636364 | N37: =SUMIF(N4:N33,">0")/COUNTIF(N4:N33,">0") -> 3.2307692 | O37: =SUMIF(O4:O33,">0")/COUNTIF(O4:O33,">0") -> 2.6153846 | P37: =SUMIF(P4:P33,">0")/COUNTIF(P4:P33,">0") -> 3.2307692 | Q37: =SUMIF(Q4:Q33,">0")/COUNTIF(Q4:Q33,">0") -> 2.6666667 | R37: =SUMIF(R4:R33,">0")/COUNTIF(R4:R33,">0") -> 3.6153846 | S37: =SUMIF(S4:S33,">0")/COUNTIF(S4:S33,">0") -> 3.3333333 | T37: =SUMIF(T4:T33,">0")/COUNTIF(T4:T33,">0") -> 6.9230769 | U37: =COUNTIF(U4:U33,">0") -> 7 | V37: =COUNTIF(V4:V33,">0") -> 8 | W37: =COUNTIF(W4:W33,">0") -> 8 | X37: =COUNTIF(X4:X33,">0") -> 10 | Y37: =COUNTIF(Y4:Y33,">0") -> 4 | Z37: =COUNTIF(Z4:Z33,">0") -> 3 | AA37: =COUNTIF(AA4:AA33,">0") -> 5 | AB37: =COUNTIF(AB4:AB33,">0") -> 12 | ... AP37: =COUNTIF(AP4:AP33,">0") -> 0
B38: Manufacturer | E38: =COUNTIF($E$4:$E$33,B38) -> 5 | H38: =SUMIFS(H$4:H$33,H$4:H$33,">0",$E$4:$E$33,$B38)/$E38 -> 8.4 | I38: =SUMIFS(I$4:I$33,$E$4:$E$33,$B38) -> 5 | J38: =SUMIFS(J$4:J$33,$E$4:$E$33,$B38) -> 0 | K38: =SUMIFS(K$4:K$33,$E$4:$E$33,$B38) -> 3 | L38: =SUMIFS(L$4:L$33,L$4:L$33,">0",$E$4:$E$33,$B38)/$E38 -> 3 | M38: =SUMIFS(M$4:M$33,M$4:M$33,">0",$E$4:$E$33,$B38)/$E38 -> 2.6 | N38: =SUMIFS(N$4:N$33,N$4:N$33,">0",$E$4:$E$33,$B38)/$E38 -> 3.8 | O38: =SUMIFS(O$4:O$33,O$4:O$33,">0",$E$4:$E$33,$B38)/$E38 -> 3.2 | P38: =SUMIFS(P$4:P$33,P$4:P$33,">0",$E$4:$E$33,$B38)/$E38 -> 4 | Q38: =SUMIFS(Q$4:Q$33,Q$4:Q$33,">0",$E$4:$E$33,$B38)/$E38 -> 2.6 | R38: =SUMIFS(R$4:R$33,R$4:R$33,">0",$E$4:$E$33,$B38)/$E38 -> 4 | S38: =SUMIFS(S$4:S$33,S$4:S$33,">0",$E$4:$E$33,$B38)/$E38 -> 3.2 | T38: =SUMIFS(T$4:T$33,T$4:T$33,">0",$E$4:$E$33,$B38)/$E38 -> 8 | U38: =SUMIFS(U$4:U$33,$E$4:$E$33,$B38) -> 4 | V38: =SUMIFS(V$4:V$33,$E$4:$E$33,$B38) -> 4 | W38: =SUMIFS(W$4:W$33,$E$4:$E$33,$B38) -> 4 | X38: =SUMIFS(X$4:X$33,$E$4:$E$33,$B38) -> 4 | Y38: =SUMIFS(Y$4:Y$33,$E$4:$E$33,$B38) -> 2 | Z38: =SUMIFS(Z$4:Z$33,$E$4:$E$33,$B38) -> 2 | AA38: =SUMIFS(AA$4:AA$33,$E$4:$E$33,$B38) -> 3 | AB38: =SUMIFS(AB$4:AB$33,$E$4:$E$33,$B38) -> 5 | ... AP38: =SUMIFS(AP$4:AP$33,$E$4:$E$33,$B38) -> 0
B39: Specialty Retail | E39: =COUNTIF($E$4:$E$33,B39) -> 3 | H39: =SUMIFS(H$4:H$33,H$4:H$33,">0",$E$4:$E$33,$B39)/$E39 -> 6 | I39: =SUMIFS(I$4:I$33,$E$4:$E$33,$B39) -> 3 | J39: =SUMIFS(J$4:J$33,$E$4:$E$33,$B39) -> 1 | K39: =SUMIFS(K$4:K$33,$E$4:$E$33,$B39) -> 1 | L39: =SUMIFS(L$4:L$33,L$4:L$33,">0",$E$4:$E$33,$B39)/$E39 -> 1.3333333 | M39: =SUMIFS(M$4:M$33,M$4:M$33,">0",$E$4:$E$33,$B39)/$E39 -> 1 | N39: =SUMIFS(N$4:N$33,N$4:N$33,">0",$E$4:$E$33,$B39)/$E39 -> 1.6666667 | O39: =SUMIFS(O$4:O$33,O$4:O$33,">0",$E$4:$E$33,$B39)/$E39 -> 1.6666667 | P39: =SUMIFS(P$4:P$33,P$4:P$33,">0",$E$4:$E$33,$B39)/$E39 -> 1.6666667 | Q39: =SUMIFS(Q$4:Q$33,Q$4:Q$33,">0",$E$4:$E$33,$B39)/$E39 -> 1.3333333 | R39: =SUMIFS(R$4:R$33,R$4:R$33,">0",$E$4:$E$33,$B39)/$E39 -> 3.3333333 | S39: =SUMIFS(S$4:S$33,S$4:S$33,">0",$E$4:$E$33,$B39)/$E39 -> 0 | T39: =SUMIFS(T$4:T$33,T$4:T$33,">0",$E$4:$E$33,$B39)/$E39 -> 5.6666667 | U39: =SUMIFS(U$4:U$33,$E$4:$E$33,$B39) -> 1 | V39: =SUMIFS(V$4:V$33,$E$4:$E$33,$B39) -> 1 | W39: =SUMIFS(W$4:W$33,$E$4:$E$33,$B39) -> 2 | X39: =SUMIFS(X$4:X$33,$E$4:$E$33,$B39) -> 2 | Y39: =SUMIFS(Y$4:Y$33,$E$4:$E$33,$B39) -> 0 | Z39: =SUMIFS(Z$4:Z$33,$E$4:$E$33,$B39) -> 0 | AA39: =SUMIFS(AA$4:AA$33,$E$4:$E$33,$B39) -> 0 | AB39: =SUMIFS(AB$4:AB$33,$E$4:$E$33,$B39) -> 3 | ... AP39: =SUMIFS(AP$4:AP$33,$E$4:$E$33,$B39) -> 0
B40: Wholesaler | E40: =COUNTIF($E$4:$E$33,B40) -> 4 | H40: =SUMIFS(H$4:H$33,H$4:H$33,">0",$E$4:$E$33,$B40)/$E40 -> 7.625 | I40: =SUMIFS(I$4:I$33,$E$4:$E$33,$B40) -> 4 | J40: =SUMIFS(J$4:J$33,$E$4:$E$33,$B40) -> 3 | K40: =SUMIFS(K$4:K$33,$E$4:$E$33,$B40) -> 2 | L40: =SUMIFS(L$4:L$33,L$4:L$33,">0",$E$4:$E$33,$B40)/$E40 -> 2.75 | M40: =SUMIFS(M$4:M$33,M$4:M$33,">0",$E$4:$E$33,$B40)/$E40 -> 2.5 | N40: =SUMIFS(N$4:N$33,N$4:N$33,">0",$E$4:$E$33,$B40)/$E40 -> 4 | O40: =SUMIFS(O$4:O$33,O$4:O$33,">0",$E$4:$E$33,$B40)/$E40 -> 3 | P40: =SUMIFS(P$4:P$33,P$4:P$33,">0",$E$4:$E$33,$B40)/$E40 -> 3.75 | Q40: =SUMIFS(Q$4:Q$33,Q$4:Q$33,">0",$E$4:$E$33,$B40)/$E40 -> 1.75 | R40: =SUMIFS(R$4:R$33,R$4:R$33,">0",$E$4:$E$33,$B40)/$E40 -> 3.25 | S40: =SUMIFS(S$4:S$33,S$4:S$33,">0",$E$4:$E$33,$B40)/$E40 -> 2.5 | T40: =SUMIFS(T$4:T$33,T$4:T$33,">0",$E$4:$E$33,$B40)/$E40 -> 7.5 | U40: =SUMIFS(U$4:U$33,$E$4:$E$33,$B40) -> 2 | V40: =SUMIFS(V$4:V$33,$E$4:$E$33,$B40) -> 2 | W40: =SUMIFS(W$4:W$33,$E$4:$E$33,$B40) -> 1 | X40: =SUMIFS(X$4:X$33,$E$4:$E$33,$B40) -> 4 | Y40: =SUMIFS(Y$4:Y$33,$E$4:$E$33,$B40) -> 1 | Z40: =SUMIFS(Z$4:Z$33,$E$4:$E$33,$B40) -> 1 | AA40: =SUMIFS(AA$4:AA$33,$E$4:$E$33,$B40) -> 2 | AB40: =SUMIFS(AB$4:AB$33,$E$4:$E$33,$B40) -> 3 | ... AP40: =SUMIFS(AP$4:AP$33,$E$4:$E$33,$B40) -> 0
B41: Retailer | E41: =COUNTIF($E$4:$E$33,B41) -> 1 | H41: =SUMIFS(H$4:H$33,H$4:H$33,">0",$E$4:$E$33,$B41)/$E41 -> 3 | I41: =SUMIFS(I$4:I$33,$E$4:$E$33,$B41) -> 1 | J41: =SUMIFS(J$4:J$33,$E$4:$E$33,$B41) -> 0 | K41: =SUMIFS(K$4:K$33,$E$4:$E$33,$B41) -> 1 | L41: =SUMIFS(L$4:L$33,L$4:L$33,">0",$E$4:$E$33,$B41)/$E41 -> 0 | M41: =SUMIFS(M$4:M$33,M$4:M$33,">0",$E$4:$E$33,$B41)/$E41 -> 0 | N41: =SUMIFS(N$4:N$33,N$4:N$33,">0",$E$4:$E$33,$B41)/$E41 -> 2 | O41: =SUMIFS(O$4:O$33,O$4:O$33,">0",$E$4:$E$33,$B41)/$E41 -> 1 | P41: =SUMIFS(P$4:P$33,P$4:P$33,">0",$E$4:$E$33,$B41)/$E41 -> 2 | Q41: =SUMIFS(Q$4:Q$33,Q$4:Q$33,">0",$E$4:$E$33,$B41)/$E41 -> 0 | R41: =SUMIFS(R$4:R$33,R$4:R$33,">0",$E$4:$E$33,$B41)/$E41 -> 4 | S41: =SUMIFS(S$4:S$33,S$4:S$33,">0",$E$4:$E$33,$B41)/$E41 -> 4 | T41: =SUMIFS(T$4:T$33,T$4:T$33,">0",$E$4:$E$33,$B41)/$E41 -> 3 | U41: =SUMIFS(U$4:U$33,$E$4:$E$33,$B41) -> 0 | V41: =SUMIFS(V$4:V$33,$E$4:$E$33,$B41) -> 1 | W41: =SUMIFS(W$4:W$33,$E$4:$E$33,$B41) -> 1 | X41: =SUMIFS(X$4:X$33,$E$4:$E$33,$B41) -> 0 | Y41: =SUMIFS(Y$4:Y$33,$E$4:$E$33,$B41) -> 1 | Z41: =SUMIFS(Z$4:Z$33,$E$4:$E$33,$B41) -> 0 | AA41: =SUMIFS(AA$4:AA$33,$E$4:$E$33,$B41) -> 0 | AB41: =SUMIFS(AB$4:AB$33,$E$4:$E$33,$B41) -> 1 | ... AP41: =SUMIFS(AP$4:AP$33,$E$4:$E$33,$B41) -> 0

Sheet Analysis — Individual
B1: Analysis — Individual Interviews
B2: FILTER DIMENSIONS
B3: Filter | C3: ROLE | D3: Interviewee Position | E3: =IFERROR(VLOOKUP("Interviewee Position",'Company 1'!$B:$C,2,0),"") -> Chief of Staff | F3: =IFERROR(VLOOKUP("Interviewee Position",'Company 2'!$B:$C,2,0),"") -> President and Managing Director Belgian Shell | G3: =IFERROR(VLOOKUP("Interviewee Position",'Company 3'!$B:$C,2,0),"") -> Business Development / Media Services Manager | H3: =IFERROR(VLOOKUP("Interviewee Position",'Company 4'!$B:$C,2,0),"") -> Data/Analytics role (formerly Department Head of Logistics) | I3: =IFERROR(VLOOKUP("Interviewee Position",'Company 5'!$B:$C,2,0),"") -> Supply Chain Director | J3: =IFERROR(VLOOKUP("Interviewee Position",'Company 6'!$B:$C,2,0),"") -> Sales Director | K3: =IFERROR(VLOOKUP("Interviewee Position",'Company 7'!$B:$C,2,0),"") -> CEO | L3: =IFERROR(VLOOKUP("Interviewee Position",'Company 8'!$B:$C,2,0),"") -> CFO / Finance Lead EMEA & LATAM | M3: =IFERROR(VLOOKUP("Interviewee Position",'Company 9'!$B:$C,2,0),"") -> Commercial Director | N3: =IFERROR(VLOOKUP("Interviewee Position",'Company 10'!$B:$C,2,0),"") -> Data Insights Team | O3: =IFERROR(VLOOKUP("Interviewee Position",'Company 11'!$B:$C,2,0),"") -> Marketing Strategic Role | P3: =IFERROR(VLOOKUP("Interviewee Position",'Company 12'!$B:$C,2,0),"") -> Marketing / Commercial Director | Q3: =IFERROR(VLOOKUP("Interviewee Position",'Company 13'!$B:$C,2,0),"") -> Data Lead / Head of IT & ERP | R3: =IFERROR(VLOOKUP("Interviewee Position",#REF!,2,0),"") | S3: =IFERROR(VLOOKUP("Interviewee Position",#REF!,2,0),"") | T3: =IFERROR(VLOOKUP("Interviewee Position",#REF!,2,0),"") | U3: =IFERROR(VLOOKUP("Interviewee Position",#REF!,2,0),"") | V3: =IFERROR(VLOOKUP("Interviewee Position",'Company 18'!$B:$C,2,0),"") -> 0 | W3: =IFERROR(VLOOKUP("Interviewee Position",'Company 19'!$B:$C,2,0),"") -> 0 | X3: =IFERROR(VLOOKUP("Interviewee Position",'Company 20'!$B:$C,2,0),"") -> 0 | Y3: =IFERROR(VLOOKUP("Interviewee Position",'Company 21'!$B:$C,2,0),"") -> 0 | Z3: =IFERROR(VLOOKUP("Interviewee Position",'Company 22'!$B:$C,2,0),"") -> 0 | AA3: =IFERROR(VLOOKUP("Interviewee Position",'Company 23'!$B:$C,2,0),"") -> 0 | AB3: =IFERROR(VLOOKUP("Interviewee Position",'Company 24'!$B:$C,2,0),"") -> 0 | AC3: =IFERROR(VLOOKUP("Interviewee Position",'Company 25'!$B:$C,2,0),"") -> 0 | AD3: =IFERROR(VLOOKUP("Interviewee Position",'Company 26'!$B:$C,2,0),"") -> 0 | AE3: =IFERROR(VLOOKUP("Interviewee Position",'Company 27'!$B:$C,2,0),"") -> 0 | AF3: =IFERROR(VLOOKUP("Interviewee Position",'Company 28'!$B:$C,2,0),"") -> 0 | AG3: =IFERROR(VLOOKUP("Interviewee Position",'Company 29'!$B:$C,2,0),"") -> 0 | AH3: =IFERROR(VLOOKUP("Interviewee Position",'Company 30'!$B:$C,2,0),"") -> 0
B4: Filter | C4: INDUSTRY | D4: Company Industry | E4: =IFERROR(VLOOKUP("Company Industry",'Company 1'!$B:$C,2,0),"") -> Specialty Retail | F4: =IFERROR(VLOOKUP("Company Industry",'Company 2'!$B:$C,2,0),"") -> Oil & Gas | G4: =IFERROR(VLOOKUP("Company Industry",'Company 3'!$B:$C,2,0),"") -> B2B Food Service Distribution | H4: =IFERROR(VLOOKUP("Company Industry",'Company 4'!$B:$C,2,0),"") -> Food Service | I4: =IFERROR(VLOOKUP("Company Industry",'Company 5'!$B:$C,2,0),"") -> Food Manufacturing | J4: =IFERROR(VLOOKUP("Company Industry",'Company 6'!$B:$C,2,0),"") -> FMCG | K4: =IFERROR(VLOOKUP("Company Industry",'Company 7'!$B:$C,2,0),"") -> Food Service / Wholesale Distribution | L4: =IFERROR(VLOOKUP("Company Industry",'Company 8'!$B:$C,2,0),"") -> Pet Food & Products | M4: =IFERROR(VLOOKUP("Company Industry",'Company 9'!$B:$C,2,0),"") -> Wholesale | N4: =IFERROR(VLOOKUP("Company Industry",'Company 10'!$B:$C,2,0),"") -> FMCG | O4: =IFERROR(VLOOKUP("Company Industry",'Company 11'!$B:$C,2,0),"") -> Pharmacy/Healthcare Retail | P4: =IFERROR(VLOOKUP("Company Industry",'Company 12'!$B:$C,2,0),"") -> Grocery Retail | Q4: =IFERROR(VLOOKUP("Company Industry",'Company 13'!$B:$C,2,0),"") -> Pet Food Manufacturing | R4: =IFERROR(VLOOKUP("Company Industry",#REF!,2,0),"") | S4: =IFERROR(VLOOKUP("Company Industry",#REF!,2,0),"") | T4: =IFERROR(VLOOKUP("Company Industry",#REF!,2,0),"") | U4: =IFERROR(VLOOKUP("Company Industry",#REF!,2,0),"") | V4: =IFERROR(VLOOKUP("Company Industry",'Company 18'!$B:$C,2,0),"") -> 0 | W4: =IFERROR(VLOOKUP("Company Industry",'Company 19'!$B:$C,2,0),"") -> 0 | X4: =IFERROR(VLOOKUP("Company Industry",'Company 20'!$B:$C,2,0),"") -> 0 | Y4: =IFERROR(VLOOKUP("Company Industry",'Company 21'!$B:$C,2,0),"") -> 0 | Z4: =IFERROR(VLOOKUP("Company Industry",'Company 22'!$B:$C,2,0),"") -> 0 | AA4: =IFERROR(VLOOKUP("Company Industry",'Company 23'!$B:$C,2,0),"") -> 0 | AB4: =IFERROR(VLOOKUP("Company Industry",'Company 24'!$B:$C,2,0),"") -> 0 | AC4: =IFERROR(VLOOKUP("Company Industry",'Company 25'!$B:$C,2,0),"") -> 0 | AD4: =IFERROR(VLOOKUP("Company Industry",'Company 26'!$B:$C,2,0),"") -> 0 | AE4: =IFERROR(VLOOKUP("Company Industry",'Company 27'!$B:$C,2,0),"") -> 0 | AF4: =IFERROR(VLOOKUP("Company Industry",'Company 28'!$B:$C,2,0),"") -> 0 | AG4: =IFERROR(VLOOKUP("Company Industry",'Company 29'!$B:$C,2,0),"") -> 0 | AH4: =IFERROR(VLOOKUP("Company Industry",'Company 30'!$B:$C,2,0),"") -> 0
B5: Filter | C5: SUB-INDUSTRY | D5: Company Sub-Industry | E5: =IFERROR(VLOOKUP("Company Sub-Industry",'Company 1'!$B:$C,2,0),"") -> Specialty Retail | F5: =IFERROR(VLOOKUP("Company Sub-Industry",'Company 2'!$B:$C,2,0),"") -> Specialty Retail | G5: =IFERROR(VLOOKUP("Company Sub-Industry",'Company 3'!$B:$C,2,0),"") -> Wholesaler | H5: =IFERROR(VLOOKUP("Company Sub-Industry",'Company 4'!$B:$C,2,0),"") -> Wholesaler | I5: =IFERROR(VLOOKUP("Company Sub-Industry",'Company 5'!$B:$C,2,0),"") -> Manufacturer | J5: =IFERROR(VLOOKUP("Company Sub-Industry",'Company 6'!$B:$C,2,0),"") -> Manufacturer | K5: =IFERROR(VLOOKUP("Company Sub-Industry",'Company 7'!$B:$C,2,0),"") -> Wholesaler | L5: =IFERROR(VLOOKUP("Company Sub-Industry",'Company 8'!$B:$C,2,0),"") -> Manufacturer | M5: =IFERROR(VLOOKUP("Company Sub-Industry",'Company 9'!$B:$C,2,0),"") -> Wholesaler | N5: =IFERROR(VLOOKUP("Company Sub-Industry",'Company 10'!$B:$C,2,0),"") -> Manufacturer | O5: =IFERROR(VLOOKUP("Company Sub-Industry",'Company 11'!$B:$C,2,0),"") -> Specialty Retail | P5: =IFERROR(VLOOKUP("Company Sub-Industry",'Company 12'!$B:$C,2,0),"") -> Retailer | Q5: =IFERROR(VLOOKUP("Company Sub-Industry",'Company 13'!$B:$C,2,0),"") -> Manufacturer | R5: =IFERROR(VLOOKUP("Company Sub-Industry",#REF!,2,0),"") | S5: =IFERROR(VLOOKUP("Company Sub-Industry",#REF!,2,0),"") | T5: =IFERROR(VLOOKUP("Company Sub-Industry",#REF!,2,0),"") | U5: =IFERROR(VLOOKUP("Company Sub-Industry",#REF!,2,0),"") | V5: =IFERROR(VLOOKUP("Company Sub-Industry",'Company 18'!$B:$C,2,0),"") -> 0 | W5: =IFERROR(VLOOKUP("Company Sub-Industry",'Company 19'!$B:$C,2,0),"") -> 0 | X5: =IFERROR(VLOOKUP("Company Sub-Industry",'Company 20'!$B:$C,2,0),"") -> 0 | Y5: =IFERROR(VLOOKUP("Company Sub-Industry",'Company 21'!$B:$C,2,0),"") -> 0 | Z5: =IFERROR(VLOOKUP("Company Sub-Industry",'Company 22'!$B:$C,2,0),"") -> 0 | AA5: =IFERROR(VLOOKUP("Company Sub-Industry",'Company 23'!$B:$C,2,0),"") -> 0 | AB5: =IFERROR(VLOOKUP("Company Sub-Industry",'Company 24'!$B:$C,2,0),"") -> 0 | AC5: =IFERROR(VLOOKUP("Company Sub-Industry",'Company 25'!$B:$C,2,0),"") -> 0 | AD5: =IFERROR(VLOOKUP("Company Sub-Industry",'Company 26'!$B:$C,2,0),"") -> 0 | AE5: =IFERROR(VLOOKUP("Company Sub-Industry",'Company 27'!$B:$C,2,0),"") -> 0 | AF5: =IFERROR(VLOOKUP("Company Sub-Industry",'Company 28'!$B:$C,2,0),"") -> 0 | AG5: =IFERROR(VLOOKUP("Company Sub-Industry",'Company 29'!$B:$C,2,0),"") -> 0 | AH5: =IFERROR(VLOOKUP("Company Sub-Industry",'Company 30'!$B:$C,2,0),"") -> 0
B6: Filter | C6: COMPANY SIZE | D6: Company Size | E6: =IFERROR(VLOOKUP("Company Size (Turnover)",'Company 1'!$B:$C,2,0),"") -> 160000000 | F6: =IFERROR(VLOOKUP("Company Size (Turnover)",'Company 2'!$B:$C,2,0),"") -> 2000000000 | G6: =IFERROR(VLOOKUP("Company Size (Turnover)",'Company 3'!$B:$C,2,0),"") -> 332000000 | H6: =IFERROR(VLOOKUP("Company Size (Turnover)",'Company 4'!$B:$C,2,0),"") -> 332000000 | I6: =IFERROR(VLOOKUP("Company Size (Turnover)",'Company 5'!$B:$C,2,0),"") -> 134000000 | J6: =IFERROR(VLOOKUP("Company Size (Turnover)",'Company 6'!$B:$C,2,0),"") -> 380000000 | K6: =IFERROR(VLOOKUP("Company Size (Turnover)",'Company 7'!$B:$C,2,0),"") -> 7800000 | L6: =IFERROR(VLOOKUP("Company Size (Turnover)",'Company 8'!$B:$C,2,0),"") -> 90000000 | M6: =IFERROR(VLOOKUP("Company Size (Turnover)",'Company 9'!$B:$C,2,0),"") -> 2000000000 | N6: =IFERROR(VLOOKUP("Company Size (Turnover)",'Company 10'!$B:$C,2,0),"") -> 52000000 | O6: =IFERROR(VLOOKUP("Company Size (Turnover)",'Company 11'!$B:$C,2,0),"") -> 140000000 | P6: =IFERROR(VLOOKUP("Company Size (Turnover)",'Company 12'!$B:$C,2,0),"") -> 3240000000 | Q6: =IFERROR(VLOOKUP("Company Size (Turnover)",'Company 13'!$B:$C,2,0),"") -> 140000000 | R6: =IFERROR(VLOOKUP("Company Size (Turnover)",#REF!,2,0),"") | S6: =IFERROR(VLOOKUP("Company Size (Turnover)",#REF!,2,0),"") | T6: =IFERROR(VLOOKUP("Company Size (Turnover)",#REF!,2,0),"") | U6: =IFERROR(VLOOKUP("Company Size (Turnover)",#REF!,2,0),"") | V6: =IFERROR(VLOOKUP("Company Size (Turnover)",'Company 18'!$B:$C,2,0),"") -> 0 | W6: =IFERROR(VLOOKUP("Company Size (Turnover)",'Company 19'!$B:$C,2,0),"") -> 0 | X6: =IFERROR(VLOOKUP("Company Size (Turnover)",'Company 20'!$B:$C,2,0),"") -> 0 | Y6: =IFERROR(VLOOKUP("Company Size (Turnover)",'Company 21'!$B:$C,2,0),"") -> 0 | Z6: =IFERROR(VLOOKUP("Company Size (Turnover)",'Company 22'!$B:$C,2,0),"") -> 0 | AA6: =IFERROR(VLOOKUP("Company Size (Turnover)",'Company 23'!$B:$C,2,0),"") -> 0 | AB6: =IFERROR(VLOOKUP("Company Size (Turnover)",'Company 24'!$B:$C,2,0),"") -> 0 | AC6: =IFERROR(VLOOKUP("Company Size (Turnover)",'Company 25'!$B:$C,2,0),"") -> 0 | AD6: =IFERROR(VLOOKUP("Company Size (Turnover)",'Company 26'!$B:$C,2,0),"") -> 0 | AE6: =IFERROR(VLOOKUP("Company Size (Turnover)",'Company 27'!$B:$C,2,0),"") -> 0 | AF6: =IFERROR(VLOOKUP("Company Size (Turnover)",'Company 28'!$B:$C,2,0),"") -> 0 | AG6: =IFERROR(VLOOKUP("Company Size (Turnover)",'Company 29'!$B:$C,2,0),"") -> 0 | AH6: =IFERROR(VLOOKUP("Company Size (Turnover)",'Company 30'!$B:$C,2,0),"") -> 0
B7: Filter | C7: COUNTRY | D7: Country | E7: =IFERROR(VLOOKUP("Country",'Company 1'!$B:$C,2,0),"") -> Belgium | F7: =IFERROR(VLOOKUP("Country",'Company 2'!$B:$C,2,0),"") -> UK | G7: =IFERROR(VLOOKUP("Country",'Company 3'!$B:$C,2,0),"") -> Belgium | H7: =IFERROR(VLOOKUP("Country",'Company 4'!$B:$C,2,0),"") -> Belgium | I7: =IFERROR(VLOOKUP("Country",'Company 5'!$B:$C,2,0),"") -> Belgium | J7: =IFERROR(VLOOKUP("Country",'Company 6'!$B:$C,2,0),"") -> Belgium | K7: =IFERROR(VLOOKUP("Country",'Company 7'!$B:$C,2,0),"") -> Belgium | L7: =IFERROR(VLOOKUP("Country",'Company 8'!$B:$C,2,0),"") -> US | M7: =IFERROR(VLOOKUP("Country",'Company 9'!$B:$C,2,0),"") -> Belgium | N7: =IFERROR(VLOOKUP("Country",'Company 10'!$B:$C,2,0),"") -> Denmark | O7: =IFERROR(VLOOKUP("Country",'Company 11'!$B:$C,2,0),"") -> Belgium | P7: =IFERROR(VLOOKUP("Country",'Company 12'!$B:$C,2,0),"") -> Germany | Q7: =IFERROR(VLOOKUP("Country",'Company 13'!$B:$C,2,0),"") -> Belgium | R7: =IFERROR(VLOOKUP("Country",#REF!,2,0),"") | S7: =IFERROR(VLOOKUP("Country",#REF!,2,0),"") | T7: =IFERROR(VLOOKUP("Country",#REF!,2,0),"") | U7: =IFERROR(VLOOKUP("Country",#REF!,2,0),"") | V7: =IFERROR(VLOOKUP("Country",'Company 18'!$B:$C,2,0),"") -> 0 | W7: =IFERROR(VLOOKUP("Country",'Company 19'!$B:$C,2,0),"") -> 0 | X7: =IFERROR(VLOOKUP("Country",'Company 20'!$B:$C,2,0),"") -> 0 | Y7: =IFERROR(VLOOKUP("Country",'Company 21'!$B:$C,2,0),"") -> 0 | Z7: =IFERROR(VLOOKUP("Country",'Company 22'!$B:$C,2,0),"") -> 0 | AA7: =IFERROR(VLOOKUP("Country",'Company 23'!$B:$C,2,0),"") -> 0 | AB7: =IFERROR(VLOOKUP("Country",'Company 24'!$B:$C,2,0),"") -> 0 | AC7: =IFERROR(VLOOKUP("Country",'Company 25'!$B:$C,2,0),"") -> 0 | AD7: =IFERROR(VLOOKUP("Country",'Company 26'!$B:$C,2,0),"") -> 0 | AE7: =IFERROR(VLOOKUP("Country",'Company 27'!$B:$C,2,0),"") -> 0 | AF7: =IFERROR(VLOOKUP("Country",'Company 28'!$B:$C,2,0),"") -> 0 | AG7: =IFERROR(VLOOKUP("Country",'Company 29'!$B:$C,2,0),"") -> 0 | AH7: =IFERROR(VLOOKUP("Country",'Company 30'!$B:$C,2,0),"") -> 0
B9: Section | C9: Question ID | D9: Question | E9: Company 1 | F9: Company 2 | G9: Company 3 | H9: Company 4 | I9: Company 5 | J9: Company 6 | K9: Company 7 | L9: Company 8 | M9: Company 9 | N9: Company 10 | O9: Company 11 | P9: Company 12 | Q9: Company 13 | R9: Company 14 | S9: Company 15 | T9: Company 16 | U9: Company 17 | V9: Company 18 | W9: Company 19 | X9: Company 20 | Y9: Company 21 | Z9: Company 22 | AA9: Company 23 | AB9: Company 24 | AC9: Company 25 | AD9: Company 26 | AE9: Company 27 | AF9: Company 28 | AG9: Company 29 | AH9: Company 30
B10: ── BASELINE ──
B11: Baseline | C11: B1_INTEREST | D11: Interest (1–10) | E11: =IFERROR(VLOOKUP("B1_INTEREST",'Company 1'!$B:$E,4,0),"") -> 7 | F11: =IFERROR(VLOOKUP("B1_INTEREST",'Company 2'!$B:$E,4,0),"") -> 2 | G11: =IFERROR(VLOOKUP("B1_INTEREST",'Company 3'!$B:$E,4,0),"") -> 7 | H11: =IFERROR(VLOOKUP("B1_INTEREST",'Company 4'!$B:$E,4,0),"") -> 7.5 | I11: =IFERROR(VLOOKUP("B1_INTEREST",'Company 5'!$B:$E,4,0),"") -> 10 | J11: =IFERROR(VLOOKUP("B1_INTEREST",'Company 6'!$B:$E,4,0),"") -> 8 | K11: =IFERROR(VLOOKUP("B1_INTEREST",'Company 7'!$B:$E,4,0),"") -> 8 | L11: =IFERROR(VLOOKUP("B1_INTEREST",'Company 8'!$B:$E,4,0),"") -> 8 | M11: =IFERROR(VLOOKUP("B1_INTEREST",'Company 9'!$B:$E,4,0),"") -> 8 | N11: =IFERROR(VLOOKUP("B1_INTEREST",'Company 10'!$B:$E,4,0),"") -> 7 | O11: =IFERROR(VLOOKUP("B1_INTEREST",'Company 11'!$B:$E,4,0),"") -> 9 | P11: =IFERROR(VLOOKUP("B1_INTEREST",'Company 12'!$B:$E,4,0),"") -> 3 | Q11: =IFERROR(VLOOKUP("B1_INTEREST",'Company 13'!$B:$E,4,0),"") -> 9 | R11: =IFERROR(VLOOKUP("B1_INTEREST",#REF!,4,0),"") | S11: =IFERROR(VLOOKUP("B1_INTEREST",#REF!,4,0),"") | T11: =IFERROR(VLOOKUP("B1_INTEREST",#REF!,4,0),"") | U11: =IFERROR(VLOOKUP("B1_INTEREST",#REF!,4,0),"") | V11: =IFERROR(VLOOKUP("B1_INTEREST",'Company 18'!$B:$E,4,0),"") -> 0 | W11: =IFERROR(VLOOKUP("B1_INTEREST",'Company 19'!$B:$E,4,0),"") -> 0 | X11: =IFERROR(VLOOKUP("B1_INTEREST",'Company 20'!$B:$E,4,0),"") -> 0 | Y11: =IFERROR(VLOOKUP("B1_INTEREST",'Company 21'!$B:$E,4,0),"") -> 0 | Z11: =IFERROR(VLOOKUP("B1_INTEREST",'Company 22'!$B:$E,4,0),"") -> 0 | AA11: =IFERROR(VLOOKUP("B1_INTEREST",'Company 23'!$B:$E,4,0),"") -> 0 | AB11: =IFERROR(VLOOKUP("B1_INTEREST",'Company 24'!$B:$E,4,0),"") -> 0 | AC11: =IFERROR(VLOOKUP("B1_INTEREST",'Company 25'!$B:$E,4,0),"") -> 0 | AD11: =IFERROR(VLOOKUP("B1_INTEREST",'Company 26'!$B:$E,4,0),"") -> 0 | AE11: =IFERROR(VLOOKUP("B1_INTEREST",'Company 27'!$B:$E,4,0),"") -> 0 | AF11: =IFERROR(VLOOKUP("B1_INTEREST",'Company 28'!$B:$E,4,0),"") -> 0 | AG11: =IFERROR(VLOOKUP("B1_INTEREST",'Company 29'!$B:$E,4,0),"") -> 0 | AH11: =IFERROR(VLOOKUP("B1_INTEREST",'Company 30'!$B:$E,4,0),"") -> 0
B12: Baseline | C12: B2_SHARING | D12: Shares data (0/1) | E12: =IFERROR(VLOOKUP("B2_SHARING",'Company 1'!$B:$E,4,0),"") -> 1 | F12: =IFERROR(VLOOKUP("B2_SHARING",'Company 2'!$B:$E,4,0),"") -> 1 | G12: =IFERROR(VLOOKUP("B2_SHARING",'Company 3'!$B:$E,4,0),"") -> 1 | H12: =IFERROR(VLOOKUP("B2_SHARING",'Company 4'!$B:$E,4,0),"") -> 1 | I12: =IFERROR(VLOOKUP("B2_SHARING",'Company 5'!$B:$E,4,0),"") -> 1 | J12: =IFERROR(VLOOKUP("B2_SHARING",'Company 6'!$B:$E,4,0),"") -> 1 | K12: =IFERROR(VLOOKUP("B2_SHARING",'Company 7'!$B:$E,4,0),"") -> 1 | L12: =IFERROR(VLOOKUP("B2_SHARING",'Company 8'!$B:$E,4,0),"") -> 1 | M12: =IFERROR(VLOOKUP("B2_SHARING",'Company 9'!$B:$E,4,0),"") -> 1 | N12: =IFERROR(VLOOKUP("B2_SHARING",'Company 10'!$B:$E,4,0),"") -> 1 | O12: =IFERROR(VLOOKUP("B2_SHARING",'Company 11'!$B:$E,4,0),"") -> 1 | P12: =IFERROR(VLOOKUP("B2_SHARING",'Company 12'!$B:$E,4,0),"") -> 1 | Q12: =IFERROR(VLOOKUP("B2_SHARING",'Company 13'!$B:$E,4,0),"") -> 1 | R12: =IFERROR(VLOOKUP("B2_SHARING",#REF!,4,0),"") | S12: =IFERROR(VLOOKUP("B2_SHARING",#REF!,4,0),"") | T12: =IFERROR(VLOOKUP("B2_SHARING",#REF!,4,0),"") | U12: =IFERROR(VLOOKUP("B2_SHARING",#REF!,4,0),"") | V12: =IFERROR(VLOOKUP("B2_SHARING",'Company 18'!$B:$E,4,0),"") -> 0 | W12: =IFERROR(VLOOKUP("B2_SHARING",'Company 19'!$B:$E,4,0),"") -> 0 | X12: =IFERROR(VLOOKUP("B2_SHARING",'Company 20'!$B:$E,4,0),"") -> 0 | Y12: =IFERROR(VLOOKUP("B2_SHARING",'Company 21'!$B:$E,4,0),"") -> 0 | Z12: =IFERROR(VLOOKUP("B2_SHARING",'Company 22'!$B:$E,4,0),"") -> 0 | AA12: =IFERROR(VLOOKUP("B2_SHARING",'Company 23'!$B:$E,4,0),"") -> 0 | AB12: =IFERROR(VLOOKUP("B2_SHARING",'Company 24'!$B:$E,4,0),"") -> 0 | AC12: =IFERROR(VLOOKUP("B2_SHARING",'Company 25'!$B:$E,4,0),"") -> 0 | AD12: =IFERROR(VLOOKUP("B2_SHARING",'Company 26'!$B:$E,4,0),"") -> 0 | AE12: =IFERROR(VLOOKUP("B2_SHARING",'Company 27'!$B:$E,4,0),"") -> 0 | AF12: =IFERROR(VLOOKUP("B2_SHARING",'Company 28'!$B:$E,4,0),"") -> 0 | AG12: =IFERROR(VLOOKUP("B2_SHARING",'Company 29'!$B:$E,4,0),"") -> 0 | AH12: =IFERROR(VLOOKUP("B2_SHARING",'Company 30'!$B:$E,4,0),"") -> 0
B13: Baseline | C13: B3_MONETIZE | D13: Monetizes data (0/1) | E13: =IFERROR(VLOOKUP("B3_MONETIZE",'Company 1'!$B:$E,4,0),"") -> 1 | F13: =IFERROR(VLOOKUP("B3_MONETIZE",'Company 2'!$B:$E,4,0),"") -> 0 | G13: =IFERROR(VLOOKUP("B3_MONETIZE",'Company 3'!$B:$E,4,0),"") -> 1 | H13: =IFERROR(VLOOKUP("B3_MONETIZE",'Company 4'!$B:$E,4,0),"") -> 0 | I13: =IFERROR(VLOOKUP("B3_MONETIZE",'Company 5'!$B:$E,4,0),"") -> 0 | J13: =IFERROR(VLOOKUP("B3_MONETIZE",'Company 6'!$B:$E,4,0),"") -> 0 | K13: =IFERROR(VLOOKUP("B3_MONETIZE",'Company 7'!$B:$E,4,0),"") -> 1 | L13: =IFERROR(VLOOKUP("B3_MONETIZE",'Company 8'!$B:$E,4,0),"") -> 0 | M13: =IFERROR(VLOOKUP("B3_MONETIZE",'Company 9'!$B:$E,4,0),"") -> 1 | N13: =IFERROR(VLOOKUP("B3_MONETIZE",'Company 10'!$B:$E,4,0),"") -> 0 | O13: =IFERROR(VLOOKUP("B3_MONETIZE",'Company 11'!$B:$E,4,0),"") -> 0 | P13: =IFERROR(VLOOKUP("B3_MONETIZE",'Company 12'!$B:$E,4,0),"") -> 0 | Q13: =IFERROR(VLOOKUP("B3_MONETIZE",'Company 13'!$B:$E,4,0),"") -> 0 | R13: =IFERROR(VLOOKUP("B3_MONETIZE",#REF!,4,0),"") | S13: =IFERROR(VLOOKUP("B3_MONETIZE",#REF!,4,0),"") | T13: =IFERROR(VLOOKUP("B3_MONETIZE",#REF!,4,0),"") | U13: =IFERROR(VLOOKUP("B3_MONETIZE",#REF!,4,0),"") | V13: =IFERROR(VLOOKUP("B3_MONETIZE",'Company 18'!$B:$E,4,0),"") -> 0 | W13: =IFERROR(VLOOKUP("B3_MONETIZE",'Company 19'!$B:$E,4,0),"") -> 0 | X13: =IFERROR(VLOOKUP("B3_MONETIZE",'Company 20'!$B:$E,4,0),"") -> 0 | Y13: =IFERROR(VLOOKUP("B3_MONETIZE",'Company 21'!$B:$E,4,0),"") -> 0 | Z13: =IFERROR(VLOOKUP("B3_MONETIZE",'Company 22'!$B:$E,4,0),"") -> 0 | AA13: =IFERROR(VLOOKUP("B3_MONETIZE",'Company 23'!$B:$E,4,0),"") -> 0 | AB13: =IFERROR(VLOOKUP("B3_MONETIZE",'Company 24'!$B:$E,4,0),"") -> 0 | AC13: =IFERROR(VLOOKUP("B3_MONETIZE",'Company 25'!$B:$E,4,0),"") -> 0 | AD13: =IFERROR(VLOOKUP("B3_MONETIZE",'Company 26'!$B:$E,4,0),"") -> 0 | AE13: =IFERROR(VLOOKUP("B3_MONETIZE",'Company 27'!$B:$E,4,0),"") -> 0 | AF13: =IFERROR(VLOOKUP("B3_MONETIZE",'Company 28'!$B:$E,4,0),"") -> 0 | AG13: =IFERROR(VLOOKUP("B3_MONETIZE",'Company 29'!$B:$E,4,0),"") -> 0 | AH13: =IFERROR(VLOOKUP("B3_MONETIZE",'Company 30'!$B:$E,4,0),"") -> 0
B14: Baseline | C14: B4_STRATEGIC | D14: Strategic reasons (0/1) | E14: =IFERROR(VLOOKUP("B4_STRATEGIC",'Company 1'!$B:$E,4,0),"") -> 0 | F14: =IFERROR(VLOOKUP("B4_STRATEGIC",'Company 2'!$B:$E,4,0),"") -> 1 | G14: =IFERROR(VLOOKUP("B4_STRATEGIC",'Company 3'!$B:$E,4,0),"") -> 1 | H14: =IFERROR(VLOOKUP("B4_STRATEGIC",'Company 4'!$B:$E,4,0),"") -> 1 | I14: =IFERROR(VLOOKUP("B4_STRATEGIC",'Company 5'!$B:$E,4,0),"") -> 1 | J14: =IFERROR(VLOOKUP("B4_STRATEGIC",'Company 6'!$B:$E,4,0),"") -> 1 | K14: =IFERROR(VLOOKUP("B4_STRATEGIC",'Company 7'!$B:$E,4,0),"") -> 0 | L14: =IFERROR(VLOOKUP("B4_STRATEGIC",'Company 8'!$B:$E,4,0),"") -> 0 | M14: =IFERROR(VLOOKUP("B4_STRATEGIC",'Company 9'!$B:$E,4,0),"") -> 0 | N14: =IFERROR(VLOOKUP("B4_STRATEGIC",'Company 10'!$B:$E,4,0),"") -> 1 | O14: =IFERROR(VLOOKUP("B4_STRATEGIC",'Company 11'!$B:$E,4,0),"") -> 0 | P14: =IFERROR(VLOOKUP("B4_STRATEGIC",'Company 12'!$B:$E,4,0),"") -> 1 | Q14: =IFERROR(VLOOKUP("B4_STRATEGIC",'Company 13'!$B:$E,4,0),"") -> 0 | R14: =IFERROR(VLOOKUP("B4_STRATEGIC",#REF!,4,0),"") | S14: =IFERROR(VLOOKUP("B4_STRATEGIC",#REF!,4,0),"") | T14: =IFERROR(VLOOKUP("B4_STRATEGIC",#REF!,4,0),"") | U14: =IFERROR(VLOOKUP("B4_STRATEGIC",#REF!,4,0),"") | V14: =IFERROR(VLOOKUP("B4_STRATEGIC",'Company 18'!$B:$E,4,0),"") -> 0 | W14: =IFERROR(VLOOKUP("B4_STRATEGIC",'Company 19'!$B:$E,4,0),"") -> 0 | X14: =IFERROR(VLOOKUP("B4_STRATEGIC",'Company 20'!$B:$E,4,0),"") -> 0 | Y14: =IFERROR(VLOOKUP("B4_STRATEGIC",'Company 21'!$B:$E,4,0),"") -> 0 | Z14: =IFERROR(VLOOKUP("B4_STRATEGIC",'Company 22'!$B:$E,4,0),"") -> 0 | AA14: =IFERROR(VLOOKUP("B4_STRATEGIC",'Company 23'!$B:$E,4,0),"") -> 0 | AB14: =IFERROR(VLOOKUP("B4_STRATEGIC",'Company 24'!$B:$E,4,0),"") -> 0 | AC14: =IFERROR(VLOOKUP("B4_STRATEGIC",'Company 25'!$B:$E,4,0),"") -> 0 | AD14: =IFERROR(VLOOKUP("B4_STRATEGIC",'Company 26'!$B:$E,4,0),"") -> 0 | AE14: =IFERROR(VLOOKUP("B4_STRATEGIC",'Company 27'!$B:$E,4,0),"") -> 0 | AF14: =IFERROR(VLOOKUP("B4_STRATEGIC",'Company 28'!$B:$E,4,0),"") -> 0 | AG14: =IFERROR(VLOOKUP("B4_STRATEGIC",'Company 29'!$B:$E,4,0),"") -> 0 | AH14: =IFERROR(VLOOKUP("B4_STRATEGIC",'Company 30'!$B:$E,4,0),"") -> 0
B15: ── MATURITY ──
B16: Maturity | C16: M1_AUTOMATED | D16: Automated vs manual | E16: =IFERROR(VLOOKUP("M1_AUTOMATED",'Company 1'!$B:$E,4,0),"") -> 3 | F16: =IFERROR(VLOOKUP("M1_AUTOMATED",'Company 2'!$B:$E,4,0),"") -> 0 | G16: =IFERROR(VLOOKUP("M1_AUTOMATED",'Company 3'!$B:$E,4,0),"") -> 4 | H16: =IFERROR(VLOOKUP("M1_AUTOMATED",'Company 4'!$B:$E,4,0),"") -> 3 | I16: =IFERROR(VLOOKUP("M1_AUTOMATED",'Company 5'!$B:$E,4,0),"") -> 2 | J16: =IFERROR(VLOOKUP("M1_AUTOMATED",'Company 6'!$B:$E,4,0),"") -> 5 | K16: =IFERROR(VLOOKUP("M1_AUTOMATED",'Company 7'!$B:$E,4,0),"") -> 1 | L16: =IFERROR(VLOOKUP("M1_AUTOMATED",'Company 8'!$B:$E,4,0),"") -> 3 | M16: =IFERROR(VLOOKUP("M1_AUTOMATED",'Company 9'!$B:$E,4,0),"") -> 3 | N16: =IFERROR(VLOOKUP("M1_AUTOMATED",'Company 10'!$B:$E,4,0),"") -> 2 | O16: =IFERROR(VLOOKUP("M1_AUTOMATED",'Company 11'!$B:$E,4,0),"") -> 1 | P16: =IFERROR(VLOOKUP("M1_AUTOMATED",'Company 12'!$B:$E,4,0),"") -> 0 | Q16: =IFERROR(VLOOKUP("M1_AUTOMATED",'Company 13'!$B:$E,4,0),"") -> 3 | R16: =IFERROR(VLOOKUP("M1_AUTOMATED",#REF!,4,0),"") | S16: =IFERROR(VLOOKUP("M1_AUTOMATED",#REF!,4,0),"") | T16: =IFERROR(VLOOKUP("M1_AUTOMATED",#REF!,4,0),"") | U16: =IFERROR(VLOOKUP("M1_AUTOMATED",#REF!,4,0),"") | V16: =IFERROR(VLOOKUP("M1_AUTOMATED",'Company 18'!$B:$E,4,0),"") -> 0 | W16: =IFERROR(VLOOKUP("M1_AUTOMATED",'Company 19'!$B:$E,4,0),"") -> 0 | X16: =IFERROR(VLOOKUP("M1_AUTOMATED",'Company 20'!$B:$E,4,0),"") -> 0 | Y16: =IFERROR(VLOOKUP("M1_AUTOMATED",'Company 21'!$B:$E,4,0),"") -> 0 | Z16: =IFERROR(VLOOKUP("M1_AUTOMATED",'Company 22'!$B:$E,4,0),"") -> 0 | AA16: =IFERROR(VLOOKUP("M1_AUTOMATED",'Company 23'!$B:$E,4,0),"") -> 0 | AB16: =IFERROR(VLOOKUP("M1_AUTOMATED",'Company 24'!$B:$E,4,0),"") -> 0 | AC16: =IFERROR(VLOOKUP("M1_AUTOMATED",'Company 25'!$B:$E,4,0),"") -> 0 | AD16: =IFERROR(VLOOKUP("M1_AUTOMATED",'Company 26'!$B:$E,4,0),"") -> 0 | AE16: =IFERROR(VLOOKUP("M1_AUTOMATED",'Company 27'!$B:$E,4,0),"") -> 0 | AF16: =IFERROR(VLOOKUP("M1_AUTOMATED",'Company 28'!$B:$E,4,0),"") -> 0 | AG16: =IFERROR(VLOOKUP("M1_AUTOMATED",'Company 29'!$B:$E,4,0),"") -> 0 | AH16: =IFERROR(VLOOKUP("M1_AUTOMATED",'Company 30'!$B:$E,4,0),"") -> 0
B17: Maturity | C17: M2_REALTIME | D17: Real-time vs lagging | E17: =IFERROR(VLOOKUP("M2_REALTIME",'Company 1'!$B:$E,4,0),"") -> 2 | F17: =IFERROR(VLOOKUP("M2_REALTIME",'Company 2'!$B:$E,4,0),"") -> 0 | G17: =IFERROR(VLOOKUP("M2_REALTIME",'Company 3'!$B:$E,4,0),"") -> 4 | H17: =IFERROR(VLOOKUP("M2_REALTIME",'Company 4'!$B:$E,4,0),"") -> 2 | I17: =IFERROR(VLOOKUP("M2_REALTIME",'Company 5'!$B:$E,4,0),"") -> 2 | J17: =IFERROR(VLOOKUP("M2_REALTIME",'Company 6'!$B:$E,4,0),"") -> 4 | K17: =IFERROR(VLOOKUP("M2_REALTIME",'Company 7'!$B:$E,4,0),"") -> 2 | L17: =IFERROR(VLOOKUP("M2_REALTIME",'Company 8'!$B:$E,4,0),"") -> 2 | M17: =IFERROR(VLOOKUP("M2_REALTIME",'Company 9'!$B:$E,4,0),"") -> 2 | N17: =IFERROR(VLOOKUP("M2_REALTIME",'Company 10'!$B:$E,4,0),"") -> 2 | O17: =IFERROR(VLOOKUP("M2_REALTIME",'Company 11'!$B:$E,4,0),"") -> 1 | P17: =IFERROR(VLOOKUP("M2_REALTIME",'Company 12'!$B:$E,4,0),"") -> 0 | Q17: =IFERROR(VLOOKUP("M2_REALTIME",'Company 13'!$B:$E,4,0),"") -> 3 | R17: =IFERROR(VLOOKUP("M2_REALTIME",#REF!,4,0),"") | S17: =IFERROR(VLOOKUP("M2_REALTIME",#REF!,4,0),"") | T17: =IFERROR(VLOOKUP("M2_REALTIME",#REF!,4,0),"") | U17: =IFERROR(VLOOKUP("M2_REALTIME",#REF!,4,0),"") | V17: =IFERROR(VLOOKUP("M2_REALTIME",'Company 18'!$B:$E,4,0),"") -> 0 | W17: =IFERROR(VLOOKUP("M2_REALTIME",'Company 19'!$B:$E,4,0),"") -> 0 | X17: =IFERROR(VLOOKUP("M2_REALTIME",'Company 20'!$B:$E,4,0),"") -> 0 | Y17: =IFERROR(VLOOKUP("M2_REALTIME",'Company 21'!$B:$E,4,0),"") -> 0 | Z17: =IFERROR(VLOOKUP("M2_REALTIME",'Company 22'!$B:$E,4,0),"") -> 0 | AA17: =IFERROR(VLOOKUP("M2_REALTIME",'Company 23'!$B:$E,4,0),"") -> 0 | AB17: =IFERROR(VLOOKUP("M2_REALTIME",'Company 24'!$B:$E,4,0),"") -> 0 | AC17: =IFERROR(VLOOKUP("M2_REALTIME",'Company 25'!$B:$E,4,0),"") -> 0 | AD17: =IFERROR(VLOOKUP("M2_REALTIME",'Company 26'!$B:$E,4,0),"") -> 0 | AE17: =IFERROR(VLOOKUP("M2_REALTIME",'Company 27'!$B:$E,4,0),"") -> 0 | AF17: =IFERROR(VLOOKUP("M2_REALTIME",'Company 28'!$B:$E,4,0),"") -> 0 | AG17: =IFERROR(VLOOKUP("M2_REALTIME",'Company 29'!$B:$E,4,0),"") -> 0 | AH17: =IFERROR(VLOOKUP("M2_REALTIME",'Company 30'!$B:$E,4,0),"") -> 0
B18: Maturity | C18: M3_STRATEGIC | D18: Ops vs strategic focus | E18: =IFERROR(VLOOKUP("M3_STRATEGIC",'Company 1'!$B:$E,4,0),"") -> 2 | F18: =IFERROR(VLOOKUP("M3_STRATEGIC",'Company 2'!$B:$E,4,0),"") -> 1 | G18: =IFERROR(VLOOKUP("M3_STRATEGIC",'Company 3'!$B:$E,4,0),"") -> 4 | H18: =IFERROR(VLOOKUP("M3_STRATEGIC",'Company 4'!$B:$E,4,0),"") -> 4 | I18: =IFERROR(VLOOKUP("M3_STRATEGIC",'Company 5'!$B:$E,4,0),"") -> 2 | J18: =IFERROR(VLOOKUP("M3_STRATEGIC",'Company 6'!$B:$E,4,0),"") -> 4 | K18: =IFERROR(VLOOKUP("M3_STRATEGIC",'Company 7'!$B:$E,4,0),"") -> 4 | L18: =IFERROR(VLOOKUP("M3_STRATEGIC",'Company 8'!$B:$E,4,0),"") -> 4 | M18: =IFERROR(VLOOKUP("M3_STRATEGIC",'Company 9'!$B:$E,4,0),"") -> 4 | N18: =IFERROR(VLOOKUP("M3_STRATEGIC",'Company 10'!$B:$E,4,0),"") -> 5 | O18: =IFERROR(VLOOKUP("M3_STRATEGIC",'Company 11'!$B:$E,4,0),"") -> 2 | P18: =IFERROR(VLOOKUP("M3_STRATEGIC",'Company 12'!$B:$E,4,0),"") -> 2 | Q18: =IFERROR(VLOOKUP("M3_STRATEGIC",'Company 13'!$B:$E,4,0),"") -> 4 | R18: =IFERROR(VLOOKUP("M3_STRATEGIC",#REF!,4,0),"") | S18: =IFERROR(VLOOKUP("M3_STRATEGIC",#REF!,4,0),"") | T18: =IFERROR(VLOOKUP("M3_STRATEGIC",#REF!,4,0),"") | U18: =IFERROR(VLOOKUP("M3_STRATEGIC",#REF!,4,0),"") | V18: =IFERROR(VLOOKUP("M3_STRATEGIC",'Company 18'!$B:$E,4,0),"") -> 0 | W18: =IFERROR(VLOOKUP("M3_STRATEGIC",'Company 19'!$B:$E,4,0),"") -> 0 | X18: =IFERROR(VLOOKUP("M3_STRATEGIC",'Company 20'!$B:$E,4,0),"") -> 0 | Y18: =IFERROR(VLOOKUP("M3_STRATEGIC",'Company 21'!$B:$E,4,0),"") -> 0 | Z18: =IFERROR(VLOOKUP("M3_STRATEGIC",'Company 22'!$B:$E,4,0),"") -> 0 | AA18: =IFERROR(VLOOKUP("M3_STRATEGIC",'Company 23'!$B:$E,4,0),"") -> 0 | AB18: =IFERROR(VLOOKUP("M3_STRATEGIC",'Company 24'!$B:$E,4,0),"") -> 0 | AC18: =IFERROR(VLOOKUP("M3_STRATEGIC",'Company 25'!$B:$E,4,0),"") -> 0 | AD18: =IFERROR(VLOOKUP("M3_STRATEGIC",'Company 26'!$B:$E,4,0),"") -> 0 | AE18: =IFERROR(VLOOKUP("M3_STRATEGIC",'Company 27'!$B:$E,4,0),"") -> 0 | AF18: =IFERROR(VLOOKUP("M3_STRATEGIC",'Company 28'!$B:$E,4,0),"") -> 0 | AG18: =IFERROR(VLOOKUP("M3_STRATEGIC",'Company 29'!$B:$E,4,0),"") -> 0 | AH18: =IFERROR(VLOOKUP("M3_STRATEGIC",'Company 30'!$B:$E,4,0),"") -> 0
B19: Maturity | C19: M4_BREADTH | D19: All clients vs selective | E19: =IFERROR(VLOOKUP("M4_BREADTH",'Company 1'!$B:$E,4,0),"") -> 2 | F19: =IFERROR(VLOOKUP("M4_BREADTH",'Company 2'!$B:$E,4,0),"") -> 1 | G19: =IFERROR(VLOOKUP("M4_BREADTH",'Company 3'!$B:$E,4,0),"") -> 5 | H19: =IFERROR(VLOOKUP("M4_BREADTH",'Company 4'!$B:$E,4,0),"") -> 2 | I19: =IFERROR(VLOOKUP("M4_BREADTH",'Company 5'!$B:$E,4,0),"") -> 4 | J19: =IFERROR(VLOOKUP("M4_BREADTH",'Company 6'!$B:$E,4,0),"") -> 3 | K19: =IFERROR(VLOOKUP("M4_BREADTH",'Company 7'!$B:$E,4,0),"") -> 3 | L19: =IFERROR(VLOOKUP("M4_BREADTH",'Company 8'!$B:$E,4,0),"") -> 3 | M19: =IFERROR(VLOOKUP("M4_BREADTH",'Company 9'!$B:$E,4,0),"") -> 2 | N19: =IFERROR(VLOOKUP("M4_BREADTH",'Company 10'!$B:$E,4,0),"") -> 3 | O19: =IFERROR(VLOOKUP("M4_BREADTH",'Company 11'!$B:$E,4,0),"") -> 2 | P19: =IFERROR(VLOOKUP("M4_BREADTH",'Company 12'!$B:$E,4,0),"") -> 1 | Q19: =IFERROR(VLOOKUP("M4_BREADTH",'Company 13'!$B:$E,4,0),"") -> 3 | R19: =IFERROR(VLOOKUP("M4_BREADTH",#REF!,4,0),"") | S19: =IFERROR(VLOOKUP("M4_BREADTH",#REF!,4,0),"") | T19: =IFERROR(VLOOKUP("M4_BREADTH",#REF!,4,0),"") | U19: =IFERROR(VLOOKUP("M4_BREADTH",#REF!,4,0),"") | V19: =IFERROR(VLOOKUP("M4_BREADTH",'Company 18'!$B:$E,4,0),"") -> 0 | W19: =IFERROR(VLOOKUP("M4_BREADTH",'Company 19'!$B:$E,4,0),"") -> 0 | X19: =IFERROR(VLOOKUP("M4_BREADTH",'Company 20'!$B:$E,4,0),"") -> 0 | Y19: =IFERROR(VLOOKUP("M4_BREADTH",'Company 21'!$B:$E,4,0),"") -> 0 | Z19: =IFERROR(VLOOKUP("M4_BREADTH",'Company 22'!$B:$E,4,0),"") -> 0 | AA19: =IFERROR(VLOOKUP("M4_BREADTH",'Company 23'!$B:$E,4,0),"") -> 0 | AB19: =IFERROR(VLOOKUP("M4_BREADTH",'Company 24'!$B:$E,4,0),"") -> 0 | AC19: =IFERROR(VLOOKUP("M4_BREADTH",'Company 25'!$B:$E,4,0),"") -> 0 | AD19: =IFERROR(VLOOKUP("M4_BREADTH",'Company 26'!$B:$E,4,0),"") -> 0 | AE19: =IFERROR(VLOOKUP("M4_BREADTH",'Company 27'!$B:$E,4,0),"") -> 0 | AF19: =IFERROR(VLOOKUP("M4_BREADTH",'Company 28'!$B:$E,4,0),"") -> 0 | AG19: =IFERROR(VLOOKUP("M4_BREADTH",'Company 29'!$B:$E,4,0),"") -> 0 | AH19: =IFERROR(VLOOKUP("M4_BREADTH",'Company 30'!$B:$E,4,0),"") -> 0
B20: Maturity | C20: M5_DATATYPES | D20: Breadth of data | E20: =IFERROR(VLOOKUP("M5_DATATYPES",'Company 1'!$B:$E,4,0),"") -> 2 | F20: =IFERROR(VLOOKUP("M5_DATATYPES",'Company 2'!$B:$E,4,0),"") -> 1 | G20: =IFERROR(VLOOKUP("M5_DATATYPES",'Company 3'!$B:$E,4,0),"") -> 4 | H20: =IFERROR(VLOOKUP("M5_DATATYPES",'Company 4'!$B:$E,4,0),"") -> 3 | I20: =IFERROR(VLOOKUP("M5_DATATYPES",'Company 5'!$B:$E,4,0),"") -> 2 | J20: =IFERROR(VLOOKUP("M5_DATATYPES",'Company 6'!$B:$E,4,0),"") -> 5 | K20: =IFERROR(VLOOKUP("M5_DATATYPES",'Company 7'!$B:$E,4,0),"") -> 3 | L20: =IFERROR(VLOOKUP("M5_DATATYPES",'Company 8'!$B:$E,4,0),"") -> 4 | M20: =IFERROR(VLOOKUP("M5_DATATYPES",'Company 9'!$B:$E,4,0),"") -> 5 | N20: =IFERROR(VLOOKUP("M5_DATATYPES",'Company 10'!$B:$E,4,0),"") -> 5 | O20: =IFERROR(VLOOKUP("M5_DATATYPES",'Company 11'!$B:$E,4,0),"") -> 2 | P20: =IFERROR(VLOOKUP("M5_DATATYPES",'Company 12'!$B:$E,4,0),"") -> 2 | Q20: =IFERROR(VLOOKUP("M5_DATATYPES",'Company 13'!$B:$E,4,0),"") -> 4 | R20: =IFERROR(VLOOKUP("M5_DATATYPES",#REF!,4,0),"") | S20: =IFERROR(VLOOKUP("M5_DATATYPES",#REF!,4,0),"") | T20: =IFERROR(VLOOKUP("M5_DATATYPES",#REF!,4,0),"") | U20: =IFERROR(VLOOKUP("M5_DATATYPES",#REF!,4,0),"") | V20: =IFERROR(VLOOKUP("M5_DATATYPES",'Company 18'!$B:$E,4,0),"") -> 0 | W20: =IFERROR(VLOOKUP("M5_DATATYPES",'Company 19'!$B:$E,4,0),"") -> 0 | X20: =IFERROR(VLOOKUP("M5_DATATYPES",'Company 20'!$B:$E,4,0),"") -> 0 | Y20: =IFERROR(VLOOKUP("M5_DATATYPES",'Company 21'!$B:$E,4,0),"") -> 0 | Z20: =IFERROR(VLOOKUP("M5_DATATYPES",'Company 22'!$B:$E,4,0),"") -> 0 | AA20: =IFERROR(VLOOKUP("M5_DATATYPES",'Company 23'!$B:$E,4,0),"") -> 0 | AB20: =IFERROR(VLOOKUP("M5_DATATYPES",'Company 24'!$B:$E,4,0),"") -> 0 | AC20: =IFERROR(VLOOKUP("M5_DATATYPES",'Company 25'!$B:$E,4,0),"") -> 0 | AD20: =IFERROR(VLOOKUP("M5_DATATYPES",'Company 26'!$B:$E,4,0),"") -> 0 | AE20: =IFERROR(VLOOKUP("M5_DATATYPES",'Company 27'!$B:$E,4,0),"") -> 0 | AF20: =IFERROR(VLOOKUP("M5_DATATYPES",'Company 28'!$B:$E,4,0),"") -> 0 | AG20: =IFERROR(VLOOKUP("M5_DATATYPES",'Company 29'!$B:$E,4,0),"") -> 0 | AH20: =IFERROR(VLOOKUP("M5_DATATYPES",'Company 30'!$B:$E,4,0),"") -> 0
B21: Maturity | C21: M6_TRUST | D21: Trust in data | E21: =IFERROR(VLOOKUP("M6_TRUST",'Company 1'!$B:$E,4,0),"") -> 4 | F21: =IFERROR(VLOOKUP("M6_TRUST",'Company 2'!$B:$E,4,0),"") -> 0 | G21: =IFERROR(VLOOKUP("M6_TRUST",'Company 3'!$B:$E,4,0),"") -> 3 | H21: =IFERROR(VLOOKUP("M6_TRUST",'Company 4'!$B:$E,4,0),"") -> 2 | I21: =IFERROR(VLOOKUP("M6_TRUST",'Company 5'!$B:$E,4,0),"") -> 2 | J21: =IFERROR(VLOOKUP("M6_TRUST",'Company 6'!$B:$E,4,0),"") -> 2 | K21: =IFERROR(VLOOKUP("M6_TRUST",'Company 7'!$B:$E,4,0),"") -> 0 | L21: =IFERROR(VLOOKUP("M6_TRUST",'Company 8'!$B:$E,4,0),"") -> 4 | M21: =IFERROR(VLOOKUP("M6_TRUST",'Company 9'!$B:$E,4,0),"") -> 2 | N21: =IFERROR(VLOOKUP("M6_TRUST",'Company 10'!$B:$E,4,0),"") -> 3 | O21: =IFERROR(VLOOKUP("M6_TRUST",'Company 11'!$B:$E,4,0),"") -> 0 | P21: =IFERROR(VLOOKUP("M6_TRUST",'Company 12'!$B:$E,4,0),"") -> 0 | Q21: =IFERROR(VLOOKUP("M6_TRUST",'Company 13'!$B:$E,4,0),"") -> 2 | R21: =IFERROR(VLOOKUP("M6_TRUST",#REF!,4,0),"") | S21: =IFERROR(VLOOKUP("M6_TRUST",#REF!,4,0),"") | T21: =IFERROR(VLOOKUP("M6_TRUST",#REF!,4,0),"") | U21: =IFERROR(VLOOKUP("M6_TRUST",#REF!,4,0),"") | V21: =IFERROR(VLOOKUP("M6_TRUST",'Company 18'!$B:$E,4,0),"") -> 0 | W21: =IFERROR(VLOOKUP("M6_TRUST",'Company 19'!$B:$E,4,0),"") -> 0 | X21: =IFERROR(VLOOKUP("M6_TRUST",'Company 20'!$B:$E,4,0),"") -> 0 | Y21: =IFERROR(VLOOKUP("M6_TRUST",'Company 21'!$B:$E,4,0),"") -> 0 | Z21: =IFERROR(VLOOKUP("M6_TRUST",'Company 22'!$B:$E,4,0),"") -> 0 | AA21: =IFERROR(VLOOKUP("M6_TRUST",'Company 23'!$B:$E,4,0),"") -> 0 | AB21: =IFERROR(VLOOKUP("M6_TRUST",'Company 24'!$B:$E,4,0),"") -> 0 | AC21: =IFERROR(VLOOKUP("M6_TRUST",'Company 25'!$B:$E,4,0),"") -> 0 | AD21: =IFERROR(VLOOKUP("M6_TRUST",'Company 26'!$B:$E,4,0),"") -> 0 | AE21: =IFERROR(VLOOKUP("M6_TRUST",'Company 27'!$B:$E,4,0),"") -> 0 | AF21: =IFERROR(VLOOKUP("M6_TRUST",'Company 28'!$B:$E,4,0),"") -> 0 | AG21: =IFERROR(VLOOKUP("M6_TRUST",'Company 29'!$B:$E,4,0),"") -> 0 | AH21: =IFERROR(VLOOKUP("M6_TRUST",'Company 30'!$B:$E,4,0),"") -> 0
B22: Maturity | C22: M7_BARRIERS | D22: Readiness/barriers | E22: =IFERROR(VLOOKUP("M7_BARRIERS",'Company 1'!$B:$E,4,0),"") -> 3 | F22: =IFERROR(VLOOKUP("M7_BARRIERS",'Company 2'!$B:$E,4,0),"") -> 5 | G22: =IFERROR(VLOOKUP("M7_BARRIERS",'Company 3'!$B:$E,4,0),"") -> 4 | H22: =IFERROR(VLOOKUP("M7_BARRIERS",'Company 4'!$B:$E,4,0),"") -> 3 | I22: =IFERROR(VLOOKUP("M7_BARRIERS",'Company 5'!$B:$E,4,0),"") -> 4 | J22: =IFERROR(VLOOKUP("M7_BARRIERS",'Company 6'!$B:$E,4,0),"") -> 5 | K22: =IFERROR(VLOOKUP("M7_BARRIERS",'Company 7'!$B:$E,4,0),"") -> 2 | L22: =IFERROR(VLOOKUP("M7_BARRIERS",'Company 8'!$B:$E,4,0),"") -> 4 | M22: =IFERROR(VLOOKUP("M7_BARRIERS",'Company 9'!$B:$E,4,0),"") -> 4 | N22: =IFERROR(VLOOKUP("M7_BARRIERS",'Company 10'!$B:$E,4,0),"") -> 4 | O22: =IFERROR(VLOOKUP("M7_BARRIERS",'Company 11'!$B:$E,4,0),"") -> 2 | P22: =IFERROR(VLOOKUP("M7_BARRIERS",'Company 12'!$B:$E,4,0),"") -> 4 | Q22: =IFERROR(VLOOKUP("M7_BARRIERS",'Company 13'!$B:$E,4,0),"") -> 3 | R22: =IFERROR(VLOOKUP("M7_BARRIERS",#REF!,4,0),"") | S22: =IFERROR(VLOOKUP("M7_BARRIERS",#REF!,4,0),"") | T22: =IFERROR(VLOOKUP("M7_BARRIERS",#REF!,4,0),"") | U22: =IFERROR(VLOOKUP("M7_BARRIERS",#REF!,4,0),"") | V22: =IFERROR(VLOOKUP("M7_BARRIERS",'Company 18'!$B:$E,4,0),"") -> 0 | W22: =IFERROR(VLOOKUP("M7_BARRIERS",'Company 19'!$B:$E,4,0),"") -> 0 | X22: =IFERROR(VLOOKUP("M7_BARRIERS",'Company 20'!$B:$E,4,0),"") -> 0 | Y22: =IFERROR(VLOOKUP("M7_BARRIERS",'Company 21'!$B:$E,4,0),"") -> 0 | Z22: =IFERROR(VLOOKUP("M7_BARRIERS",'Company 22'!$B:$E,4,0),"") -> 0 | AA22: =IFERROR(VLOOKUP("M7_BARRIERS",'Company 23'!$B:$E,4,0),"") -> 0 | AB22: =IFERROR(VLOOKUP("M7_BARRIERS",'Company 24'!$B:$E,4,0),"") -> 0 | AC22: =IFERROR(VLOOKUP("M7_BARRIERS",'Company 25'!$B:$E,4,0),"") -> 0 | AD22: =IFERROR(VLOOKUP("M7_BARRIERS",'Company 26'!$B:$E,4,0),"") -> 0 | AE22: =IFERROR(VLOOKUP("M7_BARRIERS",'Company 27'!$B:$E,4,0),"") -> 0 | AF22: =IFERROR(VLOOKUP("M7_BARRIERS",'Company 28'!$B:$E,4,0),"") -> 0 | AG22: =IFERROR(VLOOKUP("M7_BARRIERS",'Company 29'!$B:$E,4,0),"") -> 0 | AH22: =IFERROR(VLOOKUP("M7_BARRIERS",'Company 30'!$B:$E,4,0),"") -> 0
B23: Maturity | C23: M8_IMPACT | D23: Operational impact | E23: =IFERROR(VLOOKUP("M8_IMPACT",'Company 1'!$B:$E,4,0),"") -> 0 | F23: =IFERROR(VLOOKUP("M8_IMPACT",'Company 2'!$B:$E,4,0),"") -> 0 | G23: =IFERROR(VLOOKUP("M8_IMPACT",'Company 3'!$B:$E,4,0),"") -> 3 | H23: =IFERROR(VLOOKUP("M8_IMPACT",'Company 4'!$B:$E,4,0),"") -> 0 | I23: =IFERROR(VLOOKUP("M8_IMPACT",'Company 5'!$B:$E,4,0),"") -> 2 | J23: =IFERROR(VLOOKUP("M8_IMPACT",'Company 6'!$B:$E,4,0),"") -> 5 | K23: =IFERROR(VLOOKUP("M8_IMPACT",'Company 7'!$B:$E,4,0),"") -> 3 | L23: =IFERROR(VLOOKUP("M8_IMPACT",'Company 8'!$B:$E,4,0),"") -> 2 | M23: =IFERROR(VLOOKUP("M8_IMPACT",'Company 9'!$B:$E,4,0),"") -> 4 | N23: =IFERROR(VLOOKUP("M8_IMPACT",'Company 10'!$B:$E,4,0),"") -> 4 | O23: =IFERROR(VLOOKUP("M8_IMPACT",'Company 11'!$B:$E,4,0),"") -> 0 | P23: =IFERROR(VLOOKUP("M8_IMPACT",'Company 12'!$B:$E,4,0),"") -> 4 | Q23: =IFERROR(VLOOKUP("M8_IMPACT",'Company 13'!$B:$E,4,0),"") -> 3 | R23: =IFERROR(VLOOKUP("M8_IMPACT",#REF!,4,0),"") | S23: =IFERROR(VLOOKUP("M8_IMPACT",#REF!,4,0),"") | T23: =IFERROR(VLOOKUP("M8_IMPACT",#REF!,4,0),"") | U23: =IFERROR(VLOOKUP("M8_IMPACT",#REF!,4,0),"") | V23: =IFERROR(VLOOKUP("M8_IMPACT",'Company 18'!$B:$E,4,0),"") -> 0 | W23: =IFERROR(VLOOKUP("M8_IMPACT",'Company 19'!$B:$E,4,0),"") -> 0 | X23: =IFERROR(VLOOKUP("M8_IMPACT",'Company 20'!$B:$E,4,0),"") -> 0 | Y23: =IFERROR(VLOOKUP("M8_IMPACT",'Company 21'!$B:$E,4,0),"") -> 0 | Z23: =IFERROR(VLOOKUP("M8_IMPACT",'Company 22'!$B:$E,4,0),"") -> 0 | AA23: =IFERROR(VLOOKUP("M8_IMPACT",'Company 23'!$B:$E,4,0),"") -> 0 | AB23: =IFERROR(VLOOKUP("M8_IMPACT",'Company 24'!$B:$E,4,0),"") -> 0 | AC23: =IFERROR(VLOOKUP("M8_IMPACT",'Company 25'!$B:$E,4,0),"") -> 0 | AD23: =IFERROR(VLOOKUP("M8_IMPACT",'Company 26'!$B:$E,4,0),"") -> 0 | AE23: =IFERROR(VLOOKUP("M8_IMPACT",'Company 27'!$B:$E,4,0),"") -> 0 | AF23: =IFERROR(VLOOKUP("M8_IMPACT",'Company 28'!$B:$E,4,0),"") -> 0 | AG23: =IFERROR(VLOOKUP("M8_IMPACT",'Company 29'!$B:$E,4,0),"") -> 0 | AH23: =IFERROR(VLOOKUP("M8_IMPACT",'Company 30'!$B:$E,4,0),"") -> 0
B24: Maturity | C24: M9_WILLINGNESS | D24: Willingness (synthesis) | E24: =IFERROR(VLOOKUP("M9_WILLINGNESS",'Company 1'!$B:$E,4,0),"") -> 6 | F24: =IFERROR(VLOOKUP("M9_WILLINGNESS",'Company 2'!$B:$E,4,0),"") -> 2 | G24: =IFERROR(VLOOKUP("M9_WILLINGNESS",'Company 3'!$B:$E,4,0),"") -> 8 | H24: =IFERROR(VLOOKUP("M9_WILLINGNESS",'Company 4'!$B:$E,4,0),"") -> 8 | I24: =IFERROR(VLOOKUP("M9_WILLINGNESS",'Company 5'!$B:$E,4,0),"") -> 10 | J24: =IFERROR(VLOOKUP("M9_WILLINGNESS",'Company 6'!$B:$E,4,0),"") -> 6 | K24: =IFERROR(VLOOKUP("M9_WILLINGNESS",'Company 7'!$B:$E,4,0),"") -> 8 | L24: =IFERROR(VLOOKUP("M9_WILLINGNESS",'Company 8'!$B:$E,4,0),"") -> 8 | M24: =IFERROR(VLOOKUP("M9_WILLINGNESS",'Company 9'!$B:$E,4,0),"") -> 6 | N24: =IFERROR(VLOOKUP("M9_WILLINGNESS",'Company 10'!$B:$E,4,0),"") -> 7 | O24: =IFERROR(VLOOKUP("M9_WILLINGNESS",'Company 11'!$B:$E,4,0),"") -> 9 | P24: =IFERROR(VLOOKUP("M9_WILLINGNESS",'Company 12'!$B:$E,4,0),"") -> 3 | Q24: =IFERROR(VLOOKUP("M9_WILLINGNESS",'Company 13'!$B:$E,4,0),"") -> 9 | R24: =IFERROR(VLOOKUP("M9_WILLINGNESS",#REF!,4,0),"") | S24: =IFERROR(VLOOKUP("M9_WILLINGNESS",#REF!,4,0),"") | T24: =IFERROR(VLOOKUP("M9_WILLINGNESS",#REF!,4,0),"") | U24: =IFERROR(VLOOKUP("M9_WILLINGNESS",#REF!,4,0),"") | V24: =IFERROR(VLOOKUP("M9_WILLINGNESS",'Company 18'!$B:$E,4,0),"") -> 0 | W24: =IFERROR(VLOOKUP("M9_WILLINGNESS",'Company 19'!$B:$E,4,0),"") -> 0 | X24: =IFERROR(VLOOKUP("M9_WILLINGNESS",'Company 20'!$B:$E,4,0),"") -> 0 | Y24: =IFERROR(VLOOKUP("M9_WILLINGNESS",'Company 21'!$B:$E,4,0),"") -> 0 | Z24: =IFERROR(VLOOKUP("M9_WILLINGNESS",'Company 22'!$B:$E,4,0),"") -> 0 | AA24: =IFERROR(VLOOKUP("M9_WILLINGNESS",'Company 23'!$B:$E,4,0),"") -> 0 | AB24: =IFERROR(VLOOKUP("M9_WILLINGNESS",'Company 24'!$B:$E,4,0),"") -> 0 | AC24: =IFERROR(VLOOKUP("M9_WILLINGNESS",'Company 25'!$B:$E,4,0),"") -> 0 | AD24: =IFERROR(VLOOKUP("M9_WILLINGNESS",'Company 26'!$B:$E,4,0),"") -> 0 | AE24: =IFERROR(VLOOKUP("M9_WILLINGNESS",'Company 27'!$B:$E,4,0),"") -> 0 | AF24: =IFERROR(VLOOKUP("M9_WILLINGNESS",'Company 28'!$B:$E,4,0),"") -> 0 | AG24: =IFERROR(VLOOKUP("M9_WILLINGNESS",'Company 29'!$B:$E,4,0),"") -> 0 | AH24: =IFERROR(VLOOKUP("M9_WILLINGNESS",'Company 30'!$B:$E,4,0),"") -> 0
B25: ── VALUE UNLOCK ──
B26: Value Unlock | C26: SV1_PRICING | D26: Pricing | E26: =IFERROR(VLOOKUP("SV1_PRICING",'Company 1'!$B:$E,4,0),"") -> 0 | F26: =IFERROR(VLOOKUP("SV1_PRICING",'Company 2'!$B:$E,4,0),"") -> 0 | G26: =IFERROR(VLOOKUP("SV1_PRICING",'Company 3'!$B:$E,4,0),"") -> 1 | H26: =IFERROR(VLOOKUP("SV1_PRICING",'Company 4'!$B:$E,4,0),"") -> 1 | I26: =IFERROR(VLOOKUP("SV1_PRICING",'Company 5'!$B:$E,4,0),"") -> 1 | J26: =IFERROR(VLOOKUP("SV1_PRICING",'Company 6'!$B:$E,4,0),"") -> 1 | K26: =IFERROR(VLOOKUP("SV1_PRICING",'Company 7'!$B:$E,4,0),"") -> 0 | L26: =IFERROR(VLOOKUP("SV1_PRICING",'Company 8'!$B:$E,4,0),"") -> 1 | M26: =IFERROR(VLOOKUP("SV1_PRICING",'Company 9'!$B:$E,4,0),"") -> 0 | N26: =IFERROR(VLOOKUP("SV1_PRICING",'Company 10'!$B:$E,4,0),"") -> 1 | O26: =IFERROR(VLOOKUP("SV1_PRICING",'Company 11'!$B:$E,4,0),"") -> 1 | P26: =IFERROR(VLOOKUP("SV1_PRICING",'Company 12'!$B:$E,4,0),"") -> 0 | Q26: =IFERROR(VLOOKUP("SV1_PRICING",'Company 13'!$B:$E,4,0),"") -> 0 | R26: =IFERROR(VLOOKUP("SV1_PRICING",#REF!,4,0),"") | S26: =IFERROR(VLOOKUP("SV1_PRICING",#REF!,4,0),"") | T26: =IFERROR(VLOOKUP("SV1_PRICING",#REF!,4,0),"") | U26: =IFERROR(VLOOKUP("SV1_PRICING",#REF!,4,0),"") | V26: =IFERROR(VLOOKUP("SV1_PRICING",'Company 18'!$B:$E,4,0),"") -> 0 | W26: =IFERROR(VLOOKUP("SV1_PRICING",'Company 19'!$B:$E,4,0),"") -> 0 | X26: =IFERROR(VLOOKUP("SV1_PRICING",'Company 20'!$B:$E,4,0),"") -> 0 | Y26: =IFERROR(VLOOKUP("SV1_PRICING",'Company 21'!$B:$E,4,0),"") -> 0 | Z26: =IFERROR(VLOOKUP("SV1_PRICING",'Company 22'!$B:$E,4,0),"") -> 0 | AA26: =IFERROR(VLOOKUP("SV1_PRICING",'Company 23'!$B:$E,4,0),"") -> 0 | AB26: =IFERROR(VLOOKUP("SV1_PRICING",'Company 24'!$B:$E,4,0),"") -> 0 | AC26: =IFERROR(VLOOKUP("SV1_PRICING",'Company 25'!$B:$E,4,0),"") -> 0 | AD26: =IFERROR(VLOOKUP("SV1_PRICING",'Company 26'!$B:$E,4,0),"") -> 0 | AE26: =IFERROR(VLOOKUP("SV1_PRICING",'Company 27'!$B:$E,4,0),"") -> 0 | AF26: =IFERROR(VLOOKUP("SV1_PRICING",'Company 28'!$B:$E,4,0),"") -> 0 | AG26: =IFERROR(VLOOKUP("SV1_PRICING",'Company 29'!$B:$E,4,0),"") -> 0 | AH26: =IFERROR(VLOOKUP("SV1_PRICING",'Company 30'!$B:$E,4,0),"") -> 0
B27: Value Unlock | C27: SV2_PROMOTIONS | D27: Promotions | E27: =IFERROR(VLOOKUP("SV2_PROMOTIONS",'Company 1'!$B:$E,4,0),"") -> 0 | F27: =IFERROR(VLOOKUP("SV2_PROMOTIONS",'Company 2'!$B:$E,4,0),"") -> 0 | G27: =IFERROR(VLOOKUP("SV2_PROMOTIONS",'Company 3'!$B:$E,4,0),"") -> 1 | H27: =IFERROR(VLOOKUP("SV2_PROMOTIONS",'Company 4'!$B:$E,4,0),"") -> 1 | I27: =IFERROR(VLOOKUP("SV2_PROMOTIONS",'Company 5'!$B:$E,4,0),"") -> 1 | J27: =IFERROR(VLOOKUP("SV2_PROMOTIONS",'Company 6'!$B:$E,4,0),"") -> 1 | K27: =IFERROR(VLOOKUP("SV2_PROMOTIONS",'Company 7'!$B:$E,4,0),"") -> 0 | L27: =IFERROR(VLOOKUP("SV2_PROMOTIONS",'Company 8'!$B:$E,4,0),"") -> 1 | M27: =IFERROR(VLOOKUP("SV2_PROMOTIONS",'Company 9'!$B:$E,4,0),"") -> 0 | N27: =IFERROR(VLOOKUP("SV2_PROMOTIONS",'Company 10'!$B:$E,4,0),"") -> 0 | O27: =IFERROR(VLOOKUP("SV2_PROMOTIONS",'Company 11'!$B:$E,4,0),"") -> 1 | P27: =IFERROR(VLOOKUP("SV2_PROMOTIONS",'Company 12'!$B:$E,4,0),"") -> 1 | Q27: =IFERROR(VLOOKUP("SV2_PROMOTIONS",'Company 13'!$B:$E,4,0),"") -> 1 | R27: =IFERROR(VLOOKUP("SV2_PROMOTIONS",#REF!,4,0),"") | S27: =IFERROR(VLOOKUP("SV2_PROMOTIONS",#REF!,4,0),"") | T27: =IFERROR(VLOOKUP("SV2_PROMOTIONS",#REF!,4,0),"") | U27: =IFERROR(VLOOKUP("SV2_PROMOTIONS",#REF!,4,0),"") | V27: =IFERROR(VLOOKUP("SV2_PROMOTIONS",'Company 18'!$B:$E,4,0),"") -> 0 | W27: =IFERROR(VLOOKUP("SV2_PROMOTIONS",'Company 19'!$B:$E,4,0),"") -> 0 | X27: =IFERROR(VLOOKUP("SV2_PROMOTIONS",'Company 20'!$B:$E,4,0),"") -> 0 | Y27: =IFERROR(VLOOKUP("SV2_PROMOTIONS",'Company 21'!$B:$E,4,0),"") -> 0 | Z27: =IFERROR(VLOOKUP("SV2_PROMOTIONS",'Company 22'!$B:$E,4,0),"") -> 0 | AA27: =IFERROR(VLOOKUP("SV2_PROMOTIONS",'Company 23'!$B:$E,4,0),"") -> 0 | AB27: =IFERROR(VLOOKUP("SV2_PROMOTIONS",'Company 24'!$B:$E,4,0),"") -> 0 | AC27: =IFERROR(VLOOKUP("SV2_PROMOTIONS",'Company 25'!$B:$E,4,0),"") -> 0 | AD27: =IFERROR(VLOOKUP("SV2_PROMOTIONS",'Company 26'!$B:$E,4,0),"") -> 0 | AE27: =IFERROR(VLOOKUP("SV2_PROMOTIONS",'Company 27'!$B:$E,4,0),"") -> 0 | AF27: =IFERROR(VLOOKUP("SV2_PROMOTIONS",'Company 28'!$B:$E,4,0),"") -> 0 | AG27: =IFERROR(VLOOKUP("SV2_PROMOTIONS",'Company 29'!$B:$E,4,0),"") -> 0 | AH27: =IFERROR(VLOOKUP("SV2_PROMOTIONS",'Company 30'!$B:$E,4,0),"") -> 0
B28: Value Unlock | C28: SV3_SUPPLYCHAIN | D28: Supply Chain | E28: =IFERROR(VLOOKUP("SV3_SUPPLYCHAIN",'Company 1'!$B:$E,4,0),"") -> 0 | F28: =IFERROR(VLOOKUP("SV3_SUPPLYCHAIN",'Company 2'!$B:$E,4,0),"") -> 1 | G28: =IFERROR(VLOOKUP("SV3_SUPPLYCHAIN",'Company 3'!$B:$E,4,0),"") -> 0 | H28: =IFERROR(VLOOKUP("SV3_SUPPLYCHAIN",'Company 4'!$B:$E,4,0),"") -> 1 | I28: =IFERROR(VLOOKUP("SV3_SUPPLYCHAIN",'Company 5'!$B:$E,4,0),"") -> 1 | J28: =IFERROR(VLOOKUP("SV3_SUPPLYCHAIN",'Company 6'!$B:$E,4,0),"") -> 1 | K28: =IFERROR(VLOOKUP("SV3_SUPPLYCHAIN",'Company 7'!$B:$E,4,0),"") -> 0 | L28: =IFERROR(VLOOKUP("SV3_SUPPLYCHAIN",'Company 8'!$B:$E,4,0),"") -> 0 | M28: =IFERROR(VLOOKUP("SV3_SUPPLYCHAIN",'Company 9'!$B:$E,4,0),"") -> 0 | N28: =IFERROR(VLOOKUP("SV3_SUPPLYCHAIN",'Company 10'!$B:$E,4,0),"") -> 1 | O28: =IFERROR(VLOOKUP("SV3_SUPPLYCHAIN",'Company 11'!$B:$E,4,0),"") -> 1 | P28: =IFERROR(VLOOKUP("SV3_SUPPLYCHAIN",'Company 12'!$B:$E,4,0),"") -> 1 | Q28: =IFERROR(VLOOKUP("SV3_SUPPLYCHAIN",'Company 13'!$B:$E,4,0),"") -> 1 | R28: =IFERROR(VLOOKUP("SV3_SUPPLYCHAIN",#REF!,4,0),"") | S28: =IFERROR(VLOOKUP("SV3_SUPPLYCHAIN",#REF!,4,0),"") | T28: =IFERROR(VLOOKUP("SV3_SUPPLYCHAIN",#REF!,4,0),"") | U28: =IFERROR(VLOOKUP("SV3_SUPPLYCHAIN",#REF!,4,0),"") | V28: =IFERROR(VLOOKUP("SV3_SUPPLYCHAIN",'Company 18'!$B:$E,4,0),"") -> 0 | W28: =IFERROR(VLOOKUP("SV3_SUPPLYCHAIN",'Company 19'!$B:$E,4,0),"") -> 0 | X28: =IFERROR(VLOOKUP("SV3_SUPPLYCHAIN",'Company 20'!$B:$E,4,0),"") -> 0 | Y28: =IFERROR(VLOOKUP("SV3_SUPPLYCHAIN",'Company 21'!$B:$E,4,0),"") -> 0 | Z28: =IFERROR(VLOOKUP("SV3_SUPPLYCHAIN",'Company 22'!$B:$E,4,0),"") -> 0 | AA28: =IFERROR(VLOOKUP("SV3_SUPPLYCHAIN",'Company 23'!$B:$E,4,0),"") -> 0 | AB28: =IFERROR(VLOOKUP("SV3_SUPPLYCHAIN",'Company 24'!$B:$E,4,0),"") -> 0 | AC28: =IFERROR(VLOOKUP("SV3_SUPPLYCHAIN",'Company 25'!$B:$E,4,0),"") -> 0 | AD28: =IFERROR(VLOOKUP("SV3_SUPPLYCHAIN",'Company 26'!$B:$E,4,0),"") -> 0 | AE28: =IFERROR(VLOOKUP("SV3_SUPPLYCHAIN",'Company 27'!$B:$E,4,0),"") -> 0 | AF28: =IFERROR(VLOOKUP("SV3_SUPPLYCHAIN",'Company 28'!$B:$E,4,0),"") -> 0 | AG28: =IFERROR(VLOOKUP("SV3_SUPPLYCHAIN",'Company 29'!$B:$E,4,0),"") -> 0 | AH28: =IFERROR(VLOOKUP("SV3_SUPPLYCHAIN",'Company 30'!$B:$E,4,0),"") -> 0
B29: Value Unlock | C29: SV4_CATEGORY | D29: Category Planning | E29: =IFERROR(VLOOKUP("SV4_CATEGORY",'Company 1'!$B:$E,4,0),"") -> 1 | F29: =IFERROR(VLOOKUP("SV4_CATEGORY",'Company 2'!$B:$E,4,0),"") -> 0 | G29: =IFERROR(VLOOKUP("SV4_CATEGORY",'Company 3'!$B:$E,4,0),"") -> 1 | H29: =IFERROR(VLOOKUP("SV4_CATEGORY",'Company 4'!$B:$E,4,0),"") -> 1 | I29: =IFERROR(VLOOKUP("SV4_CATEGORY",'Company 5'!$B:$E,4,0),"") -> 0 | J29: =IFERROR(VLOOKUP("SV4_CATEGORY",'Company 6'!$B:$E,4,0),"") -> 1 | K29: =IFERROR(VLOOKUP("SV4_CATEGORY",'Company 7'!$B:$E,4,0),"") -> 1 | L29: =IFERROR(VLOOKUP("SV4_CATEGORY",'Company 8'!$B:$E,4,0),"") -> 1 | M29: =IFERROR(VLOOKUP("SV4_CATEGORY",'Company 9'!$B:$E,4,0),"") -> 1 | N29: =IFERROR(VLOOKUP("SV4_CATEGORY",'Company 10'!$B:$E,4,0),"") -> 1 | O29: =IFERROR(VLOOKUP("SV4_CATEGORY",'Company 11'!$B:$E,4,0),"") -> 1 | P29: =IFERROR(VLOOKUP("SV4_CATEGORY",'Company 12'!$B:$E,4,0),"") -> 0 | Q29: =IFERROR(VLOOKUP("SV4_CATEGORY",'Company 13'!$B:$E,4,0),"") -> 1 | R29: =IFERROR(VLOOKUP("SV4_CATEGORY",#REF!,4,0),"") | S29: =IFERROR(VLOOKUP("SV4_CATEGORY",#REF!,4,0),"") | T29: =IFERROR(VLOOKUP("SV4_CATEGORY",#REF!,4,0),"") | U29: =IFERROR(VLOOKUP("SV4_CATEGORY",#REF!,4,0),"") | V29: =IFERROR(VLOOKUP("SV4_CATEGORY",'Company 18'!$B:$E,4,0),"") -> 0 | W29: =IFERROR(VLOOKUP("SV4_CATEGORY",'Company 19'!$B:$E,4,0),"") -> 0 | X29: =IFERROR(VLOOKUP("SV4_CATEGORY",'Company 20'!$B:$E,4,0),"") -> 0 | Y29: =IFERROR(VLOOKUP("SV4_CATEGORY",'Company 21'!$B:$E,4,0),"") -> 0 | Z29: =IFERROR(VLOOKUP("SV4_CATEGORY",'Company 22'!$B:$E,4,0),"") -> 0 | AA29: =IFERROR(VLOOKUP("SV4_CATEGORY",'Company 23'!$B:$E,4,0),"") -> 0 | AB29: =IFERROR(VLOOKUP("SV4_CATEGORY",'Company 24'!$B:$E,4,0),"") -> 0 | AC29: =IFERROR(VLOOKUP("SV4_CATEGORY",'Company 25'!$B:$E,4,0),"") -> 0 | AD29: =IFERROR(VLOOKUP("SV4_CATEGORY",'Company 26'!$B:$E,4,0),"") -> 0 | AE29: =IFERROR(VLOOKUP("SV4_CATEGORY",'Company 27'!$B:$E,4,0),"") -> 0 | AF29: =IFERROR(VLOOKUP("SV4_CATEGORY",'Company 28'!$B:$E,4,0),"") -> 0 | AG29: =IFERROR(VLOOKUP("SV4_CATEGORY",'Company 29'!$B:$E,4,0),"") -> 0 | AH29: =IFERROR(VLOOKUP("SV4_CATEGORY",'Company 30'!$B:$E,4,0),"") -> 0
B30: Value Unlock | C30: SV5_DEMAND | D30: Demand Forecasting | E30: =IFERROR(VLOOKUP("SV5_DEMAND",'Company 1'!$B:$E,4,0),"") -> 0 | F30: =IFERROR(VLOOKUP("SV5_DEMAND",'Company 2'!$B:$E,4,0),"") -> 0 | G30: =IFERROR(VLOOKUP("SV5_DEMAND",'Company 3'!$B:$E,4,0),"") -> 0 | H30: =IFERROR(VLOOKUP("SV5_DEMAND",'Company 4'!$B:$E,4,0),"") -> 0 | I30: =IFERROR(VLOOKUP("SV5_DEMAND",'Company 5'!$B:$E,4,0),"") -> 1 | J30: =IFERROR(VLOOKUP("SV5_DEMAND",'Company 6'!$B:$E,4,0),"") -> 1 | K30: =IFERROR(VLOOKUP("SV5_DEMAND",'Company 7'!$B:$E,4,0),"") -> 0 | L30: =IFERROR(VLOOKUP("SV5_DEMAND",'Company 8'!$B:$E,4,0),"") -> 0 | M30: =IFERROR(VLOOKUP("SV5_DEMAND",'Company 9'!$B:$E,4,0),"") -> 1 | N30: =IFERROR(VLOOKUP("SV5_DEMAND",'Company 10'!$B:$E,4,0),"") -> 0 | O30: =IFERROR(VLOOKUP("SV5_DEMAND",'Company 11'!$B:$E,4,0),"") -> 0 | P30: =IFERROR(VLOOKUP("SV5_DEMAND",'Company 12'!$B:$E,4,0),"") -> 1 | Q30: =IFERROR(VLOOKUP("SV5_DEMAND",'Company 13'!$B:$E,4,0),"") -> 0 | R30: =IFERROR(VLOOKUP("SV5_DEMAND",#REF!,4,0),"") | S30: =IFERROR(VLOOKUP("SV5_DEMAND",#REF!,4,0),"") | T30: =IFERROR(VLOOKUP("SV5_DEMAND",#REF!,4,0),"") | U30: =IFERROR(VLOOKUP("SV5_DEMAND",#REF!,4,0),"") | V30: =IFERROR(VLOOKUP("SV5_DEMAND",'Company 18'!$B:$E,4,0),"") -> 0 | W30: =IFERROR(VLOOKUP("SV5_DEMAND",'Company 19'!$B:$E,4,0),"") -> 0 | X30: =IFERROR(VLOOKUP("SV5_DEMAND",'Company 20'!$B:$E,4,0),"") -> 0 | Y30: =IFERROR(VLOOKUP("SV5_DEMAND",'Company 21'!$B:$E,4,0),"") -> 0 | Z30: =IFERROR(VLOOKUP("SV5_DEMAND",'Company 22'!$B:$E,4,0),"") -> 0 | AA30: =IFERROR(VLOOKUP("SV5_DEMAND",'Company 23'!$B:$E,4,0),"") -> 0 | AB30: =IFERROR(VLOOKUP("SV5_DEMAND",'Company 24'!$B:$E,4,0),"") -> 0 | AC30: =IFERROR(VLOOKUP("SV5_DEMAND",'Company 25'!$B:$E,4,0),"") -> 0 | AD30: =IFERROR(VLOOKUP("SV5_DEMAND",'Company 26'!$B:$E,4,0),"") -> 0 | AE30: =IFERROR(VLOOKUP("SV5_DEMAND",'Company 27'!$B:$E,4,0),"") -> 0 | AF30: =IFERROR(VLOOKUP("SV5_DEMAND",'Company 28'!$B:$E,4,0),"") -> 0 | AG30: =IFERROR(VLOOKUP("SV5_DEMAND",'Company 29'!$B:$E,4,0),"") -> 0 | AH30: =IFERROR(VLOOKUP("SV5_DEMAND",'Company 30'!$B:$E,4,0),"") -> 0
B31: Value Unlock | C31: SV6_ACCOUNT | D31: Accountability | E31: =IFERROR(VLOOKUP("SV6_ACCOUNT",'Company 1'!$B:$E,4,0),"") -> 0 | F31: =IFERROR(VLOOKUP("SV6_ACCOUNT",'Company 2'!$B:$E,4,0),"") -> 0 | G31: =IFERROR(VLOOKUP("SV6_ACCOUNT",'Company 3'!$B:$E,4,0),"") -> 0 | H31: =IFERROR(VLOOKUP("SV6_ACCOUNT",'Company 4'!$B:$E,4,0),"") -> 1 | I31: =IFERROR(VLOOKUP("SV6_ACCOUNT",'Company 5'!$B:$E,4,0),"") -> 1 | J31: =IFERROR(VLOOKUP("SV6_ACCOUNT",'Company 6'!$B:$E,4,0),"") -> 1 | K31: =IFERROR(VLOOKUP("SV6_ACCOUNT",'Company 7'!$B:$E,4,0),"") -> 0 | L31: =IFERROR(VLOOKUP("SV6_ACCOUNT",'Company 8'!$B:$E,4,0),"") -> 0 | M31: =IFERROR(VLOOKUP("SV6_ACCOUNT",'Company 9'!$B:$E,4,0),"") -> 0 | N31: =IFERROR(VLOOKUP("SV6_ACCOUNT",'Company 10'!$B:$E,4,0),"") -> 0 | O31: =IFERROR(VLOOKUP("SV6_ACCOUNT",'Company 11'!$B:$E,4,0),"") -> 0 | P31: =IFERROR(VLOOKUP("SV6_ACCOUNT",'Company 12'!$B:$E,4,0),"") -> 0 | Q31: =IFERROR(VLOOKUP("SV6_ACCOUNT",'Company 13'!$B:$E,4,0),"") -> 0 | R31: =IFERROR(VLOOKUP("SV6_ACCOUNT",#REF!,4,0),"") | S31: =IFERROR(VLOOKUP("SV6_ACCOUNT",#REF!,4,0),"") | T31: =IFERROR(VLOOKUP("SV6_ACCOUNT",#REF!,4,0),"") | U31: =IFERROR(VLOOKUP("SV6_ACCOUNT",#REF!,4,0),"") | V31: =IFERROR(VLOOKUP("SV6_ACCOUNT",'Company 18'!$B:$E,4,0),"") -> 0 | W31: =IFERROR(VLOOKUP("SV6_ACCOUNT",'Company 19'!$B:$E,4,0),"") -> 0 | X31: =IFERROR(VLOOKUP("SV6_ACCOUNT",'Company 20'!$B:$E,4,0),"") -> 0 | Y31: =IFERROR(VLOOKUP("SV6_ACCOUNT",'Company 21'!$B:$E,4,0),"") -> 0 | Z31: =IFERROR(VLOOKUP("SV6_ACCOUNT",'Company 22'!$B:$E,4,0),"") -> 0 | AA31: =IFERROR(VLOOKUP("SV6_ACCOUNT",'Company 23'!$B:$E,4,0),"") -> 0 | AB31: =IFERROR(VLOOKUP("SV6_ACCOUNT",'Company 24'!$B:$E,4,0),"") -> 0 | AC31: =IFERROR(VLOOKUP("SV6_ACCOUNT",'Company 25'!$B:$E,4,0),"") -> 0 | AD31: =IFERROR(VLOOKUP("SV6_ACCOUNT",'Company 26'!$B:$E,4,0),"") -> 0 | AE31: =IFERROR(VLOOKUP("SV6_ACCOUNT",'Company 27'!$B:$E,4,0),"") -> 0 | AF31: =IFERROR(VLOOKUP("SV6_ACCOUNT",'Company 28'!$B:$E,4,0),"") -> 0 | AG31: =IFERROR(VLOOKUP("SV6_ACCOUNT",'Company 29'!$B:$E,4,0),"") -> 0 | AH31: =IFERROR(VLOOKUP("SV6_ACCOUNT",'Company 30'!$B:$E,4,0),"") -> 0
B32: Value Unlock | C32: SV7_OPS | D32: Operationalization | E32: =IFERROR(VLOOKUP("SV7_OPS",'Company 1'!$B:$E,4,0),"") -> 0 | F32: =IFERROR(VLOOKUP("SV7_OPS",'Company 2'!$B:$E,4,0),"") -> 0 | G32: =IFERROR(VLOOKUP("SV7_OPS",'Company 3'!$B:$E,4,0),"") -> 0 | H32: =IFERROR(VLOOKUP("SV7_OPS",'Company 4'!$B:$E,4,0),"") -> 1 | I32: =IFERROR(VLOOKUP("SV7_OPS",'Company 5'!$B:$E,4,0),"") -> 1 | J32: =IFERROR(VLOOKUP("SV7_OPS",'Company 6'!$B:$E,4,0),"") -> 1 | K32: =IFERROR(VLOOKUP("SV7_OPS",'Company 7'!$B:$E,4,0),"") -> 1 | L32: =IFERROR(VLOOKUP("SV7_OPS",'Company 8'!$B:$E,4,0),"") -> 0 | M32: =IFERROR(VLOOKUP("SV7_OPS",'Company 9'!$B:$E,4,0),"") -> 0 | N32: =IFERROR(VLOOKUP("SV7_OPS",'Company 10'!$B:$E,4,0),"") -> 0 | O32: =IFERROR(VLOOKUP("SV7_OPS",'Company 11'!$B:$E,4,0),"") -> 0 | P32: =IFERROR(VLOOKUP("SV7_OPS",'Company 12'!$B:$E,4,0),"") -> 0 | Q32: =IFERROR(VLOOKUP("SV7_OPS",'Company 13'!$B:$E,4,0),"") -> 1 | R32: =IFERROR(VLOOKUP("SV7_OPS",#REF!,4,0),"") | S32: =IFERROR(VLOOKUP("SV7_OPS",#REF!,4,0),"") | T32: =IFERROR(VLOOKUP("SV7_OPS",#REF!,4,0),"") | U32: =IFERROR(VLOOKUP("SV7_OPS",#REF!,4,0),"") | V32: =IFERROR(VLOOKUP("SV7_OPS",'Company 18'!$B:$E,4,0),"") -> 0 | W32: =IFERROR(VLOOKUP("SV7_OPS",'Company 19'!$B:$E,4,0),"") -> 0 | X32: =IFERROR(VLOOKUP("SV7_OPS",'Company 20'!$B:$E,4,0),"") -> 0 | Y32: =IFERROR(VLOOKUP("SV7_OPS",'Company 21'!$B:$E,4,0),"") -> 0 | Z32: =IFERROR(VLOOKUP("SV7_OPS",'Company 22'!$B:$E,4,0),"") -> 0 | AA32: =IFERROR(VLOOKUP("SV7_OPS",'Company 23'!$B:$E,4,0),"") -> 0 | AB32: =IFERROR(VLOOKUP("SV7_OPS",'Company 24'!$B:$E,4,0),"") -> 0 | AC32: =IFERROR(VLOOKUP("SV7_OPS",'Company 25'!$B:$E,4,0),"") -> 0 | AD32: =IFERROR(VLOOKUP("SV7_OPS",'Company 26'!$B:$E,4,0),"") -> 0 | AE32: =IFERROR(VLOOKUP("SV7_OPS",'Company 27'!$B:$E,4,0),"") -> 0 | AF32: =IFERROR(VLOOKUP("SV7_OPS",'Company 28'!$B:$E,4,0),"") -> 0 | AG32: =IFERROR(VLOOKUP("SV7_OPS",'Company 29'!$B:$E,4,0),"") -> 0 | AH32: =IFERROR(VLOOKUP("SV7_OPS",'Company 30'!$B:$E,4,0),"") -> 0
B33: ── CONCERNS ──
B34: Concerns | C34: SC1_DATASENS | D34: Data Sensitivity | E34: =IFERROR(VLOOKUP("SC1_DATASENS",'Company 1'!$B:$E,4,0),"") -> 1 | F34: =IFERROR(VLOOKUP("SC1_DATASENS",'Company 2'!$B:$E,4,0),"") -> 1 | G34: =IFERROR(VLOOKUP("SC1_DATASENS",'Company 3'!$B:$E,4,0),"") -> 1 | H34: =IFERROR(VLOOKUP("SC1_DATASENS",'Company 4'!$B:$E,4,0),"") -> 1 | I34: =IFERROR(VLOOKUP("SC1_DATASENS",'Company 5'!$B:$E,4,0),"") -> 1 | J34: =IFERROR(VLOOKUP("SC1_DATASENS",'Company 6'!$B:$E,4,0),"") -> 1 | K34: =IFERROR(VLOOKUP("SC1_DATASENS",'Company 7'!$B:$E,4,0),"") -> 0 | L34: =IFERROR(VLOOKUP("SC1_DATASENS",'Company 8'!$B:$E,4,0),"") -> 1 | M34: =IFERROR(VLOOKUP("SC1_DATASENS",'Company 9'!$B:$E,4,0),"") -> 1 | N34: =IFERROR(VLOOKUP("SC1_DATASENS",'Company 10'!$B:$E,4,0),"") -> 1 | O34: =IFERROR(VLOOKUP("SC1_DATASENS",'Company 11'!$B:$E,4,0),"") -> 1 | P34: =IFERROR(VLOOKUP("SC1_DATASENS",'Company 12'!$B:$E,4,0),"") -> 1 | Q34: =IFERROR(VLOOKUP("SC1_DATASENS",'Company 13'!$B:$E,4,0),"") -> 1 | R34: =IFERROR(VLOOKUP("SC1_DATASENS",#REF!,4,0),"") | S34: =IFERROR(VLOOKUP("SC1_DATASENS",#REF!,4,0),"") | T34: =IFERROR(VLOOKUP("SC1_DATASENS",#REF!,4,0),"") | U34: =IFERROR(VLOOKUP("SC1_DATASENS",#REF!,4,0),"") | V34: =IFERROR(VLOOKUP("SC1_DATASENS",'Company 18'!$B:$E,4,0),"") -> 0 | W34: =IFERROR(VLOOKUP("SC1_DATASENS",'Company 19'!$B:$E,4,0),"") -> 0 | X34: =IFERROR(VLOOKUP("SC1_DATASENS",'Company 20'!$B:$E,4,0),"") -> 0 | Y34: =IFERROR(VLOOKUP("SC1_DATASENS",'Company 21'!$B:$E,4,0),"") -> 0 | Z34: =IFERROR(VLOOKUP("SC1_DATASENS",'Company 22'!$B:$E,4,0),"") -> 0 | AA34: =IFERROR(VLOOKUP("SC1_DATASENS",'Company 23'!$B:$E,4,0),"") -> 0 | AB34: =IFERROR(VLOOKUP("SC1_DATASENS",'Company 24'!$B:$E,4,0),"") -> 0 | AC34: =IFERROR(VLOOKUP("SC1_DATASENS",'Company 25'!$B:$E,4,0),"") -> 0 | AD34: =IFERROR(VLOOKUP("SC1_DATASENS",'Company 26'!$B:$E,4,0),"") -> 0 | AE34: =IFERROR(VLOOKUP("SC1_DATASENS",'Company 27'!$B:$E,4,0),"") -> 0 | AF34: =IFERROR(VLOOKUP("SC1_DATASENS",'Company 28'!$B:$E,4,0),"") -> 0 | AG34: =IFERROR(VLOOKUP("SC1_DATASENS",'Company 29'!$B:$E,4,0),"") -> 0 | AH34: =IFERROR(VLOOKUP("SC1_DATASENS",'Company 30'!$B:$E,4,0),"") -> 0
B35: Concerns | C35: SC2_COMPLIANCE | D35: Compliance | E35: =IFERROR(VLOOKUP("SC2_COMPLIANCE",'Company 1'!$B:$E,4,0),"") -> 0 | F35: =IFERROR(VLOOKUP("SC2_COMPLIANCE",'Company 2'!$B:$E,4,0),"") -> 1 | G35: =IFERROR(VLOOKUP("SC2_COMPLIANCE",'Company 3'!$B:$E,4,0),"") -> 1 | H35: =IFERROR(VLOOKUP("SC2_COMPLIANCE",'Company 4'!$B:$E,4,0),"") -> 1 | I35: =IFERROR(VLOOKUP("SC2_COMPLIANCE",'Company 5'!$B:$E,4,0),"") -> 0 | J35: =IFERROR(VLOOKUP("SC2_COMPLIANCE",'Company 6'!$B:$E,4,0),"") -> 1 | K35: =IFERROR(VLOOKUP("SC2_COMPLIANCE",'Company 7'!$B:$E,4,0),"") -> 0 | L35: =IFERROR(VLOOKUP("SC2_COMPLIANCE",'Company 8'!$B:$E,4,0),"") -> 1 | M35: =IFERROR(VLOOKUP("SC2_COMPLIANCE",'Company 9'!$B:$E,4,0),"") -> 0 | N35: =IFERROR(VLOOKUP("SC2_COMPLIANCE",'Company 10'!$B:$E,4,0),"") -> 1 | O35: =IFERROR(VLOOKUP("SC2_COMPLIANCE",'Company 11'!$B:$E,4,0),"") -> 0 | P35: =IFERROR(VLOOKUP("SC2_COMPLIANCE",'Company 12'!$B:$E,4,0),"") -> 1 | Q35: =IFERROR(VLOOKUP("SC2_COMPLIANCE",'Company 13'!$B:$E,4,0),"") -> 1 | R35: =IFERROR(VLOOKUP("SC2_COMPLIANCE",#REF!,4,0),"") | S35: =IFERROR(VLOOKUP("SC2_COMPLIANCE",#REF!,4,0),"") | T35: =IFERROR(VLOOKUP("SC2_COMPLIANCE",#REF!,4,0),"") | U35: =IFERROR(VLOOKUP("SC2_COMPLIANCE",#REF!,4,0),"") | V35: =IFERROR(VLOOKUP("SC2_COMPLIANCE",'Company 18'!$B:$E,4,0),"") -> 0 | W35: =IFERROR(VLOOKUP("SC2_COMPLIANCE",'Company 19'!$B:$E,4,0),"") -> 0 | X35: =IFERROR(VLOOKUP("SC2_COMPLIANCE",'Company 20'!$B:$E,4,0),"") -> 0 | Y35: =IFERROR(VLOOKUP("SC2_COMPLIANCE",'Company 21'!$B:$E,4,0),"") -> 0 | Z35: =IFERROR(VLOOKUP("SC2_COMPLIANCE",'Company 22'!$B:$E,4,0),"") -> 0 | AA35: =IFERROR(VLOOKUP("SC2_COMPLIANCE",'Company 23'!$B:$E,4,0),"") -> 0 | AB35: =IFERROR(VLOOKUP("SC2_COMPLIANCE",'Company 24'!$B:$E,4,0),"") -> 0 | AC35: =IFERROR(VLOOKUP("SC2_COMPLIANCE",'Company 25'!$B:$E,4,0),"") -> 0 | AD35: =IFERROR(VLOOKUP("SC2_COMPLIANCE",'Company 26'!$B:$E,4,0),"") -> 0 | AE35: =IFERROR(VLOOKUP("SC2_COMPLIANCE",'Company 27'!$B:$E,4,0),"") -> 0 | AF35: =IFERROR(VLOOKUP("SC2_COMPLIANCE",'Company 28'!$B:$E,4,0),"") -> 0 | AG35: =IFERROR(VLOOKUP("SC2_COMPLIANCE",'Company 29'!$B:$E,4,0),"") -> 0 | AH35: =IFERROR(VLOOKUP("SC2_COMPLIANCE",'Company 30'!$B:$E,4,0),"") -> 0
B36: Concerns | C36: SC3_TRUST | D36: Trust Issues | E36: =IFERROR(VLOOKUP("SC3_TRUST",'Company 1'!$B:$E,4,0),"") -> 0 | F36: =IFERROR(VLOOKUP("SC3_TRUST",'Company 2'!$B:$E,4,0),"") -> 0 | G36: =IFERROR(VLOOKUP("SC3_TRUST",'Company 3'!$B:$E,4,0),"") -> 1 | H36: =IFERROR(VLOOKUP("SC3_TRUST",'Company 4'!$B:$E,4,0),"") -> 1 | I36: =IFERROR(VLOOKUP("SC3_TRUST",'Company 5'!$B:$E,4,0),"") -> 1 | J36: =IFERROR(VLOOKUP("SC3_TRUST",'Company 6'!$B:$E,4,0),"") -> 1 | K36: =IFERROR(VLOOKUP("SC3_TRUST",'Company 7'!$B:$E,4,0),"") -> 0 | L36: =IFERROR(VLOOKUP("SC3_TRUST",'Company 8'!$B:$E,4,0),"") -> 0 | M36: =IFERROR(VLOOKUP("SC3_TRUST",'Company 9'!$B:$E,4,0),"") -> 0 | N36: =IFERROR(VLOOKUP("SC3_TRUST",'Company 10'!$B:$E,4,0),"") -> 0 | O36: =IFERROR(VLOOKUP("SC3_TRUST",'Company 11'!$B:$E,4,0),"") -> 0 | P36: =IFERROR(VLOOKUP("SC3_TRUST",'Company 12'!$B:$E,4,0),"") -> 0 | Q36: =IFERROR(VLOOKUP("SC3_TRUST",'Company 13'!$B:$E,4,0),"") -> 1 | R36: =IFERROR(VLOOKUP("SC3_TRUST",#REF!,4,0),"") | S36: =IFERROR(VLOOKUP("SC3_TRUST",#REF!,4,0),"") | T36: =IFERROR(VLOOKUP("SC3_TRUST",#REF!,4,0),"") | U36: =IFERROR(VLOOKUP("SC3_TRUST",#REF!,4,0),"") | V36: =IFERROR(VLOOKUP("SC3_TRUST",'Company 18'!$B:$E,4,0),"") -> 0 | W36: =IFERROR(VLOOKUP("SC3_TRUST",'Company 19'!$B:$E,4,0),"") -> 0 | X36: =IFERROR(VLOOKUP("SC3_TRUST",'Company 20'!$B:$E,4,0),"") -> 0 | Y36: =IFERROR(VLOOKUP("SC3_TRUST",'Company 21'!$B:$E,4,0),"") -> 0 | Z36: =IFERROR(VLOOKUP("SC3_TRUST",'Company 22'!$B:$E,4,0),"") -> 0 | AA36: =IFERROR(VLOOKUP("SC3_TRUST",'Company 23'!$B:$E,4,0),"") -> 0 | AB36: =IFERROR(VLOOKUP("SC3_TRUST",'Company 24'!$B:$E,4,0),"") -> 0 | AC36: =IFERROR(VLOOKUP("SC3_TRUST",'Company 25'!$B:$E,4,0),"") -> 0 | AD36: =IFERROR(VLOOKUP("SC3_TRUST",'Company 26'!$B:$E,4,0),"") -> 0 | AE36: =IFERROR(VLOOKUP("SC3_TRUST",'Company 27'!$B:$E,4,0),"") -> 0 | AF36: =IFERROR(VLOOKUP("SC3_TRUST",'Company 28'!$B:$E,4,0),"") -> 0 | AG36: =IFERROR(VLOOKUP("SC3_TRUST",'Company 29'!$B:$E,4,0),"") -> 0 | AH36: =IFERROR(VLOOKUP("SC3_TRUST",'Company 30'!$B:$E,4,0),"") -> 0
B37: Concerns | C37: SC4_DATAPROC | D37: Data Processing | E37: =IFERROR(VLOOKUP("SC4_DATAPROC",'Company 1'!$B:$E,4,0),"") -> 0 | F37: =IFERROR(VLOOKUP("SC4_DATAPROC",'Company 2'!$B:$E,4,0),"") -> 1 | G37: =IFERROR(VLOOKUP("SC4_DATAPROC",'Company 3'!$B:$E,4,0),"") -> 1 | H37: =IFERROR(VLOOKUP("SC4_DATAPROC",'Company 4'!$B:$E,4,0),"") -> 1 | I37: =IFERROR(VLOOKUP("SC4_DATAPROC",'Company 5'!$B:$E,4,0),"") -> 1 | J37: =IFERROR(VLOOKUP("SC4_DATAPROC",'Company 6'!$B:$E,4,0),"") -> 1 | K37: =IFERROR(VLOOKUP("SC4_DATAPROC",'Company 7'!$B:$E,4,0),"") -> 1 | L37: =IFERROR(VLOOKUP("SC4_DATAPROC",'Company 8'!$B:$E,4,0),"") -> 0 | M37: =IFERROR(VLOOKUP("SC4_DATAPROC",'Company 9'!$B:$E,4,0),"") -> 0 | N37: =IFERROR(VLOOKUP("SC4_DATAPROC",'Company 10'!$B:$E,4,0),"") -> 1 | O37: =IFERROR(VLOOKUP("SC4_DATAPROC",'Company 11'!$B:$E,4,0),"") -> 1 | P37: =IFERROR(VLOOKUP("SC4_DATAPROC",'Company 12'!$B:$E,4,0),"") -> 0 | Q37: =IFERROR(VLOOKUP("SC4_DATAPROC",'Company 13'!$B:$E,4,0),"") -> 1 | R37: =IFERROR(VLOOKUP("SC4_DATAPROC",#REF!,4,0),"") | S37: =IFERROR(VLOOKUP("SC4_DATAPROC",#REF!,4,0),"") | T37: =IFERROR(VLOOKUP("SC4_DATAPROC",#REF!,4,0),"") | U37: =IFERROR(VLOOKUP("SC4_DATAPROC",#REF!,4,0),"") | V37: =IFERROR(VLOOKUP("SC4_DATAPROC",'Company 18'!$B:$E,4,0),"") -> 0 | W37: =IFERROR(VLOOKUP("SC4_DATAPROC",'Company 19'!$B:$E,4,0),"") -> 0 | X37: =IFERROR(VLOOKUP("SC4_DATAPROC",'Company 20'!$B:$E,4,0),"") -> 0 | Y37: =IFERROR(VLOOKUP("SC4_DATAPROC",'Company 21'!$B:$E,4,0),"") -> 0 | Z37: =IFERROR(VLOOKUP("SC4_DATAPROC",'Company 22'!$B:$E,4,0),"") -> 0 | AA37: =IFERROR(VLOOKUP("SC4_DATAPROC",'Company 23'!$B:$E,4,0),"") -> 0 | AB37: =IFERROR(VLOOKUP("SC4_DATAPROC",'Company 24'!$B:$E,4,0),"") -> 0 | AC37: =IFERROR(VLOOKUP("SC4_DATAPROC",'Company 25'!$B:$E,4,0),"") -> 0 | AD37: =IFERROR(VLOOKUP("SC4_DATAPROC",'Company 26'!$B:$E,4,0),"") -> 0 | AE37: =IFERROR(VLOOKUP("SC4_DATAPROC",'Company 27'!$B:$E,4,0),"") -> 0 | AF37: =IFERROR(VLOOKUP("SC4_DATAPROC",'Company 28'!$B:$E,4,0),"") -> 0 | AG37: =IFERROR(VLOOKUP("SC4_DATAPROC",'Company 29'!$B:$E,4,0),"") -> 0 | AH37: =IFERROR(VLOOKUP("SC4_DATAPROC",'Company 30'!$B:$E,4,0),"") -> 0
B38: ── TOOL FEATURES ──
B39: Tool Features | C39: SF1_REALTIME | D39: Real-time exchange | E39: =IFERROR(VLOOKUP("SF1_REALTIME",'Company 1'!$B:$E,4,0),"") -> 0 | F39: =IFERROR(VLOOKUP("SF1_REALTIME",'Company 2'!$B:$E,4,0),"") -> 0 | G39: =IFERROR(VLOOKUP("SF1_REALTIME",'Company 3'!$B:$E,4,0),"") -> 1 | H39: =IFERROR(VLOOKUP("SF1_REALTIME",'Company 4'!$B:$E,4,0),"") -> 0 | I39: =IFERROR(VLOOKUP("SF1_REALTIME",'Company 5'!$B:$E,4,0),"") -> 1 | J39: =IFERROR(VLOOKUP("SF1_REALTIME",'Company 6'!$B:$E,4,0),"") -> 1 | K39: =IFERROR(VLOOKUP("SF1_REALTIME",'Company 7'!$B:$E,4,0),"") -> 1 | L39: =IFERROR(VLOOKUP("SF1_REALTIME",'Company 8'!$B:$E,4,0),"") -> 0 | M39: =IFERROR(VLOOKUP("SF1_REALTIME",'Company 9'!$B:$E,4,0),"") -> 0 | N39: =IFERROR(VLOOKUP("SF1_REALTIME",'Company 10'!$B:$E,4,0),"") -> 1 | O39: =IFERROR(VLOOKUP("SF1_REALTIME",'Company 11'!$B:$E,4,0),"") -> 0 | P39: =IFERROR(VLOOKUP("SF1_REALTIME",'Company 12'!$B:$E,4,0),"") -> 0 | Q39: =IFERROR(VLOOKUP("SF1_REALTIME",'Company 13'!$B:$E,4,0),"") -> 0 | R39: =IFERROR(VLOOKUP("SF1_REALTIME",#REF!,4,0),"") | S39: =IFERROR(VLOOKUP("SF1_REALTIME",#REF!,4,0),"") | T39: =IFERROR(VLOOKUP("SF1_REALTIME",#REF!,4,0),"") | U39: =IFERROR(VLOOKUP("SF1_REALTIME",#REF!,4,0),"") | V39: =IFERROR(VLOOKUP("SF1_REALTIME",'Company 18'!$B:$E,4,0),"") -> 0 | W39: =IFERROR(VLOOKUP("SF1_REALTIME",'Company 19'!$B:$E,4,0),"") -> 0 | X39: =IFERROR(VLOOKUP("SF1_REALTIME",'Company 20'!$B:$E,4,0),"") -> 0 | Y39: =IFERROR(VLOOKUP("SF1_REALTIME",'Company 21'!$B:$E,4,0),"") -> 0 | Z39: =IFERROR(VLOOKUP("SF1_REALTIME",'Company 22'!$B:$E,4,0),"") -> 0 | AA39: =IFERROR(VLOOKUP("SF1_REALTIME",'Company 23'!$B:$E,4,0),"") -> 0 | AB39: =IFERROR(VLOOKUP("SF1_REALTIME",'Company 24'!$B:$E,4,0),"") -> 0 | AC39: =IFERROR(VLOOKUP("SF1_REALTIME",'Company 25'!$B:$E,4,0),"") -> 0 | AD39: =IFERROR(VLOOKUP("SF1_REALTIME",'Company 26'!$B:$E,4,0),"") -> 0 | AE39: =IFERROR(VLOOKUP("SF1_REALTIME",'Company 27'!$B:$E,4,0),"") -> 0 | AF39: =IFERROR(VLOOKUP("SF1_REALTIME",'Company 28'!$B:$E,4,0),"") -> 0 | AG39: =IFERROR(VLOOKUP("SF1_REALTIME",'Company 29'!$B:$E,4,0),"") -> 0 | AH39: =IFERROR(VLOOKUP("SF1_REALTIME",'Company 30'!$B:$E,4,0),"") -> 0
B40: Tool Features | C40: SF2_ACCESS | D40: Equal access | E40: =IFERROR(VLOOKUP("SF2_ACCESS",'Company 1'!$B:$E,4,0),"") -> 0 | F40: =IFERROR(VLOOKUP("SF2_ACCESS",'Company 2'!$B:$E,4,0),"") -> 0 | G40: =IFERROR(VLOOKUP("SF2_ACCESS",'Company 3'!$B:$E,4,0),"") -> 1 | H40: =IFERROR(VLOOKUP("SF2_ACCESS",'Company 4'!$B:$E,4,0),"") -> 0 | I40: =IFERROR(VLOOKUP("SF2_ACCESS",'Company 5'!$B:$E,4,0),"") -> 0 | J40: =IFERROR(VLOOKUP("SF2_ACCESS",'Company 6'!$B:$E,4,0),"") -> 1 | K40: =IFERROR(VLOOKUP("SF2_ACCESS",'Company 7'!$B:$E,4,0),"") -> 0 | L40: =IFERROR(VLOOKUP("SF2_ACCESS",'Company 8'!$B:$E,4,0),"") -> 0 | M40: =IFERROR(VLOOKUP("SF2_ACCESS",'Company 9'!$B:$E,4,0),"") -> 1 | N40: =IFERROR(VLOOKUP("SF2_ACCESS",'Company 10'!$B:$E,4,0),"") -> 0 | O40: =IFERROR(VLOOKUP("SF2_ACCESS",'Company 11'!$B:$E,4,0),"") -> 0 | P40: =IFERROR(VLOOKUP("SF2_ACCESS",'Company 12'!$B:$E,4,0),"") -> 0 | Q40: =IFERROR(VLOOKUP("SF2_ACCESS",'Company 13'!$B:$E,4,0),"") -> 1 | R40: =IFERROR(VLOOKUP("SF2_ACCESS",#REF!,4,0),"") | S40: =IFERROR(VLOOKUP("SF2_ACCESS",#REF!,4,0),"") | T40: =IFERROR(VLOOKUP("SF2_ACCESS",#REF!,4,0),"") | U40: =IFERROR(VLOOKUP("SF2_ACCESS",#REF!,4,0),"") | V40: =IFERROR(VLOOKUP("SF2_ACCESS",'Company 18'!$B:$E,4,0),"") -> 0 | W40: =IFERROR(VLOOKUP("SF2_ACCESS",'Company 19'!$B:$E,4,0),"") -> 0 | X40: =IFERROR(VLOOKUP("SF2_ACCESS",'Company 20'!$B:$E,4,0),"") -> 0 | Y40: =IFERROR(VLOOKUP("SF2_ACCESS",'Company 21'!$B:$E,4,0),"") -> 0 | Z40: =IFERROR(VLOOKUP("SF2_ACCESS",'Company 22'!$B:$E,4,0),"") -> 0 | AA40: =IFERROR(VLOOKUP("SF2_ACCESS",'Company 23'!$B:$E,4,0),"") -> 0 | AB40: =IFERROR(VLOOKUP("SF2_ACCESS",'Company 24'!$B:$E,4,0),"") -> 0 | AC40: =IFERROR(VLOOKUP("SF2_ACCESS",'Company 25'!$B:$E,4,0),"") -> 0 | AD40: =IFERROR(VLOOKUP("SF2_ACCESS",'Company 26'!$B:$E,4,0),"") -> 0 | AE40: =IFERROR(VLOOKUP("SF2_ACCESS",'Company 27'!$B:$E,4,0),"") -> 0 | AF40: =IFERROR(VLOOKUP("SF2_ACCESS",'Company 28'!$B:$E,4,0),"") -> 0 | AG40: =IFERROR(VLOOKUP("SF2_ACCESS",'Company 29'!$B:$E,4,0),"") -> 0 | AH40: =IFERROR(VLOOKUP("SF2_ACCESS",'Company 30'!$B:$E,4,0),"") -> 0
B41: Tool Features | C41: SF3_UX | D41: Simple UX/UI | E41: =IFERROR(VLOOKUP("SF3_UX",'Company 1'!$B:$E,4,0),"") -> 0 | F41: =IFERROR(VLOOKUP("SF3_UX",'Company 2'!$B:$E,4,0),"") -> 0 | G41: =IFERROR(VLOOKUP("SF3_UX",'Company 3'!$B:$E,4,0),"") -> 0 | H41: =IFERROR(VLOOKUP("SF3_UX",'Company 4'!$B:$E,4,0),"") -> 1 | I41: =IFERROR(VLOOKUP("SF3_UX",'Company 5'!$B:$E,4,0),"") -> 1 | J41: =IFERROR(VLOOKUP("SF3_UX",'Company 6'!$B:$E,4,0),"") -> 0 | K41: =IFERROR(VLOOKUP("SF3_UX",'Company 7'!$B:$E,4,0),"") -> 1 | L41: =IFERROR(VLOOKUP("SF3_UX",'Company 8'!$B:$E,4,0),"") -> 0 | M41: =IFERROR(VLOOKUP("SF3_UX",'Company 9'!$B:$E,4,0),"") -> 1 | N41: =IFERROR(VLOOKUP("SF3_UX",'Company 10'!$B:$E,4,0),"") -> 1 | O41: =IFERROR(VLOOKUP("SF3_UX",'Company 11'!$B:$E,4,0),"") -> 1 | P41: =IFERROR(VLOOKUP("SF3_UX",'Company 12'!$B:$E,4,0),"") -> 0 | Q41: =IFERROR(VLOOKUP("SF3_UX",'Company 13'!$B:$E,4,0),"") -> 0 | R41: =IFERROR(VLOOKUP("SF3_UX",#REF!,4,0),"") | S41: =IFERROR(VLOOKUP("SF3_UX",#REF!,4,0),"") | T41: =IFERROR(VLOOKUP("SF3_UX",#REF!,4,0),"") | U41: =IFERROR(VLOOKUP("SF3_UX",#REF!,4,0),"") | V41: =IFERROR(VLOOKUP("SF3_UX",'Company 18'!$B:$E,4,0),"") -> 0 | W41: =IFERROR(VLOOKUP("SF3_UX",'Company 19'!$B:$E,4,0),"") -> 0 | X41: =IFERROR(VLOOKUP("SF3_UX",'Company 20'!$B:$E,4,0),"") -> 0 | Y41: =IFERROR(VLOOKUP("SF3_UX",'Company 21'!$B:$E,4,0),"") -> 0 | Z41: =IFERROR(VLOOKUP("SF3_UX",'Company 22'!$B:$E,4,0),"") -> 0 | AA41: =IFERROR(VLOOKUP("SF3_UX",'Company 23'!$B:$E,4,0),"") -> 0 | AB41: =IFERROR(VLOOKUP("SF3_UX",'Company 24'!$B:$E,4,0),"") -> 0 | AC41: =IFERROR(VLOOKUP("SF3_UX",'Company 25'!$B:$E,4,0),"") -> 0 | AD41: =IFERROR(VLOOKUP("SF3_UX",'Company 26'!$B:$E,4,0),"") -> 0 | AE41: =IFERROR(VLOOKUP("SF3_UX",'Company 27'!$B:$E,4,0),"") -> 0 | AF41: =IFERROR(VLOOKUP("SF3_UX",'Company 28'!$B:$E,4,0),"") -> 0 | AG41: =IFERROR(VLOOKUP("SF3_UX",'Company 29'!$B:$E,4,0),"") -> 0 | AH41: =IFERROR(VLOOKUP("SF3_UX",'Company 30'!$B:$E,4,0),"") -> 0
B42: Tool Features | C42: SF4_DECISION | D42: Joint decisions | E42: =IFERROR(VLOOKUP("SF4_DECISION",'Company 1'!$B:$E,4,0),"") -> 0 | F42: =IFERROR(VLOOKUP("SF4_DECISION",'Company 2'!$B:$E,4,0),"") -> 0 | G42: =IFERROR(VLOOKUP("SF4_DECISION",'Company 3'!$B:$E,4,0),"") -> 1 | H42: =IFERROR(VLOOKUP("SF4_DECISION",'Company 4'!$B:$E,4,0),"") -> 0 | I42: =IFERROR(VLOOKUP("SF4_DECISION",'Company 5'!$B:$E,4,0),"") -> 1 | J42: =IFERROR(VLOOKUP("SF4_DECISION",'Company 6'!$B:$E,4,0),"") -> 1 | K42: =IFERROR(VLOOKUP("SF4_DECISION",'Company 7'!$B:$E,4,0),"") -> 0 | L42: =IFERROR(VLOOKUP("SF4_DECISION",'Company 8'!$B:$E,4,0),"") -> 0 | M42: =IFERROR(VLOOKUP("SF4_DECISION",'Company 9'!$B:$E,4,0),"") -> 0 | N42: =IFERROR(VLOOKUP("SF4_DECISION",'Company 10'!$B:$E,4,0),"") -> 0 | O42: =IFERROR(VLOOKUP("SF4_DECISION",'Company 11'!$B:$E,4,0),"") -> 0 | P42: =IFERROR(VLOOKUP("SF4_DECISION",'Company 12'!$B:$E,4,0),"") -> 0 | Q42: =IFERROR(VLOOKUP("SF4_DECISION",'Company 13'!$B:$E,4,0),"") -> 1 | R42: =IFERROR(VLOOKUP("SF4_DECISION",#REF!,4,0),"") | S42: =IFERROR(VLOOKUP("SF4_DECISION",#REF!,4,0),"") | T42: =IFERROR(VLOOKUP("SF4_DECISION",#REF!,4,0),"") | U42: =IFERROR(VLOOKUP("SF4_DECISION",#REF!,4,0),"") | V42: =IFERROR(VLOOKUP("SF4_DECISION",'Company 18'!$B:$E,4,0),"") -> 0 | W42: =IFERROR(VLOOKUP("SF4_DECISION",'Company 19'!$B:$E,4,0),"") -> 0 | X42: =IFERROR(VLOOKUP("SF4_DECISION",'Company 20'!$B:$E,4,0),"") -> 0 | Y42: =IFERROR(VLOOKUP("SF4_DECISION",'Company 21'!$B:$E,4,0),"") -> 0 | Z42: =IFERROR(VLOOKUP("SF4_DECISION",'Company 22'!$B:$E,4,0),"") -> 0 | AA42: =IFERROR(VLOOKUP("SF4_DECISION",'Company 23'!$B:$E,4,0),"") -> 0 | AB42: =IFERROR(VLOOKUP("SF4_DECISION",'Company 24'!$B:$E,4,0),"") -> 0 | AC42: =IFERROR(VLOOKUP("SF4_DECISION",'Company 25'!$B:$E,4,0),"") -> 0 | AD42: =IFERROR(VLOOKUP("SF4_DECISION",'Company 26'!$B:$E,4,0),"") -> 0 | AE42: =IFERROR(VLOOKUP("SF4_DECISION",'Company 27'!$B:$E,4,0),"") -> 0 | AF42: =IFERROR(VLOOKUP("SF4_DECISION",'Company 28'!$B:$E,4,0),"") -> 0 | AG42: =IFERROR(VLOOKUP("SF4_DECISION",'Company 29'!$B:$E,4,0),"") -> 0 | AH42: =IFERROR(VLOOKUP("SF4_DECISION",'Company 30'!$B:$E,4,0),"") -> 0
B43: Tool Features | C43: SF5_MASKING | D43: Masking rules | E43: =IFERROR(VLOOKUP("SF5_MASKING",'Company 1'!$B:$E,4,0),"") -> 1 | F43: =IFERROR(VLOOKUP("SF5_MASKING",'Company 2'!$B:$E,4,0),"") -> 1 | G43: =IFERROR(VLOOKUP("SF5_MASKING",'Company 3'!$B:$E,4,0),"") -> 0 | H43: =IFERROR(VLOOKUP("SF5_MASKING",'Company 4'!$B:$E,4,0),"") -> 0 | I43: =IFERROR(VLOOKUP("SF5_MASKING",'Company 5'!$B:$E,4,0),"") -> 0 | J43: =IFERROR(VLOOKUP("SF5_MASKING",'Company 6'!$B:$E,4,0),"") -> 0 | K43: =IFERROR(VLOOKUP("SF5_MASKING",'Company 7'!$B:$E,4,0),"") -> 0 | L43: =IFERROR(VLOOKUP("SF5_MASKING",'Company 8'!$B:$E,4,0),"") -> 0 | M43: =IFERROR(VLOOKUP("SF5_MASKING",'Company 9'!$B:$E,4,0),"") -> 0 | N43: =IFERROR(VLOOKUP("SF5_MASKING",'Company 10'!$B:$E,4,0),"") -> 0 | O43: =IFERROR(VLOOKUP("SF5_MASKING",'Company 11'!$B:$E,4,0),"") -> 0 | P43: =IFERROR(VLOOKUP("SF5_MASKING",'Company 12'!$B:$E,4,0),"") -> 1 | Q43: =IFERROR(VLOOKUP("SF5_MASKING",'Company 13'!$B:$E,4,0),"") -> 1 | R43: =IFERROR(VLOOKUP("SF5_MASKING",#REF!,4,0),"") | S43: =IFERROR(VLOOKUP("SF5_MASKING",#REF!,4,0),"") | T43: =IFERROR(VLOOKUP("SF5_MASKING",#REF!,4,0),"") | U43: =IFERROR(VLOOKUP("SF5_MASKING",#REF!,4,0),"") | V43: =IFERROR(VLOOKUP("SF5_MASKING",'Company 18'!$B:$E,4,0),"") -> 0 | W43: =IFERROR(VLOOKUP("SF5_MASKING",'Company 19'!$B:$E,4,0),"") -> 0 | X43: =IFERROR(VLOOKUP("SF5_MASKING",'Company 20'!$B:$E,4,0),"") -> 0 | Y43: =IFERROR(VLOOKUP("SF5_MASKING",'Company 21'!$B:$E,4,0),"") -> 0 | Z43: =IFERROR(VLOOKUP("SF5_MASKING",'Company 22'!$B:$E,4,0),"") -> 0 | AA43: =IFERROR(VLOOKUP("SF5_MASKING",'Company 23'!$B:$E,4,0),"") -> 0 | AB43: =IFERROR(VLOOKUP("SF5_MASKING",'Company 24'!$B:$E,4,0),"") -> 0 | AC43: =IFERROR(VLOOKUP("SF5_MASKING",'Company 25'!$B:$E,4,0),"") -> 0 | AD43: =IFERROR(VLOOKUP("SF5_MASKING",'Company 26'!$B:$E,4,0),"") -> 0 | AE43: =IFERROR(VLOOKUP("SF5_MASKING",'Company 27'!$B:$E,4,0),"") -> 0 | AF43: =IFERROR(VLOOKUP("SF5_MASKING",'Company 28'!$B:$E,4,0),"") -> 0 | AG43: =IFERROR(VLOOKUP("SF5_MASKING",'Company 29'!$B:$E,4,0),"") -> 0 | AH43: =IFERROR(VLOOKUP("SF5_MASKING",'Company 30'!$B:$E,4,0),"") -> 0
B44: ── DATASETS ──
B45: Datasets | C45: SD1_TRENDS | D45: Global trends | E45: =IFERROR(VLOOKUP("SD1_TRENDS",'Company 1'!$B:$E,4,0),"") -> 1 | F45: =IFERROR(VLOOKUP("SD1_TRENDS",'Company 2'!$B:$E,4,0),"") -> 0 | G45: =IFERROR(VLOOKUP("SD1_TRENDS",'Company 3'!$B:$E,4,0),"") -> 0 | H45: =IFERROR(VLOOKUP("SD1_TRENDS",'Company 4'!$B:$E,4,0),"") -> 0 | I45: =IFERROR(VLOOKUP("SD1_TRENDS",'Company 5'!$B:$E,4,0),"") -> 0 | J45: =IFERROR(VLOOKUP("SD1_TRENDS",'Company 6'!$B:$E,4,0),"") -> 1 | K45: =IFERROR(VLOOKUP("SD1_TRENDS",'Company 7'!$B:$E,4,0),"") -> 0 | L45: =IFERROR(VLOOKUP("SD1_TRENDS",'Company 8'!$B:$E,4,0),"") -> 1 | M45: =IFERROR(VLOOKUP("SD1_TRENDS",'Company 9'!$B:$E,4,0),"") -> 1 | N45: =IFERROR(VLOOKUP("SD1_TRENDS",'Company 10'!$B:$E,4,0),"") -> 1 | O45: =IFERROR(VLOOKUP("SD1_TRENDS",'Company 11'!$B:$E,4,0),"") -> 1 | P45: =IFERROR(VLOOKUP("SD1_TRENDS",'Company 12'!$B:$E,4,0),"") -> 1 | Q45: =IFERROR(VLOOKUP("SD1_TRENDS",'Company 13'!$B:$E,4,0),"") -> 1 | R45: =IFERROR(VLOOKUP("SD1_TRENDS",#REF!,4,0),"") | S45: =IFERROR(VLOOKUP("SD1_TRENDS",#REF!,4,0),"") | T45: =IFERROR(VLOOKUP("SD1_TRENDS",#REF!,4,0),"") | U45: =IFERROR(VLOOKUP("SD1_TRENDS",#REF!,4,0),"") | V45: =IFERROR(VLOOKUP("SD1_TRENDS",'Company 18'!$B:$E,4,0),"") -> 0 | W45: =IFERROR(VLOOKUP("SD1_TRENDS",'Company 19'!$B:$E,4,0),"") -> 0 | X45: =IFERROR(VLOOKUP("SD1_TRENDS",'Company 20'!$B:$E,4,0),"") -> 0 | Y45: =IFERROR(VLOOKUP("SD1_TRENDS",'Company 21'!$B:$E,4,0),"") -> 0 | Z45: =IFERROR(VLOOKUP("SD1_TRENDS",'Company 22'!$B:$E,4,0),"") -> 0 | AA45: =IFERROR(VLOOKUP("SD1_TRENDS",'Company 23'!$B:$E,4,0),"") -> 0 | AB45: =IFERROR(VLOOKUP("SD1_TRENDS",'Company 24'!$B:$E,4,0),"") -> 0 | AC45: =IFERROR(VLOOKUP("SD1_TRENDS",'Company 25'!$B:$E,4,0),"") -> 0 | AD45: =IFERROR(VLOOKUP("SD1_TRENDS",'Company 26'!$B:$E,4,0),"") -> 0 | AE45: =IFERROR(VLOOKUP("SD1_TRENDS",'Company 27'!$B:$E,4,0),"") -> 0 | AF45: =IFERROR(VLOOKUP("SD1_TRENDS",'Company 28'!$B:$E,4,0),"") -> 0 | AG45: =IFERROR(VLOOKUP("SD1_TRENDS",'Company 29'!$B:$E,4,0),"") -> 0 | AH45: =IFERROR(VLOOKUP("SD1_TRENDS",'Company 30'!$B:$E,4,0),"") -> 0
B46: Datasets | C46: SD2_MARKET | D46: Market research | E46: =IFERROR(VLOOKUP("SD2_MARKET",'Company 1'!$B:$E,4,0),"") -> 1 | F46: =IFERROR(VLOOKUP("SD2_MARKET",'Company 2'!$B:$E,4,0),"") -> 1 | G46: =IFERROR(VLOOKUP("SD2_MARKET",'Company 3'!$B:$E,4,0),"") -> 0 | H46: =IFERROR(VLOOKUP("SD2_MARKET",'Company 4'!$B:$E,4,0),"") -> 1 | I46: =IFERROR(VLOOKUP("SD2_MARKET",'Company 5'!$B:$E,4,0),"") -> 0 | J46: =IFERROR(VLOOKUP("SD2_MARKET",'Company 6'!$B:$E,4,0),"") -> 1 | K46: =IFERROR(VLOOKUP("SD2_MARKET",'Company 7'!$B:$E,4,0),"") -> 1 | L46: =IFERROR(VLOOKUP("SD2_MARKET",'Company 8'!$B:$E,4,0),"") -> 1 | M46: =IFERROR(VLOOKUP("SD2_MARKET",'Company 9'!$B:$E,4,0),"") -> 1 | N46: =IFERROR(VLOOKUP("SD2_MARKET",'Company 10'!$B:$E,4,0),"") -> 1 | O46: =IFERROR(VLOOKUP("SD2_MARKET",'Company 11'!$B:$E,4,0),"") -> 1 | P46: =IFERROR(VLOOKUP("SD2_MARKET",'Company 12'!$B:$E,4,0),"") -> 1 | Q46: =IFERROR(VLOOKUP("SD2_MARKET",'Company 13'!$B:$E,4,0),"") -> 1 | R46: =IFERROR(VLOOKUP("SD2_MARKET",#REF!,4,0),"") | S46: =IFERROR(VLOOKUP("SD2_MARKET",#REF!,4,0),"") | T46: =IFERROR(VLOOKUP("SD2_MARKET",#REF!,4,0),"") | U46: =IFERROR(VLOOKUP("SD2_MARKET",#REF!,4,0),"") | V46: =IFERROR(VLOOKUP("SD2_MARKET",'Company 18'!$B:$E,4,0),"") -> 0 | W46: =IFERROR(VLOOKUP("SD2_MARKET",'Company 19'!$B:$E,4,0),"") -> 0 | X46: =IFERROR(VLOOKUP("SD2_MARKET",'Company 20'!$B:$E,4,0),"") -> 0 | Y46: =IFERROR(VLOOKUP("SD2_MARKET",'Company 21'!$B:$E,4,0),"") -> 0 | Z46: =IFERROR(VLOOKUP("SD2_MARKET",'Company 22'!$B:$E,4,0),"") -> 0 | AA46: =IFERROR(VLOOKUP("SD2_MARKET",'Company 23'!$B:$E,4,0),"") -> 0 | AB46: =IFERROR(VLOOKUP("SD2_MARKET",'Company 24'!$B:$E,4,0),"") -> 0 | AC46: =IFERROR(VLOOKUP("SD2_MARKET",'Company 25'!$B:$E,4,0),"") -> 0 | AD46: =IFERROR(VLOOKUP("SD2_MARKET",'Company 26'!$B:$E,4,0),"") -> 0 | AE46: =IFERROR(VLOOKUP("SD2_MARKET",'Company 27'!$B:$E,4,0),"") -> 0 | AF46: =IFERROR(VLOOKUP("SD2_MARKET",'Company 28'!$B:$E,4,0),"") -> 0 | AG46: =IFERROR(VLOOKUP("SD2_MARKET",'Company 29'!$B:$E,4,0),"") -> 0 | AH46: =IFERROR(VLOOKUP("SD2_MARKET",'Company 30'!$B:$E,4,0),"") -> 0
B47: Datasets | C47: SD3_CATEGORY | D47: Category perf. | E47: =IFERROR(VLOOKUP("SD3_CATEGORY",'Company 1'!$B:$E,4,0),"") -> 1 | F47: =IFERROR(VLOOKUP("SD3_CATEGORY",'Company 2'!$B:$E,4,0),"") -> 0 | G47: =IFERROR(VLOOKUP("SD3_CATEGORY",'Company 3'!$B:$E,4,0),"") -> 1 | H47: =IFERROR(VLOOKUP("SD3_CATEGORY",'Company 4'!$B:$E,4,0),"") -> 1 | I47: =IFERROR(VLOOKUP("SD3_CATEGORY",'Company 5'!$B:$E,4,0),"") -> 0 | J47: =IFERROR(VLOOKUP("SD3_CATEGORY",'Company 6'!$B:$E,4,0),"") -> 1 | K47: =IFERROR(VLOOKUP("SD3_CATEGORY",'Company 7'!$B:$E,4,0),"") -> 1 | L47: =IFERROR(VLOOKUP("SD3_CATEGORY",'Company 8'!$B:$E,4,0),"") -> 1 | M47: =IFERROR(VLOOKUP("SD3_CATEGORY",'Company 9'!$B:$E,4,0),"") -> 1 | N47: =IFERROR(VLOOKUP("SD3_CATEGORY",'Company 10'!$B:$E,4,0),"") -> 1 | O47: =IFERROR(VLOOKUP("SD3_CATEGORY",'Company 11'!$B:$E,4,0),"") -> 1 | P47: =IFERROR(VLOOKUP("SD3_CATEGORY",'Company 12'!$B:$E,4,0),"") -> 0 | Q47: =IFERROR(VLOOKUP("SD3_CATEGORY",'Company 13'!$B:$E,4,0),"") -> 1 | R47: =IFERROR(VLOOKUP("SD3_CATEGORY",#REF!,4,0),"") | S47: =IFERROR(VLOOKUP("SD3_CATEGORY",#REF!,4,0),"") | T47: =IFERROR(VLOOKUP("SD3_CATEGORY",#REF!,4,0),"") | U47: =IFERROR(VLOOKUP("SD3_CATEGORY",#REF!,4,0),"") | V47: =IFERROR(VLOOKUP("SD3_CATEGORY",'Company 18'!$B:$E,4,0),"") -> 0 | W47: =IFERROR(VLOOKUP("SD3_CATEGORY",'Company 19'!$B:$E,4,0),"") -> 0 | X47: =IFERROR(VLOOKUP("SD3_CATEGORY",'Company 20'!$B:$E,4,0),"") -> 0 | Y47: =IFERROR(VLOOKUP("SD3_CATEGORY",'Company 21'!$B:$E,4,0),"") -> 0 | Z47: =IFERROR(VLOOKUP("SD3_CATEGORY",'Company 22'!$B:$E,4,0),"") -> 0 | AA47: =IFERROR(VLOOKUP("SD3_CATEGORY",'Company 23'!$B:$E,4,0),"") -> 0 | AB47: =IFERROR(VLOOKUP("SD3_CATEGORY",'Company 24'!$B:$E,4,0),"") -> 0 | AC47: =IFERROR(VLOOKUP("SD3_CATEGORY",'Company 25'!$B:$E,4,0),"") -> 0 | AD47: =IFERROR(VLOOKUP("SD3_CATEGORY",'Company 26'!$B:$E,4,0),"") -> 0 | AE47: =IFERROR(VLOOKUP("SD3_CATEGORY",'Company 27'!$B:$E,4,0),"") -> 0 | AF47: =IFERROR(VLOOKUP("SD3_CATEGORY",'Company 28'!$B:$E,4,0),"") -> 0 | AG47: =IFERROR(VLOOKUP("SD3_CATEGORY",'Company 29'!$B:$E,4,0),"") -> 0 | AH47: =IFERROR(VLOOKUP("SD3_CATEGORY",'Company 30'!$B:$E,4,0),"") -> 0
B48: Datasets | C48: SD4_SHIPMENT | D48: Shipments | E48: =IFERROR(VLOOKUP("SD4_SHIPMENT",'Company 1'!$B:$E,4,0),"") -> 0 | F48: =IFERROR(VLOOKUP("SD4_SHIPMENT",'Company 2'!$B:$E,4,0),"") -> 0 | G48: =IFERROR(VLOOKUP("SD4_SHIPMENT",'Company 3'!$B:$E,4,0),"") -> 0 | H48: =IFERROR(VLOOKUP("SD4_SHIPMENT",'Company 4'!$B:$E,4,0),"") -> 1 | I48: =IFERROR(VLOOKUP("SD4_SHIPMENT",'Company 5'!$B:$E,4,0),"") -> 1 | J48: =IFERROR(VLOOKUP("SD4_SHIPMENT",'Company 6'!$B:$E,4,0),"") -> 1 | K48: =IFERROR(VLOOKUP("SD4_SHIPMENT",'Company 7'!$B:$E,4,0),"") -> 0 | L48: =IFERROR(VLOOKUP("SD4_SHIPMENT",'Company 8'!$B:$E,4,0),"") -> 0 | M48: =IFERROR(VLOOKUP("SD4_SHIPMENT",'Company 9'!$B:$E,4,0),"") -> 1 | N48: =IFERROR(VLOOKUP("SD4_SHIPMENT",'Company 10'!$B:$E,4,0),"") -> 0 | O48: =IFERROR(VLOOKUP("SD4_SHIPMENT",'Company 11'!$B:$E,4,0),"") -> 0 | P48: =IFERROR(VLOOKUP("SD4_SHIPMENT",'Company 12'!$B:$E,4,0),"") -> 1 | Q48: =IFERROR(VLOOKUP("SD4_SHIPMENT",'Company 13'!$B:$E,4,0),"") -> 1 | R48: =IFERROR(VLOOKUP("SD4_SHIPMENT",#REF!,4,0),"") | S48: =IFERROR(VLOOKUP("SD4_SHIPMENT",#REF!,4,0),"") | T48: =IFERROR(VLOOKUP("SD4_SHIPMENT",#REF!,4,0),"") | U48: =IFERROR(VLOOKUP("SD4_SHIPMENT",#REF!,4,0),"") | V48: =IFERROR(VLOOKUP("SD4_SHIPMENT",'Company 18'!$B:$E,4,0),"") -> 0 | W48: =IFERROR(VLOOKUP("SD4_SHIPMENT",'Company 19'!$B:$E,4,0),"") -> 0 | X48: =IFERROR(VLOOKUP("SD4_SHIPMENT",'Company 20'!$B:$E,4,0),"") -> 0 | Y48: =IFERROR(VLOOKUP("SD4_SHIPMENT",'Company 21'!$B:$E,4,0),"") -> 0 | Z48: =IFERROR(VLOOKUP("SD4_SHIPMENT",'Company 22'!$B:$E,4,0),"") -> 0 | AA48: =IFERROR(VLOOKUP("SD4_SHIPMENT",'Company 23'!$B:$E,4,0),"") -> 0 | AB48: =IFERROR(VLOOKUP("SD4_SHIPMENT",'Company 24'!$B:$E,4,0),"") -> 0 | AC48: =IFERROR(VLOOKUP("SD4_SHIPMENT",'Company 25'!$B:$E,4,0),"") -> 0 | AD48: =IFERROR(VLOOKUP("SD4_SHIPMENT",'Company 26'!$B:$E,4,0),"") -> 0 | AE48: =IFERROR(VLOOKUP("SD4_SHIPMENT",'Company 27'!$B:$E,4,0),"") -> 0 | AF48: =IFERROR(VLOOKUP("SD4_SHIPMENT",'Company 28'!$B:$E,4,0),"") -> 0 | AG48: =IFERROR(VLOOKUP("SD4_SHIPMENT",'Company 29'!$B:$E,4,0),"") -> 0 | AH48: =IFERROR(VLOOKUP("SD4_SHIPMENT",'Company 30'!$B:$E,4,0),"") -> 0
B49: Datasets | C49: SD5_LEAD | D49: Lead times | E49: =IFERROR(VLOOKUP("SD5_LEAD",'Company 1'!$B:$E,4,0),"") -> 0 | F49: =IFERROR(VLOOKUP("SD5_LEAD",'Company 2'!$B:$E,4,0),"") -> 0 | G49: =IFERROR(VLOOKUP("SD5_LEAD",'Company 3'!$B:$E,4,0),"") -> 0 | H49: =IFERROR(VLOOKUP("SD5_LEAD",'Company 4'!$B:$E,4,0),"") -> 1 | I49: =IFERROR(VLOOKUP("SD5_LEAD",'Company 5'!$B:$E,4,0),"") -> 1 | J49: =IFERROR(VLOOKUP("SD5_LEAD",'Company 6'!$B:$E,4,0),"") -> 0 | K49: =IFERROR(VLOOKUP("SD5_LEAD",'Company 7'!$B:$E,4,0),"") -> 0 | L49: =IFERROR(VLOOKUP("SD5_LEAD",'Company 8'!$B:$E,4,0),"") -> 0 | M49: =IFERROR(VLOOKUP("SD5_LEAD",'Company 9'!$B:$E,4,0),"") -> 0 | N49: =IFERROR(VLOOKUP("SD5_LEAD",'Company 10'!$B:$E,4,0),"") -> 0 | O49: =IFERROR(VLOOKUP("SD5_LEAD",'Company 11'!$B:$E,4,0),"") -> 0 | P49: =IFERROR(VLOOKUP("SD5_LEAD",'Company 12'!$B:$E,4,0),"") -> 0 | Q49: =IFERROR(VLOOKUP("SD5_LEAD",'Company 13'!$B:$E,4,0),"") -> 1 | R49: =IFERROR(VLOOKUP("SD5_LEAD",#REF!,4,0),"") | S49: =IFERROR(VLOOKUP("SD5_LEAD",#REF!,4,0),"") | T49: =IFERROR(VLOOKUP("SD5_LEAD",#REF!,4,0),"") | U49: =IFERROR(VLOOKUP("SD5_LEAD",#REF!,4,0),"") | V49: =IFERROR(VLOOKUP("SD5_LEAD",'Company 18'!$B:$E,4,0),"") -> 0 | W49: =IFERROR(VLOOKUP("SD5_LEAD",'Company 19'!$B:$E,4,0),"") -> 0 | X49: =IFERROR(VLOOKUP("SD5_LEAD",'Company 20'!$B:$E,4,0),"") -> 0 | Y49: =IFERROR(VLOOKUP("SD5_LEAD",'Company 21'!$B:$E,4,0),"") -> 0 | Z49: =IFERROR(VLOOKUP("SD5_LEAD",'Company 22'!$B:$E,4,0),"") -> 0 | AA49: =IFERROR(VLOOKUP("SD5_LEAD",'Company 23'!$B:$E,4,0),"") -> 0 | AB49: =IFERROR(VLOOKUP("SD5_LEAD",'Company 24'!$B:$E,4,0),"") -> 0 | AC49: =IFERROR(VLOOKUP("SD5_LEAD",'Company 25'!$B:$E,4,0),"") -> 0 | AD49: =IFERROR(VLOOKUP("SD5_LEAD",'Company 26'!$B:$E,4,0),"") -> 0 | AE49: =IFERROR(VLOOKUP("SD5_LEAD",'Company 27'!$B:$E,4,0),"") -> 0 | AF49: =IFERROR(VLOOKUP("SD5_LEAD",'Company 28'!$B:$E,4,0),"") -> 0 | AG49: =IFERROR(VLOOKUP("SD5_LEAD",'Company 29'!$B:$E,4,0),"") -> 0 | AH49: =IFERROR(VLOOKUP("SD5_LEAD",'Company 30'!$B:$E,4,0),"") -> 0
B50: Datasets | C50: SD6_CONJOINT | D50: Conjoint names | E50: =IFERROR(VLOOKUP("SD6_CONJOINT",'Company 1'!$B:$E,4,0),"") -> 0 | F50: =IFERROR(VLOOKUP("SD6_CONJOINT",'Company 2'!$B:$E,4,0),"") -> 0 | G50: =IFERROR(VLOOKUP("SD6_CONJOINT",'Company 3'!$B:$E,4,0),"") -> 0 | H50: =IFERROR(VLOOKUP("SD6_CONJOINT",'Company 4'!$B:$E,4,0),"") -> 0 | I50: =IFERROR(VLOOKUP("SD6_CONJOINT",'Company 5'!$B:$E,4,0),"") -> 0 | J50: =IFERROR(VLOOKUP("SD6_CONJOINT",'Company 6'!$B:$E,4,0),"") -> 0 | K50: =IFERROR(VLOOKUP("SD6_CONJOINT",'Company 7'!$B:$E,4,0),"") -> 0 | L50: =IFERROR(VLOOKUP("SD6_CONJOINT",'Company 8'!$B:$E,4,0),"") -> 0 | M50: =IFERROR(VLOOKUP("SD6_CONJOINT",'Company 9'!$B:$E,4,0),"") -> 0 | N50: =IFERROR(VLOOKUP("SD6_CONJOINT",'Company 10'!$B:$E,4,0),"") -> 0 | O50: =IFERROR(VLOOKUP("SD6_CONJOINT",'Company 11'!$B:$E,4,0),"") -> 0 | P50: =IFERROR(VLOOKUP("SD6_CONJOINT",'Company 12'!$B:$E,4,0),"") -> 0 | Q50: =IFERROR(VLOOKUP("SD6_CONJOINT",'Company 13'!$B:$E,4,0),"") -> 0 | R50: =IFERROR(VLOOKUP("SD6_CONJOINT",#REF!,4,0),"") | S50: =IFERROR(VLOOKUP("SD6_CONJOINT",#REF!,4,0),"") | T50: =IFERROR(VLOOKUP("SD6_CONJOINT",#REF!,4,0),"") | U50: =IFERROR(VLOOKUP("SD6_CONJOINT",#REF!,4,0),"") | V50: =IFERROR(VLOOKUP("SD6_CONJOINT",'Company 18'!$B:$E,4,0),"") -> 0 | W50: =IFERROR(VLOOKUP("SD6_CONJOINT",'Company 19'!$B:$E,4,0),"") -> 0 | X50: =IFERROR(VLOOKUP("SD6_CONJOINT",'Company 20'!$B:$E,4,0),"") -> 0 | Y50: =IFERROR(VLOOKUP("SD6_CONJOINT",'Company 21'!$B:$E,4,0),"") -> 0 | Z50: =IFERROR(VLOOKUP("SD6_CONJOINT",'Company 22'!$B:$E,4,0),"") -> 0 | AA50: =IFERROR(VLOOKUP("SD6_CONJOINT",'Company 23'!$B:$E,4,0),"") -> 0 | AB50: =IFERROR(VLOOKUP("SD6_CONJOINT",'Company 24'!$B:$E,4,0),"") -> 0 | AC50: =IFERROR(VLOOKUP("SD6_CONJOINT",'Company 25'!$B:$E,4,0),"") -> 0 | AD50: =IFERROR(VLOOKUP("SD6_CONJOINT",'Company 26'!$B:$E,4,0),"") -> 0 | AE50: =IFERROR(VLOOKUP("SD6_CONJOINT",'Company 27'!$B:$E,4,0),"") -> 0 | AF50: =IFERROR(VLOOKUP("SD6_CONJOINT",'Company 28'!$B:$E,4,0),"") -> 0 | AG50: =IFERROR(VLOOKUP("SD6_CONJOINT",'Company 29'!$B:$E,4,0),"") -> 0 | AH50: =IFERROR(VLOOKUP("SD6_CONJOINT",'Company 30'!$B:$E,4,0),"") -> 0
B52: LEGEND | C52: Baseline: 1–10 or 0/1 | Maturity: 1–5 | Sub-items: 0/1 | Use Filter View tab to filter by industry/role/country

Sheet Company 1
B1: Tom & Co — Juliette Hamer (Chief of Staff) — Int. 1
B2: Interviewee Details | C2: Response | D2: Coding | H2: Status
B3: Interviewee Name | C3: Juliette Hamer | D3: AY reviewed
B4: Interviewee Position | C4: Chief of Staff
B5: Company (Real) | C5: Tom & Co
B6: Company (Disguised) | C6: Company 1
B7: Interview Date | C7: 13/05/2026
B8: Interviewer | C8: Aysegul & Lore
B9: Interviewer Support
B10: Company Industry | C10: Specialty Retail
B11: Company Sub-Industry | C11: Specialty Retail
B12: Company Size (Turnover) | C12: 160000000
B13: Country | C13: Belgium
B15: Question ID | C15: Question
B16: ── BASELINE BLOCK ── | I16: Notes
B17: B1_INTEREST | C17: Are you interested in data collaboration? | D17: 1-10 | E17: 7 | F17: 1 = No interest — explicitly dismisses value of data collaboration | G17: 10 = Fully committed — actively seeking deeper data collaboration | H17: Take the number directly from the interviewee's answer. If a range, take midpoint. If implicit, infer from overall tone (cross-check with M9). | I17: Changing from 6 to 7 as she seemed OK to be doing collaboration if the conditions were right
B18: ↳ QUOTE | C18: "So yeah, I think it would be interesting depending on what level of data access they have... if they do have good data, I think it would be interesting to get them." "The topic is always the cost. As you know, retailers don't have the biggest margins, and so everything we can get out of a negotiation cost-wise, helps us and everything we have to give back is a bit from the bottom."
B19: B2_SHARING | C19: Do you share data currently? | D19: 0/1 | E19: 1 | F19: 0 = No — no active data sharing with any partners described | G19: 1 = Yes — any form of data sharing mentioned, even informal or ad hoc | H19: 1 = any active data sharing with partners mentioned, even informal. 0 = no sharing described whatsoever.
B20: B3_MONETIZE | C20: Do you monetize your data currently? | D20: 0/1 | E20: 1 | F20: 0 = No — data shared freely or not at all | G20: 1 = Yes — describes payment or structured value exchange for data | H20: 1 = interviewee describes receiving payment or structured value exchange. 0 = sharing is free, informal, or nonexistent.
B21: B4_STRATEGIC | C21: Do you not share/monetize due to strategic reasons? | D21: 0/1 | E21: 0 | F21: 0 = No — technical inability or simply not considered | G21: 1 = Yes — strategy or competitive sensitivity cited as PRIMARY reason for not sharing | H21: 1 = strategy/competitive sensitivity cited as primary reason. 0 = technical inability or no mention. Score 1 only if this is THE primary reason.
B22: ── DATA SHARING MATURITY (1–5) ──
B23: Question ID | C23: Question | D23: Scale | E23: SCORE | F23: Score = 1 means... | G23: Score = 5 means... | H23: Coding Guidance
B24: M1_AUTOMATED | C24: Is data sharing automated or manual? | D24: 1–5 | E24: 3 | F24: 1 = Fully manual — data pulled on request, no structured process | G24: 5 = Fully automated — data flows via API or live dashboard, no human intervention | H24: Look for HOW data is extracted and delivered. Keywords: "we pull it manually" → 1-2; "scheduled reports" → 3; "API", "live dashboard" → 4-5.
B25: M2_REALTIME | C25: Is data sharing in real-time, or lagging? | D25: 1–5 | E25: 2 | F25: 1 = Significant lag — data shared weekly/monthly or on request only | G25: 5 = Real-time — data continuously updated and immediately accessible to partners | H25: Look for time references around data freshness. "real-time", "live" → 5; "daily batch" → 3-4; "weekly report", "on request" → 1-2.
B26: M3_STRATEGIC | C26: Is data sharing focused on operations or strategic planning? | D26: 1–5 | E26: 2 | F26: 1 = Purely operational — shipments, lead times, stock levels only | G26: 5 = Fully strategic — joint planning, forecasting, category growth, market insights | H26: Look for TYPE of data discussed. Operational = logistics/inventory → 1-2. Category/benchmarks = mix → 3. Market, planning, forecasting = strategic → 4-5.
B27: M4_BREADTH | C27: Is data sharing available to all clients, or based on strategic importance? | D27: 1–5 | E27: 2 | F27: 1 = Exclusive — shared with one or very few top partners only | G27: 5 = Universal — all clients have access to same data, often via self-serve | H27: Look for LANGUAGE about who gets access. "top clients only" → 1-2; "key accounts" → 3; "all our partners", "self-serve" → 4-5.
B28: M5_DATATYPES | C28: Breadth of data exchanged | D28: 1–5 | E28: 2 | F28: 1 = Internal only — shipment schedules and lead times | G28: 5 = Full suite — global trends, market research, category performance, shipments, lead times | H28: Look for TYPES of datasets mentioned. Each additional data type moves score up. Internal → external → market-level.
B29: M6_TRUST | C29: Trust in received data | D29: 1–5 | E29: 4 | F29: 1 = No trust — always re-validates everything received from partners | G29: 5 = Full trust — uses partner data directly without independent verification | H29: Look for re-validation language. "we always check" → 1-2; "we validate some" → 3; "we take it at face value" → 4-5.
B30: M7_BARRIERS | C30: Readiness / barriers to collaborate | D30: 1–5 | E30: 3 | F30: 1 = Cannot pull data at all — no technical capability | G30: 5 = Technology is ready — strategic choice is the only barrier to sharing | H30: Look for what STOPS them from sharing more. Technical inability → 1-2. Manual process limitations → 3. Strategic/deliberate choice → 4-5.
B31: M8_IMPACT | C31: Operational impact of data gaps
B32: M9_WILLINGNESS | C32: Willingness to collaborate overall | D32: 1-10 | E32: 6 | F32: 1 = No interest — sees no value in deeper data collaboration with IMPAQTR | G32: 10 = Fully committed — actively seeking deeper data collaboration with partners | H32: SYNTHESIS score (1–10) — use across the full interview. Should align closely with B1. If B1 was explicit (e.g. 7), use that as anchor and adjust up/down based on overall tone.
B33: ── VALUE UNLOCK AREAS (0 = not mentioned / 1 = mentioned) ──
B34: Guidance | C34: 1 = interviewee explicitly mentioned this as valuable or relevant. 0 = not mentioned or actively dismissed.
B35: SV1_PRICING | C35: Pricing | D35: 0/1 | E35: 0 | F35: 0 = Did not mention | G35: 1 = Mentioned
B36: ↳ QUOTE | C36: "I will even start with basic category management because we make our decision of whether or not to continue a product or to launch a product based on what works at our stores. But we have no clue of what works elsewhere."
B37: SV2_PROMOTIONS | C37: Promotions | D37: 0/1 | E37: 0 | F37: 0 = Did not mention | G37: 1 = Mentioned
B38: SV3_SUPPLYCHAIN | C38: Supply Chain Management | D38: 0/1 | E38: 0 | F38: 0 = Did not mention | G38: 1 = Mentioned
B39: SV4_CATEGORY | C39: Category Planning | D39: 0/1 | E39: 1 | F39: 0 = Did not mention | G39: 1 = Mentioned
B40: SV5_DEMAND | C40: Demand Forecasting | D40: 0/1 | E40: 0 | F40: 0 = Did not mention | G40: 1 = Mentioned
B41: SV6_ACCOUNT | C41: Accountability | D41: 0/1 | F41: 0 = Did not mention | G41: 1 = Mentioned | H41: 1 = interviewee explicitly mentioned this as valuable or relevant. 0 = not mentioned or actively dismissed.
B42: SV7_OPS | C42: Operationalization & Workflows | D42: 0/1 | F42: 0 = Did not mention | G42: 1 = Mentioned | H42: 1 = interviewee explicitly mentioned this as valuable or relevant. 0 = not mentioned or actively dismissed.
B43: ── CONCERNS TO RESOLVE (0 = not mentioned / 1 = mentioned) ──
B44: Guidance | C44: 1 = interviewee explicitly mentioned this as valuable or relevant. 0 = not mentioned or actively dismissed.
B45: SC1_DATASENS | C45: Data Sensitivity | D45: 0/1 | E45: 1 | F45: 0 = Did not mention | G45: 1 = Mentioned | H45: Mentioned Competition
B46: SC2_COMPLIANCE | C46: Compliance | D46: 0/1 | E46: 0 | F46: 0 = Did not mention | G46: 1 = Mentioned
B47: SC3_TRUST | C47: Trust Issues | D47: 0/1 | E47: 0 | F47: 0 = Did not mention | G47: 1 = Mentioned | H47: 1 = interviewee explicitly mentioned this as valuable or relevant. 0 = not mentioned or actively dismissed.
B48: SC4_DATAPROC | C48: Data Processing | D48: 0/1 | E48: 0 | F48: 0 = Did not mention | G48: 1 = Mentioned | H48: 1 = interviewee explicitly mentioned this as valuable or relevant. 0 = not mentioned or actively dismissed.
B49: ── CRITICAL TOOL FEATURES (0 = not mentioned / 1 = mentioned) ──
B50: Guidance | C50: 1 = interviewee explicitly mentioned this as valuable or relevant. 0 = not mentioned or actively dismissed.
B51: SF1_REALTIME | C51: Dynamic, real-time data exchange | D51: 0/1 | E51: 0 | F51: 0 = Did not mention | G51: 1 = Mentioned
B52: ↳ QUOTE | C52: "I'm assuming that many of our suppliers have the exact same data sets that they want to monetize with us. But as soon as one of them gives it to us, everybody else loses."
B53: SF2_ACCESS | C53: Equal access to shared datasets | D53: 0/1 | E53: 0 | F53: 0 = Did not mention | G53: 1 = Mentioned
B54: SF3_UX | C54: Simple UX/UI | D54: 0/1 | E54: 0 | F54: 0 = Did not mention | G54: 1 = Mentioned
B55: SF4_DECISION | C55: Allows joint decision making | D55: 0/1 | E55: 0 | F55: 0 = Did not mention | G55: 1 = Mentioned
B56: SF5_MASKING | C56: Clear masking rules by supplier/user | D56: 0/1 | E56: 1 | F56: 0 = Did not mention | G56: 1 = Mentioned | H56: She mentioned that the tool would do this to make the collab process streamlined
B57: ── PREFERRED DATASETS (0 = not mentioned / 1 = mentioned) ──
B58: Guidance | C58: 1 = interviewee explicitly mentioned this as valuable or relevant. 0 = not mentioned or actively dismissed.
B59: SD1_TRENDS | C59: Global trends and insights | D59: 0/1 | E59: 1 | F59: 0 = Did not mention | G59: 1 = Mentioned
B60: SD2_MARKET | C60: Market research | D60: 0/1 | E60: 1 | F60: 0 = Did not mention | G60: 1 = Mentioned
